Workbook

Sheet 표지
F3: 에스텍 그룹
A5: 현대자동차 울산공장 정문 보안용역 도급업무
A6: 見 積 書
A7: 2027년 용역 도급 견적서 · Q U O T A T I O N
A30: 투입 인력 구성
A35: ="보안(경비) "&(N('견적서'!F28)+N('견적서'!F29)+N('견적서'!F30))&"명"&" ("&"실장 "&(N('견적서'!F28))&" · "&"팀장 "&(N('견적서'!F29))&" · "&"요원 "&(N('견적서'!F30))&")" -> 보안(경비) 13명 (실장 1 · 팀장 3 · 요원 9)
B37: 수 신 | D37: 현대자동차 울산공장 정문 貴中
B38: 용 역 명 | D38: 보안용역 도급업무
B39: 용역기간 | D39: 2027. 1. 1 ~ 2027. 12. 31 (12개월)
B40: 견적금액 | D40: ="월 "&TEXT('견적서'!I31,"#,##0")&"원 (VAT 별도) · "&'견적서'!F31&"명" -> 월 56,928,000원 (VAT 별도) · 13명
B41: 견적기준 | D41: 2027년 최저임금 10,700원 · 4대보험 법정요율
A43: 2026년 10월
F45: ㈜에스텍시스템 에스텍 그룹
A47: 서울특별시 강남구 개포로 619, 8층(개포동, 서울강남우체국청사) ·

Sheet 견적서
D1: 견 적 서 | I1: No. 261021-2703
I2: 작성일 2026. 10. 21
D3: Q U O T A T I O N
A7: 현대자동차 울산공장 정문 貴中 | F7: 등록번호 | G7: 202-81-62708
A8: 용 역 명 | C8: 보안용역 도급업무 | F8: 상 호 | G8: ㈜에스텍시스템 | H8: 대 표 | I8: 이병화 (인)
A9: 용역기간 | C9: 2027. 1. 1 ~ 2027. 12. 31 (12개월) | F9: 주 소 | G9: 서울특별시 강남구 개포로 619, 8층(개포동, 서울강남우체국청사)
A10: 유효기간 | C10: 작성일로부터 1개월 | F10: 업 태 | G10: 서비스 | H10: 종 목 | I10: 시설경비·신변보호·기계경비·호송경비, 건물(시설)관리용역, 위생관리, 주차관리
A11: 사 업 장 | C11: 울산 북구 염포로 700 | F11: 허가·신고
A12: 귀사의 무궁한 발전을 기원하며, 아래와 같이 견적합니다. | F12: 담 당 | G12: 에스텍 그룹
A14: 견적금액 · 월 (VAT 별도) | G14: ="부가세 포함 월 "&TEXT(I33,"#,##0")&"원 · "&F31&"명 / 평균 "&TEXT(IF(N(F31)=0,0,SUM(I28:I30)/F31),"#,##0")&"원" -> 부가세 포함 월 62,620,800원 · 13명 / 평균 4,379,077원
A15: =I31 -> 56928000 | D15: ="일금 "&IF(ROUND(ABS(N(I31)),0)=0,"영",CHOOSE(VALUE(MID(TEXT(ROUND(ABS(N(I31)),0),"000000000000"),1,1))+1,"","일","이","삼","사","오","육","칠","팔","구")&IF(MID(TEXT(ROUND(ABS(N(I31)),0),"000000000000"),1,1)="0","","천")&CHOOSE(VALUE(MID(TEXT(ROUND(ABS(N(I31)),0),"000000000000"),2,1))+1,"","일","이","삼","사","오","육","칠","팔","구")&IF(MID(TEXT(ROUND(ABS(N(I31)),0),"000000000000"),2,1)="0","","백")&CHOOSE(VALUE(MID(TEXT(ROUND(ABS(N(I31)),0),"000000000000"),3,1))+1,"","일","이","삼","사","오","육","칠","팔","구")&IF(MID(TEXT(ROUND(ABS(N(I31)),0),"000000000000"),3,1)="0","","십")&CHOOSE(VALUE(MID(TEXT(ROUND(ABS(N(I31)),0),"000000000000"),4,1))+1,"","일","이","삼","사","오","육","칠","팔","구")&IF(MID(TEXT(ROUND(ABS(N(I31)),0),"000000000000"),4,1)="0","","")&IF(MID(TEXT(ROUND(ABS(N(I31)),0),"000000000000"),1,4)="0000","","억")&CHOOSE(VALUE(MID(TEXT(ROUND(ABS(N(I31)),0),"000000000000"),5,1))+1,"","일","이","삼","사","오","육","칠","팔","구")&IF(MID(TEXT(ROUND(ABS(N(I31)),0),"000000000000"),5,1)="0","","천")&CHOOSE(VALUE(MID(TEXT(ROUND(ABS(N(I31)),0),"000000000000"),6,1))+1,"","일","이","삼","사","오","육","칠","팔","구")&IF(MID(TEXT(ROUND(ABS(N(I31)),0),"000000000000"),6,1)="0","","백")&CHOOSE(VALUE(MID(TEXT(ROUND(ABS(N(I31)),0),"000000000000"),7,1))+1,"","일","이","삼","사","오","육","칠","팔","구")&IF(MID(TEXT(ROUND(ABS(N(I31)),0),"000000000000"),7,1)="0","","십")&CHOOSE(VALUE(MID(TEXT(ROUND(ABS(N(I31)),0),"000000000000"),8,1))+1,"","일","이","삼","사","오","육","칠","팔","구")&IF(MID(TEXT(ROUND(ABS(N(I31)),0),"000000000000"),8,1)="0","","")&IF(MID(TEXT(ROUND(ABS(N(I31)),0),"000000000000"),5,4)="0000","","만")&CHOOSE(VALUE(MID(TEXT(ROUND(ABS(N(I31)),0),"000000000000"),9,1))+1,"","일","이","삼","사","오","육","칠","팔","구")&IF(MID(TEXT(ROUND(ABS(N(I31)),0),"000000000000"),9,1)="0","","천")&CHOOSE(VALUE(MID(TEXT(ROUND(ABS(N(I31)),0),"000000000000"),10,1))+1,"","일","이","삼","사","오","육","칠","팔","구")&IF(MID(TEXT(ROUND(ABS(N(I31)),0),"000000000000"),10,1)="0","","백")&CHOOSE(VALUE(MID(TEXT(ROUND(ABS(N(I31)),0),"000000000000"),11,1))+1,"","일","이","삼","사","오","육","칠","팔","구")&IF(MID(TEXT(ROUND(ABS(N(I31)),0),"000000000000"),11,1)="0","","십")&CHOOSE(VALUE(MID(TEXT(ROUND(ABS(N(I31)),0),"000000000000"),12,1))+1,"","일","이","삼","사","오","육","칠","팔","구")&IF(MID(TEXT(ROUND(ABS(N(I31)),0),"000000000000"),12,1)="0","",""))&"원정" -> 일금 오천육백구십이만팔천원정 | G15: ="계약기간 12개월 총액 "&TEXT(I34,"#,##0")&"원 (VAT 별도)" -> 계약기간 12개월 총액 683,136,000원 (VAT 별도)
A17: ■ 투입 인력 구성
A22: ="보안(경비) "&(N(F28)+N(F29)+N(F30))&"명" -> 보안(경비) 13명
A23: ="실장 "&(N(F28))&" · "&"팀장 "&(N(F29))&" · "&"요원 "&(N(F30)) -> 실장 1 · 팀장 3 · 요원 9
A24: ="월 "&TEXT(N(I28)+N(I29)+N(I30),"#,##0")&"원" -> 월 56,928,000원
A26: ■ 견적 내역 | J26: (단위: 명, 원 / VAT 별도)
A27: No | B27: 직종 | C27: 직책 | D27: 근무지·직무 | E27: 운영형태 | F27: 인원 | H27: 2027년 단가 | I27: 월 합계 | J27: 비고
A28: 1 | B28: 보안 | C28: 실장 | E28: 주간 주5일 (11h·연장3h/일) | F28: ='산출내역서'!C10 -> 1 | H28: ='산출내역서'!C67 -> 4794000 | I28: =F28*H28 -> 4794000
A29: 2 | B29: 보안 | C29: 팀장 | E29: 주간 주5일 (11h·연장3h/일) | F29: ='산출내역서'!D10 -> 3 | H29: ='산출내역서'!D67 -> 4517000 | I29: =F29*H29 -> 13551000
A30: 3 | B30: 보안 | C30: 요원 | E30: 3조2교대 (12h) | F30: ='산출내역서'!E10 -> 9 | H30: ='산출내역서'!E67 -> 4287000 | I30: =F30*H30 -> 38583000
A31: 월 합계 | F31: =SUM(F28:F30) -> 13 | I31: =SUM(I28:I30) -> 56928000
A32: 부가가치세 (10%) | I32: =ROUND(I31*0.1,0) -> 5692800
A33: 월 총계 (VAT 포함) | I33: =I31+I32 -> 62620800
A34: 계약기간 총액 (VAT 별도 · 12개월) | I34: =I31*12 -> 683136000
A36: ■ 견적 조건
A37: ○ 견적 기준 : 2027년 최저임금(10,700원) 및 통상시급 적용
A38: 단, 매년 법정최저임금(4대보험 포함) 등 관계법령이 변경될 경우 그 즉시 변경된 내용에 따라 적용합니다.
A39: ○ 납입 조건 : 전자세금계산서 발행(당월 20일 청구, 익월 5일 납입, 현금결제)
A40: ○ 손해배상 : 총 2억원 (당사의 귀책사유로 인한 사고 발생시 손해배상 책임보험에 의거)
A41: 1) 대인배상 : 1인 2천만원 한도 총 1억원(1사고당), 2) 대물배상 : 1억원한도(사고당)
A42: ○ 상기 금액은 피복, 장비, 복리후생 등 포함한 금액입니다.
A43: ○ 업무 수행에 필요한 근무실, 휴게실, 청소용품(소모품 포함), 집기류, 통신, 식사는 고객사 제공조건
C46: ㈜에스텍시스템 · 에스텍 그룹 서울특별시 강남구 개포로 619, 8층(개포동, 서울강남우체국청사)

Sheet 산출내역서
D1: 2027년 현대자동차 울산공장 정문 산출내역서 | H1: No. 261021-2703
H2: 작성일 2026. 10. 21
D3: 보안용역 도급업무 · 용역기간 2027. 1. 1 ~ 2027. 12. 31 (12개월) · 단위: 원, VAT 별도 · 노란 칸 = 입력값(수정 시 자동 재계산)
A7: 구 분 | C7: 보안 | D7: 보안 | E7: 보안 | F7: 월간총액 | G7: 평균단가 | H7: 계약기간 계 | I7: 산출 근거 (수식)
C8: 실장 | D8: 팀장 | E8: 요원
C9: 주간 주5일 | D9: 주간 주5일 | E9: 3조2교대
A10: 기초자료 | B10: 인원(명) | C10: 1 | D10: 3 | E10: 9 | F10: =SUM(C10:E10) -> 13 | I10: 입력값
B11: 시급 | C11: 10700 | D11: 10700 | E11: 10700 | I11: 입력값
B12: 기본시간(주휴포함) | C12: 209 | D12: 209 | E12: 209 | I12: 입력값
B13: 연장근로시간 | C13: 65 | D13: 65 | E13: 25 | I13: 입력값
B14: 야간근로시간 | C14: 0 | D14: 0 | E14: 82 | I14: 입력값
B15: 공휴일근무(일/년) | C15: 0 | D15: 0 | E15: 0 | I15: 입력값
B16: 연차적치일수 | C16: 15 | D16: 15 | E16: 15 | I16: 입력값
B17: 상여율(연, 기본급 대비) | C17: 0 | D17: 0 | E17: 0 | I17: 입력값
B18: 상여 기준(0=기본급,1=통상임금) | C18: 0 | D18: 0 | E18: 0 | I18: 입력값
B19: 근로자의날 유급시간 | C19: 11 | D19: 11 | E19: 11 | I19: 입력값
B20: 감시단속(1=승인) | C20: 1 | D20: 1 | E20: 1 | I20: 입력값
B21: 퇴직충당금(1=반영) | C21: 1 | D21: 1 | E21: 1 | I21: 입력값
B22: 국민연금 적용률 | C22: 1 | D22: 1 | E22: 1 | I22: 입력값
... B25: 연간 근무개월 | C25: 12 | D25: 12 | E25: 12 | I25: 입력값
B26: 통상시급 | C26: =IF(C12=0,0,(C27+C30+C34+C32)/C12) -> 13092.344 | D26: =IF(D12=0,0,(D27+D30+D34+D32)/D12) -> 12135.407 | E26: =IF(E12=0,0,(E27+E30+E34+E32)/E12) -> 11178.469
A27: 직접인건비 | B27: 기본급여 | C27: =ROUNDUP(C12*C11,-1) -> 2236300 | D27: =ROUNDUP(D12*D11,-1) -> 2236300 | E27: =ROUNDUP(E12*E11,-1) -> 2236300 | F27: =SUMPRODUCT(C27:E27,C10:E10) -> 29071900 | G27: =IF($C$96=0,0,F27/$C$96) -> 2236300 | H27: =SUMPRODUCT(C27:E27,C10:E10,C25:E25) -> 348862800 | I27: ROUNDUP(시급 × 기본시간, -1)
B28: 연장근로수당 | C28: =IF(C13=0,0,ROUNDUP(C13*IF(C20=1,C11*$C$81,C26*$C$80),-1)) -> 695500 | D28: =IF(D13=0,0,ROUNDUP(D13*IF(D20=1,D11*$C$81,D26*$C$80),-1)) -> 695500 | E28: =IF(E13=0,0,ROUNDUP(E13*IF(E20=1,E11*$C$81,E26*$C$80),-1)) -> 267500 | F28: =SUMPRODUCT(C28:E28,C10:E10) -> 5189500 | G28: =IF($C$96=0,0,F28/$C$96) -> 399192.31 | H28: =SUMPRODUCT(C28:E28,C10:E10,C25:E25) -> 62274000 | I28: 감시단속: 시급×배율 / 일반: 통상시급×1.5 × 연장시간
B29: 야간가산수당 | C29: =ROUNDUP(C14*$C$82*C26,-1) -> 0 | D29: =ROUNDUP(D14*$C$82*D26,-1) -> 0 | E29: =ROUNDUP(E14*$C$82*E26,-1) -> 458320 | F29: =SUMPRODUCT(C29:E29,C10:E10) -> 4124880 | G29: =IF($C$96=0,0,F29/$C$96) -> 317298.46 | H29: =SUMPRODUCT(C29:E29,C10:E10,C25:E25) -> 49498560 | I29: ROUNDUP(야간근로시간 × 가산율 × 통상시급, -1)
B30: 직책수당 | C30: 0 | D30: 0 | E30: 0 | F30: =SUMPRODUCT(C30:E30,C10:E10) -> 0 | G30: =IF($C$96=0,0,F30/$C$96) -> 0 | H30: =SUMPRODUCT(C30:E30,C10:E10,C25:E25) -> 0
B31: 공휴일근무수당 | C31: =IF(C15=0,0,ROUNDUP(C11*C15*8*0.5/12,-1)) -> 0 | D31: =IF(D15=0,0,ROUNDUP(D11*D15*8*0.5/12,-1)) -> 0 | E31: =IF(E15=0,0,ROUNDUP(E11*E15*8*0.5/12,-1)) -> 0 | F31: =SUMPRODUCT(C31:E31,C10:E10) -> 0 | G31: =IF($C$96=0,0,F31/$C$96) -> 0 | H31: =SUMPRODUCT(C31:E31,C10:E10,C25:E25) -> 0 | I31: 시급 × 공휴일수 × 8h × 50% ÷ 12
B32: 직무수당 | C32: 500000 | D32: 300000 | E32: 0 | F32: =SUMPRODUCT(C32:E32,C10:E10) -> 1400000 | G32: =IF($C$96=0,0,F32/$C$96) -> 107692.31 | H32: =SUMPRODUCT(C32:E32,C10:E10,C25:E25) -> 16800000
B33: 식대(비과세) | C33: 0 | D33: 0 | E33: 0 | F33: =SUMPRODUCT(C33:E33,C10:E10) -> 0 | G33: =IF($C$96=0,0,F33/$C$96) -> 0 | H33: =SUMPRODUCT(C33:E33,C10:E10,C25:E25) -> 0
B34: 조정수당 | C34: 0 | D34: 0 | E34: 100000 | F34: =SUMPRODUCT(C34:E34,C10:E10) -> 900000 | G34: =IF($C$96=0,0,F34/$C$96) -> 69230.769 | H34: =SUMPRODUCT(C34:E34,C10:E10,C25:E25) -> 10800000
B35: 소 계 | C35: =SUM(C27:C34) -> 3431800 | D35: =SUM(D27:D34) -> 3231800 | E35: =SUM(E27:E34) -> 3062120 | F35: =SUMPRODUCT(C35:E35,C10:E10) -> 40686280 | G35: =IF($C$96=0,0,F35/$C$96) -> 3129713.8 | H35: =SUMPRODUCT(C35:E35,C10:E10,C25:E25) -> 488235360 | I35: 기본급여 ~ 조정수당 합계
B36: 연차수당(적치) | C36: =ROUNDUP(C26*$C$83*C16/12,-1) -> 130930 | D36: =ROUNDUP(D26*$C$83*D16/12,-1) -> 121360 | E36: =ROUNDUP(E26*$C$83*E16/12,-1) -> 111790 | F36: =SUMPRODUCT(C36:E36,C10:E10) -> 1501120 | G36: =IF($C$96=0,0,F36/$C$96) -> 115470.77 | H36: =SUMPRODUCT(C36:E36,C10:E10,C25:E25) -> 18013440 | I36: ROUNDUP(통상시급 × 연차1일시간 × 적치일수 ÷ 12, -1)
B37: 근로자의날 | C37: =ROUNDUP(C19/12*C26,-1) -> 12010 | D37: =ROUNDUP(D19/12*D26,-1) -> 11130 | E37: =ROUNDUP(E19/12*E26,-1) -> 10250 | F37: =SUMPRODUCT(C37:E37,C10:E10) -> 137650 | G37: =IF($C$96=0,0,F37/$C$96) -> 10588.462 | H37: =SUMPRODUCT(C37:E37,C10:E10,C25:E25) -> 1651800 | I37: ROUNDUP(유급시간 ÷ 12 × 통상시급, -1)
B38: 상여금 | C38: =IF(C17=0,0,ROUNDUP(IF(C18=1,C27+C30+C34+C32,C27)*C17/12,-1)) -> 0 | D38: =IF(D17=0,0,ROUNDUP(IF(D18=1,D27+D30+D34+D32,D27)*D17/12,-1)) -> 0 | E38: =IF(E17=0,0,ROUNDUP(IF(E18=1,E27+E30+E34+E32,E27)*E17/12,-1)) -> 0 | F38: =SUMPRODUCT(C38:E38,C10:E10) -> 0 | G38: =IF($C$96=0,0,F38/$C$96) -> 0 | H38: =SUMPRODUCT(C38:E38,C10:E10,C25:E25) -> 0 | I38: ROUNDUP(기본급(또는 통상임금) × 상여율 ÷ 12, -1)
B39: 퇴직충당금 | C39: =IF(C21=1,ROUNDUP((C35+C36+C37+C38)/12,-1),0) -> 297900 | D39: =IF(D21=1,ROUNDUP((D35+D36+D37+D38)/12,-1),0) -> 280360 | E39: =IF(E21=1,ROUNDUP((E35+E36+E37+E38)/12,-1),0) -> 265350 | F39: =SUMPRODUCT(C39:E39,C10:E10) -> 3527130 | G39: =IF($C$96=0,0,F39/$C$96) -> 271317.69 | H39: =SUMPRODUCT(C39:E39,C10:E10,C25:E25) -> 42325560 | I39: ROUNDUP((소계+연차+근로자의날+상여금) ÷ 12, -1)
B40: 직접비 계 ① | C40: =C35+C36+C37+C38+C39 -> 3872640 | D40: =D35+D36+D37+D38+D39 -> 3644650 | E40: =E35+E36+E37+E38+E39 -> 3449510 | F40: =SUMPRODUCT(C40:E40,C10:E10) -> 45852180 | G40: =IF($C$96=0,0,F40/$C$96) -> 3527090.8 | H40: =SUMPRODUCT(C40:E40,C10:E10,C25:E25) -> 550226160 | I40: 소계 + 연차 + 근로자의날 + 상여금 + 퇴직충당금
A41: 간접인건비 | B41: 건강보험료 | C41: =ROUNDUP((C40-C39-C33)*$C$73,-1) -> 128520 | D41: =ROUNDUP((D40-D39-D33)*$C$73,-1) -> 120950 | E41: =ROUNDUP((E40-E39-E33)*$C$73,-1) -> 114480 | F41: =SUMPRODUCT(C41:E41,C10:E10) -> 1521690 | G41: =IF($C$96=0,0,F41/$C$96) -> 117053.08 | H41: =SUMPRODUCT(C41:E41,C10:E10,C25:E25) -> 18260280 | I41: ROUNDUP((직접비 계 − 퇴직충당금 − 식대) × 건강보험요율, -1)
B42: 노인장기요양보험 | C42: =ROUNDUP(C41*$C$74,-1) -> 16890 | D42: =ROUNDUP(D41*$C$74,-1) -> 15900 | E42: =ROUNDUP(E41*$C$74,-1) -> 15050 | F42: =SUMPRODUCT(C42:E42,C10:E10) -> 200040 | G42: =IF($C$96=0,0,F42/$C$96) -> 15387.692 | H42: =SUMPRODUCT(C42:E42,C10:E10,C25:E25) -> 2400480 | I42: ROUNDUP(건강보험료 × 장기요양요율, -1)
B43: 국민연금 | C43: =ROUNDUP((C40-C39-C33)*$C$75*C22,-1) -> 178740 | D43: =ROUNDUP((D40-D39-D33)*$C$75*D22,-1) -> 168220 | E43: =ROUNDUP((E40-E39-E33)*$C$75*E22,-1) -> 159210 | F43: =SUMPRODUCT(C43:E43,C10:E10) -> 2116290 | G43: =IF($C$96=0,0,F43/$C$96) -> 162791.54 | H43: =SUMPRODUCT(C43:E43,C10:E10,C25:E25) -> 25395480 | I43: ROUNDUP((직접비−퇴직−식대) × 국민연금요율 × 적용률, -1)
B44: 고용보험료 | C44: =ROUNDUP((C40-C39-C33)*$C$76,-1) -> 66140 | D44: =ROUNDUP((D40-D39-D33)*$C$76,-1) -> 62240 | E44: =ROUNDUP((E40-E39-E33)*$C$76,-1) -> 58910 | F44: =SUMPRODUCT(C44:E44,C10:E10) -> 783050 | G44: =IF($C$96=0,0,F44/$C$96) -> 60234.615 | H44: =SUMPRODUCT(C44:E44,C10:E10,C25:E25) -> 9396600 | I44: ROUNDUP((직접비−퇴직−식대) × 고용보험요율, -1)
B45: 산재보험료 | C45: =ROUNDUP((C40-C39-C33)*$C$77,-1) -> 30750 | D45: =ROUNDUP((D40-D39-D33)*$C$77,-1) -> 28940 | E45: =ROUNDUP((E40-E39-E33)*$C$77,-1) -> 27390 | F45: =SUMPRODUCT(C45:E45,C10:E10) -> 364080 | G45: =IF($C$96=0,0,F45/$C$96) -> 28006.154 | H45: =SUMPRODUCT(C45:E45,C10:E10,C25:E25) -> 4368960 | I45: ROUNDUP((직접비−퇴직−식대) × 산재보험요율, -1)
B46: 임금채권부담금 | C46: =ROUNDUP((C40-C39-C33)*$C$78,-1) -> 3220 | D46: =ROUNDUP((D40-D39-D33)*$C$78,-1) -> 3030 | E46: =ROUNDUP((E40-E39-E33)*$C$78,-1) -> 2870 | F46: =SUMPRODUCT(C46:E46,C10:E10) -> 38140 | G46: =IF($C$96=0,0,F46/$C$96) -> 2933.8462 | H46: =SUMPRODUCT(C46:E46,C10:E10,C25:E25) -> 457680 | I46: ROUNDUP((직접비−퇴직−식대) × 임금채권요율, -1)
B47: 석면피해구제분담금 | C47: =IF($C$79=0,0,ROUNDUP((C40-C39-C33)*$C$79,-1)) -> 220 | D47: =IF($C$79=0,0,ROUNDUP((D40-D39-D33)*$C$79,-1)) -> 210 | E47: =IF($C$79=0,0,ROUNDUP((E40-E39-E33)*$C$79,-1)) -> 200 | F47: =SUMPRODUCT(C47:E47,C10:E10) -> 2650 | G47: =IF($C$96=0,0,F47/$C$96) -> 203.84615 | H47: =SUMPRODUCT(C47:E47,C10:E10,C25:E25) -> 31800 | I47: ROUNDUP((직접비−퇴직−식대) × 석면요율, -1)
B48: 특수건강검진 | C48: =IF(C23=1,ROUNDUP($C$84/12,-1),0) -> 0 | D48: =IF(D23=1,ROUNDUP($C$84/12,-1),0) -> 0 | E48: =IF(E23=1,ROUNDUP($C$84/12,-1),0) -> 6670 | F48: =SUMPRODUCT(C48:E48,C10:E10) -> 60030 | G48: =IF($C$96=0,0,F48/$C$96) -> 4617.6923 | H48: =SUMPRODUCT(C48:E48,C10:E10,C25:E25) -> 720360 | I48: ROUNDUP(연 검진비 ÷ 12, -1)
B49: 장애인고용부담금 | C49: =IF($C$85=1,ROUNDUP($C$86*$C$87*$C$88,-1),0) -> 42160 | D49: =IF($C$85=1,ROUNDUP($C$86*$C$87*$C$88,-1),0) -> 42160 | E49: =IF($C$85=1,ROUNDUP($C$86*$C$87*$C$88,-1),0) -> 42160 | F49: =SUMPRODUCT(C49:E49,C10:E10) -> 548080 | G49: =IF($C$96=0,0,F49/$C$96) -> 42160 | H49: =SUMPRODUCT(C49:E49,C10:E10,C25:E25) -> 6576960 | I49: ROUNDUP(의무고용률 × 부담기초액 × 반영률, -1)
B50: 간접비 계 ② | C50: =SUM(C41:C49) -> 466640 | D50: =SUM(D41:D49) -> 441650 | E50: =SUM(E41:E49) -> 426940 | F50: =SUMPRODUCT(C50:E50,C10:E10) -> 5634050 | G50: =IF($C$96=0,0,F50/$C$96) -> 433388.46 | H50: =SUMPRODUCT(C50:E50,C10:E10,C25:E25) -> 67608600 | I50: 건강보험 ~ 장애인부담금 합계
B51: 노무비 계 (1) | C51: =C40+C50 -> 4339280 | D51: =D40+D50 -> 4086300 | E51: =E40+E50 -> 3876450 | F51: =SUMPRODUCT(C51:E51,C10:E10) -> 51486230 | G51: =IF($C$96=0,0,F51/$C$96) -> 3960479.2 | H51: =SUMPRODUCT(C51:E51,C10:E10,C25:E25) -> 617834760 | I51: 직접비 ① + 간접비 ②
A52: 경비 | B52: 피복장구비 | C52: 30000 | D52: 30000 | E52: 30000 | F52: =SUMPRODUCT(C52:E52,C10:E10) -> 390000 | G52: =IF($C$96=0,0,F52/$C$96) -> 30000 | H52: =SUMPRODUCT(C52:E52,C10:E10,C25:E25) -> 4680000
B53: 직원선물대 | C53: =IF($C$89=0,0,ROUNDUP($C$89/12,-1)) -> 8340 | D53: =IF($C$89=0,0,ROUNDUP($C$89/12,-1)) -> 8340 | E53: =IF($C$89=0,0,ROUNDUP($C$89/12,-1)) -> 8340 | F53: =SUMPRODUCT(C53:E53,C10:E10) -> 108420 | G53: =IF($C$96=0,0,F53/$C$96) -> 8340 | H53: =SUMPRODUCT(C53:E53,C10:E10,C25:E25) -> 1301040 | I53: ROUNDUP(명절선물 ÷ 12, -1)
B54: 직원회의비 | C54: =$C$90 -> 10000 | D54: =$C$90 -> 10000 | E54: =$C$90 -> 10000 | F54: =SUMPRODUCT(C54:E54,C10:E10) -> 130000 | G54: =IF($C$96=0,0,F54/$C$96) -> 10000 | H54: =SUMPRODUCT(C54:E54,C10:E10,C25:E25) -> 1560000
B55: 경조비 | C55: =$C$91 -> 4000 | D55: =$C$91 -> 4000 | E55: =$C$91 -> 4000 | F55: =SUMPRODUCT(C55:E55,C10:E10) -> 52000 | G55: =IF($C$96=0,0,F55/$C$96) -> 4000 | H55: =SUMPRODUCT(C55:E55,C10:E10,C25:E25) -> 624000
B56: 대치근무비 | C56: =C26*$C$92*$C$93/12 -> 23566.22 | D56: =D26*$C$92*$C$93/12 -> 21843.732 | E56: =E26*$C$92*$C$93/12 -> 20121.244 | F56: =SUMPRODUCT(C56:E56,C10:E10) -> 270188.61 | G56: =IF($C$96=0,0,F56/$C$96) -> 20783.739 | H56: =SUMPRODUCT(C56:E56,C10:E10,C25:E25) -> 3242263.3 | I56: 통상시급 × 기준시간 × 대치일수 ÷ 12
B57: 주민세(사업소분) | C57: =IF($C$96=0,0,$C$94*$C$95/12/$C$96) -> 400.64103 | D57: =IF($C$96=0,0,$C$94*$C$95/12/$C$96) -> 400.64103 | E57: =IF($C$96=0,0,$C$94*$C$95/12/$C$96) -> 400.64103 | F57: =SUMPRODUCT(C57:E57,C10:E10) -> 5208.3333 | G57: =IF($C$96=0,0,F57/$C$96) -> 400.64103 | H57: =SUMPRODUCT(C57:E57,C10:E10,C25:E25) -> 62500 | I57: 주민세 × 개소 ÷ 12 ÷ 총인원
B58: 교육훈련비 | C58: =IF($C$98>0,$C$98,C51*$C$97) -> 43392.8 | D58: =IF($C$98>0,$C$98,D51*$C$97) -> 40863 | E58: =IF($C$98>0,$C$98,E51*$C$97) -> 38764.5 | F58: =SUMPRODUCT(C58:E58,C10:E10) -> 514862.3 | G58: =IF($C$96=0,0,F58/$C$96) -> 39604.792 | H58: =SUMPRODUCT(C58:E58,C10:E10,C25:E25) -> 6178347.6 | I58: 고정액 또는 노무비 × 교육훈련비율
B59: 위험부담금 | C59: =IF($C$100>0,$C$100,C51*$C$99) -> 21696.4 | D59: =IF($C$100>0,$C$100,D51*$C$99) -> 20431.5 | E59: =IF($C$100>0,$C$100,E51*$C$99) -> 19382.25 | F59: =SUMPRODUCT(C59:E59,C10:E10) -> 257431.15 | G59: =IF($C$96=0,0,F59/$C$96) -> 19802.396 | H59: =SUMPRODUCT(C59:E59,C10:E10,C25:E25) -> 3089173.8 | I59: 고정액 또는 노무비 × 위험부담율
B60: 부대비용 배분 | C60: =IF(OR($C$101=0,C24=1,$C$103=0),0,$C$102/$C$103) -> 0 | D60: =IF(OR($C$101=0,D24=1,$C$103=0),0,$C$102/$C$103) -> 0 | E60: =IF(OR($C$101=0,E24=1,$C$103=0),0,$C$102/$C$103) -> 0 | F60: =SUMPRODUCT(C60:E60,C10:E10) -> 0 | G60: =IF($C$96=0,0,F60/$C$96) -> 0 | H60: =SUMPRODUCT(C60:E60,C10:E10,C25:E25) -> 0 | I60: 부대비용 월계 ÷ 배분 인원
B61: 경비 계 (2) | C61: =SUM(C52:C60) -> 141396.06 | D61: =SUM(D52:D60) -> 135878.87 | E61: =SUM(E52:E60) -> 131008.64 | F61: =SUMPRODUCT(C61:E61,C10:E10) -> 1728110.4 | G61: =IF($C$96=0,0,F61/$C$96) -> 132931.57 | H61: =SUMPRODUCT(C61:E61,C10:E10,C25:E25) -> 20737325 | I61: 피복 ~ 부대비용 합계
A62: 원가 | B62: 1. 직접원가 | C62: =C51+C61 -> 4480676.1 | D62: =D51+D61 -> 4222178.9 | E62: =E51+E61 -> 4007458.6 | F62: =SUMPRODUCT(C62:E62,C10:E10) -> 53214340 | G62: =IF($C$96=0,0,F62/$C$96) -> 4093410.8 | H62: =SUMPRODUCT(C62:E62,C10:E10,C25:E25) -> 6.3857208e+08 | I62: 노무비 (1) + 경비 (2)
B63: 2. 일반관리비 | C63: =IF($C$105=1,ROUNDUP(C62*$C$104,-1),C62*$C$104) -> 224040 | D63: =IF($C$105=1,ROUNDUP(D62*$C$104,-1),D62*$C$104) -> 211110 | E63: =IF($C$105=1,ROUNDUP(E62*$C$104,-1),E62*$C$104) -> 200380 | F63: =SUMPRODUCT(C63:E63,C10:E10) -> 2660790 | G63: =IF($C$96=0,0,F63/$C$96) -> 204676.15 | H63: =SUMPRODUCT(C63:E63,C10:E10,C25:E25) -> 31929480 | I63: 직접원가 × 일반관리비율
B64: 3. 원가소계 | C64: =C62+C63 -> 4704716.1 | D64: =D62+D63 -> 4433288.9 | E64: =E62+E63 -> 4207838.6 | F64: =SUMPRODUCT(C64:E64,C10:E10) -> 55875130 | G64: =IF($C$96=0,0,F64/$C$96) -> 4298087 | H64: =SUMPRODUCT(C64:E64,C10:E10,C25:E25) -> 6.7050156e+08 | I64: 직접원가 + 일반관리비
B65: 4. 기업이윤 | C65: =IF($C$107=1,C64,C62)*$C$106 -> 89613.521 | D65: =IF($C$107=1,D64,D62)*$C$106 -> 84443.577 | E65: =IF($C$107=1,E64,E62)*$C$106 -> 80149.173 | F65: =SUMPRODUCT(C65:E65,C10:E10) -> 1064286.8 | G65: =IF($C$96=0,0,F65/$C$96) -> 81868.216 | H65: =SUMPRODUCT(C65:E65,C10:E10,C25:E25) -> 12771442 | I65: 직접원가(또는 원가소계) × 이윤율
B66: 5. 원가총계 | C66: =C64+C65 -> 4794329.6 | D66: =D64+D65 -> 4517732.5 | E66: =E64+E65 -> 4287987.8 | F66: =SUMPRODUCT(C66:E66,C10:E10) -> 56939417 | G66: =IF($C$96=0,0,F66/$C$96) -> 4379955.2 | H66: =SUMPRODUCT(C66:E66,C10:E10,C25:E25) -> 6.8327301e+08 | I66: 원가소계 + 기업이윤
B67: 6. 견적금액(인당) | C67: =ROUNDDOWN(C66,-3) -> 4794000 | D67: =ROUNDDOWN(D66,-3) -> 4517000 | E67: =ROUNDDOWN(E66,-3) -> 4287000 | F67: =SUMPRODUCT(C67:E67,C10:E10) -> 56928000 | G67: =IF($C$96=0,0,F67/$C$96) -> 4379076.9 | H67: =SUMPRODUCT(C67:E67,C10:E10,C25:E25) -> 683136000 | I67: 원가총계 단수처리
A70: ■ 산출 기준 (2027년 · 사업주 부담) — 노란 칸의 요율·기준을 고치면 위 산출내역이 모두 다시 계산됩니다
B71: 항목 | C71: 값 | D71: 비고
B72: 최저시급 (시간당) | C72: 10700 | D72: 원 · 2027년 · 법정(4. 요율·기준)
B73: 건강보험 | C73: 0.03595 | D73: 보수월액 × 7.19% 중 사업주분 · 법정(4. 요율·기준)
B74: 노인장기요양 (건보료 대비) | C74: 0.1314
B75: 국민연금 | C75: 0.05
B76: 고용보험 | C76: 0.0185 | D76: 실업급여 + 고용안정·직능(규모별)
B77: 산재보험 | C77: 0.0086 | D77: 사업종류별 + 출퇴근재해
B78: 임금채권부담금 | C78: 0.0009
B79: 석면피해구제분담금 | C79: 6e-05
B80: 연장 가산배율 (일반) | C80: 1.5
B81: 연장 배율 (감시단속) | C81: 1
B82: 야간 가산율 | C82: 0.5
B83: 연차 1일 시간 | C83: 8
B84: 특수건강검진 (연/인) | C84: 80000
B85: 장애인부담금 반영 (1=반영) | C85: 1
B86: 장애인 의무고용률 | C86: 0.031
B87: 부담기초액 | C87: 1360000
B88: 부담금 반영률 | C88: 1
B89: 명절선물대 (연/인) | C89: 100000
... B95: 주민세 개소 수 | C95: 1
B96: 총 인원 | C96: =SUM(C10:E10) -> 13 | D96: 인원 행 합계
B97: 교육훈련비율 (노무비 대비) | C97: 0.01
B98: 교육훈련비 고정액 | C98: 0 | D98: 0이면 비율 적용
B99: 위험부담율 (노무비 대비) | C99: 0.005
B100: 위험부담금 고정액 | C100: 0 | D100: 0이면 비율 적용
B101: 부대비용 인당 배분 (1=배분) | C101: 1 | D101: 0이면 별도 청구
B102: 부대비용 월계 | C102: 0 | D102: 차량·장비·기타
B103: 배분 대상 인원 | C103: =SUMPRODUCT(C10:E10,1-C24:E24) -> 13
B104: 일반관리비율 | C104: 0.05
B105: 일반관리비 10원 절상 (1=예) | C105: 1
B106: 기업이윤율 | C106: 0.02
B107: 이윤 기준 (0=직접원가, 1=원가소계) | C107: 0
C109: ㈜에스텍시스템 · 에스텍 그룹 | 서울특별시 강남구 개포로 619, 8층(개포동, 서울강남우체국청사)

Sheet 부대비용
B1: 부대비용 산출 명세 | E1: No. 261021-2703
E2: 작성일 2026. 10. 21
B3: 현대자동차 울산공장 정문 · 반영방식 인당 단가 균등 배분 · 단위: 원, VAT 별도
A7: 구분 | B7: 항목 | C7: 수량 | D7: 월 금액 | E7: 산출 근거
A8: 합계 | D8: 0 | E8: 인당 0원 배분 (13명)

Sheet 업무별 비용 배분
A1: 업무별 비용 배분 (견적서 기반) | X1: No. 261021-2703
X2: 작성일 2026. 10. 21
A3: 현대자동차 울산공장 정문 · 보안용역 도급업무 · 단위: 원, VAT 별도
A5: ■ 산정 요약 | N5: ■ 견적 금액 구성 (월)
A6: 산정 방식 | D6: B. 견적서 기반 업무별 비용 산정 | N6: 직접노무비 ① (산출내역서 40행) | Q6: 45852180 | R6: 0.8054
A7: 사업장 유형 · 직종 | D7: 공장 · 보안 | N7: 간접노무비 ② (산출내역서 50행) | Q7: 5634050 | R7: 0.099
A8: 견적 연도 | D8: 2027년 | N8: 경비 (산출내역서 61행) | Q8: 1728110 | R8: 0.0304
A9: 월 총 업무시간 (h) | D9: 1752.4397 | N9: 일반관리비 (산출내역서 63행) | Q9: 2660790 | R9: 0.0467
A10: 업무량 기준 필요 인원 (명) | D10: 10.7261 | N10: 기업이윤 · 단수조정 (65행 + 견적단가 1,000원 미만 절사) | Q10: 1052870 | R10: 0.0185
A11: 견적 인원 (명) | D11: 13 | N11: 월 합계 (= 견적서 월 합계) | Q11: =SUM(Q6:Q10) -> 56928000 | R11: 1
A12: 견적 인원 월 근무시간 (h) | D12: 2584.2167
A13: 1인 업무부하 (업무시간 ÷ 근무시간) | D13: 0.6781
A14: 견적 월 합계 (원) | D14: 56928000
A15: 계약기간 총액 (원) | D15: 683136000
A16: 시간당 단가 (월 합계 ÷ 월 업무시간) | D16: 32484.997
A17: 원 견적 인원 (명) | D17: 13
A18: 수행 가능 업무량 (원 견적 인원 기준) | D18: 1
A19: 부족 인력 (명) | D19: 0
A20: 부족 인력 반영 | D20: 해당 없음
A22: 코드 | B22: 대분류 | C22: 중분류 | D22: 업무명 | E22: 구분 | F22: 투입 | G22: 단위시간(분) | H22: 수량 | I22: 단위 | J22: 빈도 | K22: 주기 | L22: 월 횟수 | M22: 월 업무시간(h) | N22: 연 업무시간(h) | O22: 시간 비중 | P22: 시간당 단가 | Q22: 직접노무비 | R22: 간접노무비 | S22: 경비 | T22: 일반관리비 | U22: 이윤·단수 | V22: 월 배분액 | W22: 연 배분액 | X22: 단위당 단가
A23: A | B23: 출입통제 | E23: 19개 업무 | M23: 1009.0451 | N23: 12108.542 | O23: 0.5758 | P23: 32484.997 | Q23: 26401432 | R23: 3244055 | S23: 995035 | T23: 1532069 | U23: 606237 | V23: =SUM(Q23:U23) -> 32778828 | W23: =V23*12 -> 393345936 | Z23: 0
A24: A1 | B24: 출입통제 | C24: 정문 초소 | E24: 13개 업무 | M24: 729.6 | N24: 8755.2 | O24: 0.4163 | P24: 32484.996 | Q24: 19089815 | R24: 2345646 | S24: 719469 | T24: 1107777 | U24: 438346 | V24: =SUM(Q24:U24) -> 23701053 | W24: =V24*12 -> 284412636 | Z24: 0
A25: A1-1 | B25: 출입통제 | C25: 정문 초소 | D25: 정문 상주 근무 (24시간 경계·대기) | E25: 상주(잔여) | F25: 공통 | G25: 1440 | H25: 1 | I25: 개소 | J25: 1 | K25: 매일 | L25: 30.4 | M25: 427.7787 | N25: 5133.344 | O25: 0.2441 | P25: 32484.998 | Q25: 11192730 | R25: 1375298 | S25: 421840 | T25: 649511 | U25: 257010 | V25: =SUM(Q25:U25) -> 13896389 | W25: =V25*12 -> 166756668 | X25: 457118.06 | Z25: 1
A26: A1-2-a | B26: 출입통제 | C26: 정문 초소 | D26: 입문 차량 확인·출입 기록 | E26: 작업 | F26: 공통 | G26: 0.5 | H26: 108 | I26: 대 | J26: 1 | K26: 매일 | L26: 3283.2 | M26: 31.464 | N26: 377.568 | O26: 0.018 | P26: 32484.999 | Q26: 823248 | R26: 101156 | S26: 31027 | T26: 47773 | U26: 18904 | V26: =SUM(Q26:U26) -> 1022108 | W26: =V26*12 -> 12265296 | X26: 311.3146 | Z26: 1
A27: A1-2-b | B27: 출입통제 | C27: 정문 초소 | D27: 출문 차량 적재물 확인 | E27: 작업 | F27: 공통 | G27: 1 | H27: 54 | I27: 대 | J27: 1 | K27: 매일 | L27: 1641.6 | M27: 31.464 | N27: 377.568 | O27: 0.018 | P27: 32484.999 | Q27: 823248 | R27: 101156 | S27: 31027 | T27: 47773 | U27: 18904 | V27: =SUM(Q27:U27) -> 1022108 | W27: =V27*12 -> 12265296 | X27: 622.6291 | Z27: 1
A28: A1-2-c | B28: 출입통제 | C28: 정문 초소 | D28: 협력업체·납품차량 출입 통제 | E28: 작업 | F28: 공통 | G28: 3 | H28: 18 | I28: 대 | J28: 1 | K28: 매일 | L28: 547.2 | M28: 31.464 | N28: 377.568 | O28: 0.018 | P28: 32484.999 | Q28: 823248 | R28: 101156 | S28: 31027 | T28: 47773 | U28: 18904 | V28: =SUM(Q28:U28) -> 1022108 | W28: =V28*12 -> 12265296 | X28: 1867.8874 | Z28: 1
A29: A1-2-d | B29: 출입통제 | C29: 정문 초소 | D29: 긴급·관공서 차량 우선 통행 안내 | E29: 작업 | F29: 공통 | G29: 3 | H29: 2 | I29: 대 | J29: 1 | K29: 매일 | L29: 60.8 | M29: 3.496 | N29: 41.952 | O29: 0.002 | P29: 32484.84 | Q29: 91472 | R29: 11240 | S29: 3447 | T29: 5308 | U29: 2100 | V29: =SUM(Q29:U29) -> 113567 | W29: =V29*12 -> 1362804 | X29: 1867.8783 | Z29: 1
A30: A1-3-a | B30: 출입통제 | C30: 정문 초소 | D30: 방문객 신원확인·출입증 발급 | E30: 작업 | F30: 공통 | G30: 2 | H30: 60 | I30: 명 | J30: 1 | K30: 매일 | L30: 1824 | M30: 69.92 | N30: 839.04 | O30: 0.0399 | P30: 32484.997 | Q30: 1829441 | R30: 224791 | S30: 68949 | T30: 106162 | U30: 42008 | V30: =SUM(Q30:U30) -> 2271351 | W30: =V30*12 -> 27256212 | X30: 1245.2582 | Z30: 1
A31: A1-3-b | B31: 출입통제 | C31: 정문 초소 | D31: 출입증 회수·방문 대장 정리 | E31: 작업 | F31: 공통 | G31: 0.5 | H31: 60 | I31: 명 | J31: 1 | K31: 매일 | L31: 1824 | M31: 17.48 | N31: 209.76 | O31: 0.01 | P31: 32485.011 | Q31: 457360 | R31: 56198 | S31: 17237 | T31: 26541 | U31: 10502 | V31: =SUM(Q31:U31) -> 567838 | W31: =V31*12 -> 6814056 | X31: 311.3147 | Z31: 1
A32: A1-3-c | B32: 출입통제 | C32: 정문 초소 | D32: 사전 방문예약 확인·접견자 연락 | E32: 작업 | F32: 공통 | G32: 1 | H32: 24 | I32: 건 | J32: 1 | K32: 매일 | L32: 729.6 | M32: 13.984 | N32: 167.808 | O32: 0.008 | P32: 32484.983 | Q32: 365888 | R32: 44958 | S32: 13790 | T32: 21232 | U32: 8402 | V32: =SUM(Q32:U32) -> 454270 | W32: =V32*12 -> 5451240 | X32: 622.6288 | Z32: 1
A33: A1-4-a | B33: 출입통제 | C33: 정문 초소 | D33: 반출입증 확인·물품 대조 | E33: 작업 | F33: 공통 | G33: 3 | H33: 14 | I33: 건 | J33: 1 | K33: 매일 | L33: 425.6 | M33: 24.472 | N33: 293.664 | O33: 0.014 | P33: 32485.003 | Q33: 640304 | R33: 78677 | S33: 24132 | T33: 37157 | U33: 14703 | V33: =SUM(Q33:U33) -> 794973 | W33: =V33*12 -> 9539676 | X33: 1867.8877 | Z33: 1
A34: A1-4-b | B34: 출입통제 | C34: 정문 초소 | D34: 반입 금지물품(화기·위험물) 검색 | E34: 작업 | F34: 공통 | G34: 1 | H34: 60 | I34: 명 | J34: 1 | K34: 매일 | L34: 1824 | M34: 34.96 | N34: 419.52 | O34: 0.0199 | P34: 32484.983 | Q34: 914720 | R34: 112395 | S34: 34475 | T34: 53081 | U34: 21004 | V34: =SUM(Q34:U34) -> 1135675 | W34: =V34*12 -> 13628100 | X34: 622.6288 | Z34: 1
A35: A1-5-a | B35: 출입통제 | C35: 정문 초소 | D35: 택배 수령·보관 등록 | E35: 작업 | F35: 공통 | G35: 1 | H35: 40 | I35: 건 | J35: 1 | K35: 매일 | L35: 1216 | M35: 23.3067 | N35: 279.68 | O35: 0.0133 | P35: 32484.997 | Q35: 609814 | R35: 74930 | S35: 22983 | T35: 35387 | U35: 14003 | V35: =SUM(Q35:U35) -> 757117 | W35: =V35*12 -> 9085404 | X35: 622.6291 | Z35: 1
A36: A1-5-b | B36: 출입통제 | C36: 정문 초소 | D36: 수령자 연락·인계 확인 | E36: 작업 | F36: 공통 | G36: 0.7 | H36: 40 | I36: 건 | J36: 1 | K36: 매일 | L36: 1216 | M36: 16.3147 | N36: 195.776 | O36: 0.0093 | P36: 32485.003 | Q36: 426870 | R36: 52451 | S36: 16088 | T36: 24771 | U36: 9802 | V36: =SUM(Q36:U36) -> 529982 | W36: =V36*12 -> 6359784 | X36: 435.8405 | Z36: 1
A37: A1-5-c | B37: 출입통제 | C37: 정문 초소 | D37: 등기·우편물 분류 | E37: 작업 | F37: 공통 | G37: 0.5 | H37: 12 | I37: 건 | J37: 1 | K37: 매일 | L37: 364.8 | M37: 3.496 | N37: 41.952 | O37: 0.002 | P37: 32484.84 | Q37: 91472 | R37: 11240 | S37: 3447 | T37: 5308 | U37: 2100 | V37: =SUM(Q37:U37) -> 113567 | W37: =V37*12 -> 1362804 | X37: 311.313 | Z37: 1
A38: A2 | B38: 출입통제 | C38: 후문·부출입구 | E38: 3개 업무 | M38: 260.7143 | N38: 3128.5714 | O38: 0.1488 | P38: 32484.994 | Q38: 6821529 | R38: 838189 | S38: 257095 | T38: 395852 | U38: 156637 | V38: =SUM(Q38:U38) -> 8469302 | W38: =V38*12 -> 101631624 | Z38: 0
A39: A2-1 | B39: 출입통제 | C39: 후문·부출입구 | D39: 후문 주간 상주 (07~19시) | E39: 상주(잔여) | F39: 공통 | G39: 720 | H39: 1 | I39: 개소 | J39: 5 | K39: 매주 | L39: 21.7262 | M39: 224.0758 | N39: 2688.91 | O39: 0.1279 | P39: 32484.994 | Q39: 5862892 | R39: 720398 | S39: 220965 | T39: 340222 | U39: 134625 | V39: =SUM(Q39:U39) -> 7279102 | W39: =V39*12 -> 87349224 | X39: 335038.12 | Z39: 1
A40: A2-2 | B40: 출입통제 | C40: 후문·부출입구 | D40: 출퇴근 시간 출입 통제 | E40: 작업 | F40: 공통 | G40: 30 | H40: 1 | I40: 개소 | J40: 10 | K40: 매주 | L40: 43.4524 | M40: 24.9851 | N40: 299.8214 | O40: 0.0143 | P40: 32484.976 | Q40: 653730 | R40: 80326 | S40: 24638 | T40: 37936 | U40: 15011 | V40: =SUM(Q40:U40) -> 811641 | W40: =V40*12 -> 9739692 | X40: 18678.861 | Z40: 1
A41: A2-3 | B41: 출입통제 | C41: 후문·부출입구 | D41: 야간 출입문 시건·개방 | E41: 작업 | F41: 공통 | G41: 10 | H41: 1 | I41: 개소 | J41: 2 | K41: 매일 | L41: 60.8 | M41: 11.6533 | N41: 139.84 | O41: 0.0066 | P41: 32485.04 | Q41: 304907 | R41: 37465 | S41: 11492 | T41: 17694 | U41: 7001 | V41: =SUM(Q41:U41) -> 378559 | W41: =V41*12 -> 4542708 | X41: 6226.2993 | Z41: 1
A42: A3 | B42: 출입통제 | C42: 출입보안시스템 | E42: 3개 업무 | M42: 18.7309 | N42: 224.7702 | O42: 0.0107 | P42: 32485.066 | Q42: 490088 | R42: 60220 | S42: 18471 | T42: 28440 | U42: 11254 | V42: =SUM(Q42:U42) -> 608473 | W42: =V42*12 -> 7301676 | Z42: 0
A43: A3-1 | B43: 출입통제 | C43: 출입보안시스템 | D43: 출입카드 발급·회수·분실 처리 | E43: 작업 | F43: 공통 | G43: 5 | H43: 10 | I43: 건 | J43: 1 | K43: 매주 | L43: 43.4524 | M43: 4.1642 | N43: 49.9702 | O43: 0.0024 | P43: 32485.096 | Q43: 108955 | R43: 13388 | S43: 4106 | T43: 6323 | U43: 2502 | V43: =SUM(Q43:U43) -> 135274 | W43: =V43*12 -> 1623288 | X43: 3113.1551 | Z43: 1
A44: A3-2 | B44: 출입통제 | C44: 출입보안시스템 | D44: 출입기록 확인·이상 출입 조치 | E44: 작업 | F44: 공통 | G44: 15 | H44: 1 | I44: 회 | J44: 1 | K44: 매일 | L44: 30.4 | M44: 8.74 | N44: 104.88 | O44: 0.005 | P44: 32485.011 | Q44: 228680 | R44: 28099 | S44: 8619 | T44: 13270 | U44: 5251 | V44: =SUM(Q44:U44) -> 283919 | W44: =V44*12 -> 3407028 | X44: 9339.4408 | Z44: 1
A45: A3-3 | B45: 출입통제 | C45: 출입보안시스템 | D45: 스피드게이트·출입통제기 작동 확인 | E45: 작업 | F45: 공통 | G45: 5 | H45: 2 | I45: 대 | J45: 1 | K45: 매일 | L45: 60.8 | M45: 5.8267 | N45: 69.92 | O45: 0.0033 | P45: 32485.126 | Q45: 152453 | R45: 18733 | S45: 5746 | T45: 8847 | U45: 3501 | V45: =SUM(Q45:U45) -> 189280 | W45: =V45*12 -> 2271360 | X45: 3113.1579 | Z45: 1
A46: B | B46: 순찰 | E46: 7개 업무 | M46: 417.956 | N46: 5015.472 | O46: 0.2385 | P46: 32484.998 | Q46: 10935722 | R46: 1343718 | S46: 412154 | T46: 634597 | U46: 251109 | V46: =SUM(Q46:U46) -> 13577300 | W46: =V46*12 -> 162927600 | Z46: 0
A47: B1 | B47: 순찰 | C47: 정기순찰 | E47: 4개 업무 | M47: 318.136 | N47: 3817.632 | O47: 0.1815 | P47: 32485 | Q47: 8323954 | R47: 1022800 | S47: 313720 | T47: 483037 | U47: 191137 | V47: =SUM(Q47:U47) -> 10334648 | W47: =V47*12 -> 124015776 | Z47: 0
A48: B1-1 | B48: 순찰 | C48: 정기순찰 | D48: 외곽 울타리·담장 순찰 | E48: 작업 | F48: 공통 | G48: 30 | H48: 2 | I48: 구역 | J48: 4 | K48: 매일 | L48: 243.2 | M48: 139.84 | N48: 1678.08 | O48: 0.0798 | P48: 32484.997 | Q48: 3658881 | R48: 449582 | S48: 137899 | T48: 212324 | U48: 84016 | V48: =SUM(Q48:U48) -> 4542702 | W48: =V48*12 -> 54512424 | X48: 18678.873 | Z48: 1
A49: B1-2 | B49: 순찰 | C49: 정기순찰 | D49: 건물 내부 층별 순찰 | E49: 작업 | F49: 공통 | G49: 5 | H49: 18 | I49: 층 | J49: 2 | K49: 매일 | L49: 1094.4 | M49: 104.88 | N49: 1258.56 | O49: 0.0598 | P49: 32485.002 | Q49: 2744161 | R49: 337187 | S49: 103424 | T49: 159243 | U49: 63012 | V49: =SUM(Q49:U49) -> 3407027 | W49: =V49*12 -> 40884324 | X49: 3113.146 | Z49: 1
A50: B1-3 | B50: 순찰 | C50: 정기순찰 | D50: 주차장 순찰 | E50: 작업 | F50: 공통 | G50: 8 | H50: 3 | I50: 구역 | J50: 3 | K50: 매일 | L50: 273.6 | M50: 41.952 | N50: 503.424 | O50: 0.0239 | P50: 32485.007 | Q50: 1097664 | R50: 134875 | S50: 41370 | T50: 63697 | U50: 25205 | V50: =SUM(Q50:U50) -> 1362811 | W50: =V50*12 -> 16353732 | X50: 4981.0344 | Z50: 1
A51: B1-4 | B51: 순찰 | C51: 정기순찰 | D51: 야간 문단속·소등·전열기구 확인 | E51: 작업 | F51: 공통 | G51: 3 | H51: 18 | I51: 층 | J51: 1 | K51: 매일 | L51: 547.2 | M51: 31.464 | N51: 377.568 | O51: 0.018 | P51: 32484.999 | Q51: 823248 | R51: 101156 | S51: 31027 | T51: 47773 | U51: 18904 | V51: =SUM(Q51:U51) -> 1022108 | W51: =V51*12 -> 12265296 | X51: 1867.8874 | Z51: 1
A52: B2 | B52: 순찰 | C52: 특별순찰 | E52: 3개 업무 | M52: 99.82 | N52: 1197.84 | O52: 0.057 | P52: 32484.993 | Q52: 2611768 | R52: 320918 | S52: 98434 | T52: 151560 | U52: 59972 | V52: =SUM(Q52:U52) -> 3242652 | W52: =V52*12 -> 38911824 | Z52: 0
A53: B2-1 | B53: 순찰 | C53: 특별순찰 | D53: 취약지역·사각지대 집중 순찰 | E53: 작업 | F53: 공통 | G53: 20 | H53: 3 | I53: 개소 | J53: 2 | K53: 매일 | L53: 182.4 | M53: 69.92 | N53: 839.04 | O53: 0.0399 | P53: 32484.997 | Q53: 1829441 | R53: 224791 | S53: 68949 | T53: 106162 | U53: 42008 | V53: =SUM(Q53:U53) -> 2271351 | W53: =V53*12 -> 27256212 | X53: 12452.582 | Z53: 1
A54: B2-2 | B54: 순찰 | C54: 특별순찰 | D54: 휴일·공휴일 전수 점검 | E54: 작업 | F54: 공통 | G54: 30 | H54: 6 | I54: 동 | J54: 8 | K54: 매월 | L54: 48 | M54: 27.6 | N54: 331.2 | O54: 0.0157 | P54: 32485 | Q54: 722148 | R54: 88733 | S54: 27217 | T54: 41906 | U54: 16582 | V54: =SUM(Q54:U54) -> 896586 | W54: =V54*12 -> 10759032 | X54: 18678.875 | Z54: 1
A55: B2-3 | B55: 순찰 | C55: 특별순찰 | D55: 기상특보(태풍·폭우·폭설) 비상 순찰 | E55: 작업 | F55: 공통 | G55: 60 | H55: 6 | I55: 동 | J55: 4 | K55: 매년 | L55: 2 | M55: 2.3 | N55: 27.6 | O55: 0.0013 | P55: 32484.783 | Q55: 60179 | R55: 7394 | S55: 2268 | T55: 3492 | U55: 1382 | V55: =SUM(Q55:U55) -> 74715 | W55: =V55*12 -> 896580 | X55: 37357.5 | Z55: 1
A56: C | B56: 상황대처 | E56: 23개 업무 | M56: 52.3378 | N56: 628.0533 | O56: 0.0299 | P56: 32485.082 | Q56: 1369406 | R56: 168266 | S56: 51611 | T56: 79467 | U56: 31447 | V56: =SUM(Q56:U56) -> 1700197 | W56: =V56*12 -> 20402364 | Z56: 0
A57: C1 | B57: 상황대처 | C57: 화재·소방 | E57: 4개 업무 | M57: 2.7153 | N57: 32.5833 | O57: 0.0015 | P57: 32485.443 | Q57: 71044 | R57: 8730 | S57: 2678 | T57: 4123 | U57: 1632 | V57: =SUM(Q57:U57) -> 88207 | W57: =V57*12 -> 1058484 | Z57: 0
A58: C1-1 | B58: 상황대처 | C58: 화재·소방 | D58: 화재경보 발생 시 현장 출동·확인 | E58: 작업 | F58: 공통 | G58: 15 | H58: 1 | I58: 건 | J58: 6 | K58: 매월 | L58: 6 | M58: 1.725 | N58: 20.7 | O58: 0.001 | P58: 32484.638 | Q58: 45134 | R58: 5546 | S58: 1701 | T58: 2619 | U58: 1036 | V58: =SUM(Q58:U58) -> 56036 | W58: =V58*12 -> 672432 | X58: 9339.3333 | Z58: 1
A59: C1-2 | B59: 상황대처 | C59: 화재·소방 | D59: 비화재보 복구·수신기 리셋 | E59: 작업 | F59: 공통 | G59: 10 | H59: 1 | I59: 건 | J59: 4 | K59: 매월 | L59: 4 | M59: 0.7667 | N59: 9.2 | O59: 0.0004 | P59: 32486.087 | Q59: 20060 | R59: 2465 | S59: 756 | T59: 1164 | U59: 461 | V59: =SUM(Q59:U59) -> 24906 | W59: =V59*12 -> 298872 | X59: 6226.5 | Z59: 1
A60: C1-3 | B60: 상황대처 | C60: 화재·소방 | D60: 초기 소화·피난 유도 | E60: 작업 | F60: 공통 | G60: 60 | H60: 1 | I60: 건 | J60: 1 | K60: 매년 | L60: 0.0833 | M60: 0.0958 | N60: 1.15 | O60: 0.0001 | P60: 32493.913 | Q60: 2507 | R60: 308 | S60: 95 | T60: 146 | U60: 58 | V60: =SUM(Q60:U60) -> 3114 | W60: =V60*12 -> 37368 | X60: 37368 | Z60: 1
A61: C1-4 | B61: 상황대처 | C61: 화재·소방 | D61: 소방서 신고·소방차 진입 안내 | E61: 작업 | F61: 공통 | G61: 20 | H61: 1 | I61: 건 | J61: 1 | K61: 분기 | L61: 0.3333 | M61: 0.1278 | N61: 1.5333 | O61: 0.0001 | P61: 32486.087 | Q61: 3343 | R61: 411 | S61: 126 | T61: 194 | U61: 77 | V61: =SUM(Q61:U61) -> 4151 | W61: =V61*12 -> 49812 | X61: 12453 | Z61: 1
A62: C2 | B62: 상황대처 | C62: 응급·안전사고 | E62: 5개 업무 | M62: 2.3 | N62: 27.6 | O62: 0.0013 | P62: 32486.087 | Q62: 60180 | R62: 7395 | S62: 2268 | T62: 3492 | U62: 1383 | V62: =SUM(Q62:U62) -> 74718 | W62: =V62*12 -> 896616 | Z62: 0
A63: C2-1 | B63: 상황대처 | C63: 응급·안전사고 | D63: 응급환자 응급조치·119 신고·인계 | E63: 작업 | F63: 공통 | G63: 30 | H63: 1 | I63: 건 | J63: 1 | K63: 매월 | L63: 1 | M63: 0.575 | N63: 6.9 | O63: 0.0003 | P63: 32486.957 | Q63: 15045 | R63: 1849 | S63: 567 | T63: 873 | U63: 346 | V63: =SUM(Q63:U63) -> 18680 | W63: =V63*12 -> 224160 | X63: 18680 | Z63: 1
A64: C2-2 | B64: 상황대처 | C64: 응급·안전사고 | D64: AED·구급함 점검 | E64: 작업 | F64: 공통 | G64: 5 | H64: 6 | I64: 개소 | J64: 1 | K64: 매월 | L64: 6 | M64: 0.575 | N64: 6.9 | O64: 0.0003 | P64: 32486.957 | Q64: 15045 | R64: 1849 | S64: 567 | T64: 873 | U64: 346 | V64: =SUM(Q64:U64) -> 18680 | W64: =V64*12 -> 224160 | X64: 3113.3333 | Z64: 1
A65: C2-3 | B65: 상황대처 | C65: 응급·안전사고 | D65: 산업재해 발생 시 현장 통제·보고 | E65: 작업 | F65: 공통 | G65: 60 | H65: 1 | I65: 건 | J65: 2 | K65: 매년 | L65: 0.1667 | M65: 0.1917 | N65: 2.3 | O65: 0.0001 | P65: 32483.478 | Q65: 5015 | R65: 616 | S65: 189 | T65: 291 | U65: 115 | V65: =SUM(Q65:U65) -> 6226 | W65: =V65*12 -> 74712 | X65: 37356 | Z65: 1
A66: C2-4 | B66: 상황대처 | C66: 응급·안전사고 | D66: 승강기 갇힘 사고 대응·구조 연계 | E66: 작업 | F66: 공통 | G66: 30 | H66: 1 | I66: 건 | J66: 1 | K66: 매월 | L66: 1 | M66: 0.575 | N66: 6.9 | O66: 0.0003 | P66: 32486.957 | Q66: 15045 | R66: 1849 | S66: 567 | T66: 873 | U66: 346 | V66: =SUM(Q66:U66) -> 18680 | W66: =V66*12 -> 224160 | X66: 18680 | Z66: 1
A67: C2-5 | B67: 상황대처 | C67: 응급·안전사고 | D67: 넘어짐·추락 사고 현장 조치 | E67: 작업 | F67: 공통 | G67: 20 | H67: 1 | I67: 건 | J67: 1 | K67: 매월 | L67: 1 | M67: 0.3833 | N67: 4.6 | O67: 0.0002 | P67: 32483.478 | Q67: 10030 | R67: 1232 | S67: 378 | T67: 582 | U67: 230 | V67: =SUM(Q67:U67) -> 12452 | W67: =V67*12 -> 149424 | X67: 12452 | Z67: 1
A68: C3 | B68: 상황대처 | C68: 침입·도난·범죄 | E68: 4개 업무 | M68: 6.7083 | N68: 80.5 | O68: 0.0038 | P68: 32484.969 | Q68: 175522 | R68: 21567 | S68: 6615 | T68: 10185 | U68: 4031 | V68: =SUM(Q68:U68) -> 217920 | W68: =V68*12 -> 2615040 | Z68: 0
A69: C3-1 | B69: 상황대처 | C69: 침입·도난·범죄 | D69: 무단침입 발생 시 대응·경찰 신고 | E69: 작업 | F69: 공통 | G69: 40 | H69: 1 | I69: 건 | J69: 2 | K69: 매월 | L69: 2 | M69: 1.5333 | N69: 18.4 | O69: 0.0009 | P69: 32484.783 | Q69: 40119 | R69: 4930 | S69: 1512 | T69: 2328 | U69: 921 | V69: =SUM(Q69:U69) -> 49810 | W69: =V69*12 -> 597720 | X69: 24905 | Z69: 1
A70: C3-2 | B70: 상황대처 | C70: 침입·도난·범죄 | D70: 도난·분실 신고 접수·조사 협조 | E70: 작업 | F70: 공통 | G70: 30 | H70: 1 | I70: 건 | J70: 1 | K70: 매월 | L70: 1 | M70: 0.575 | N70: 6.9 | O70: 0.0003 | P70: 32486.957 | Q70: 15045 | R70: 1849 | S70: 567 | T70: 873 | U70: 346 | V70: =SUM(Q70:U70) -> 18680 | W70: =V70*12 -> 224160 | X70: 18680 | Z70: 1
A71: C3-3 | B71: 상황대처 | C71: 침입·도난·범죄 | D71: CCTV 영상 확인·증거 보존 지원 | E71: 작업 | F71: 공통 | G71: 30 | H71: 1 | I71: 건 | J71: 4 | K71: 매월 | L71: 4 | M71: 2.3 | N71: 27.6 | O71: 0.0013 | P71: 32484.783 | Q71: 60179 | R71: 7394 | S71: 2268 | T71: 3492 | U71: 1382 | V71: =SUM(Q71:U71) -> 74715 | W71: =V71*12 -> 896580 | X71: 18678.75 | Z71: 1
A72: C3-4 | B72: 상황대처 | C72: 침입·도난·범죄 | D72: 수상한 물건·거동 수상자 확인 | E72: 작업 | F72: 공통 | G72: 15 | H72: 1 | I72: 건 | J72: 8 | K72: 매월 | L72: 8 | M72: 2.3 | N72: 27.6 | O72: 0.0013 | P72: 32484.783 | Q72: 60179 | R72: 7394 | S72: 2268 | T72: 3492 | U72: 1382 | V72: =SUM(Q72:U72) -> 74715 | W72: =V72*12 -> 896580 | X72: 9339.375 | Z72: 1
A73: C4 | B73: 상황대처 | C73: 소란·민원·폭력 | E73: 4개 업무 | M73: 18.63 | N73: 223.56 | O73: 0.0106 | P73: 32485.024 | Q73: 487450 | R73: 59895 | S73: 18371 | T73: 28287 | U73: 11193 | V73: =SUM(Q73:U73) -> 605196 | W73: =V73*12 -> 7262352 | Z73: 0
A74: C4-1 | B74: 상황대처 | C74: 소란·민원·폭력 | D74: 소란·난동 발생 시 제지·분리 | E74: 작업 | F74: 공통 | G74: 30 | H74: 1 | I74: 건 | J74: 1 | K74: 매월 | L74: 1 | M74: 0.575 | N74: 6.9 | O74: 0.0003 | P74: 32486.957 | Q74: 15045 | R74: 1849 | S74: 567 | T74: 873 | U74: 346 | V74: =SUM(Q74:U74) -> 18680 | W74: =V74*12 -> 224160 | X74: 18680 | Z74: 1
A75: C4-2 | B75: 상황대처 | C75: 소란·민원·폭력 | D75: 주취자·노숙인 대응 | E75: 작업 | F75: 공통 | G75: 20 | H75: 1 | I75: 건 | J75: 1 | K75: 매월 | L75: 1 | M75: 0.3833 | N75: 4.6 | O75: 0.0002 | P75: 32483.478 | Q75: 10030 | R75: 1232 | S75: 378 | T75: 582 | U75: 230 | V75: =SUM(Q75:U75) -> 12452 | W75: =V75*12 -> 149424 | X75: 12452 | Z75: 1
A76: C4-3 | B76: 상황대처 | C76: 소란·민원·폭력 | D76: 현장 민원 접수·응대 | E76: 작업 | F76: 공통 | G76: 10 | H76: 3 | I76: 건 | J76: 1 | K76: 매일 | L76: 91.2 | M76: 17.48 | N76: 209.76 | O76: 0.01 | P76: 32485.011 | Q76: 457360 | R76: 56198 | S76: 17237 | T76: 26541 | U76: 10502 | V76: =SUM(Q76:U76) -> 567838 | W76: =V76*12 -> 6814056 | X76: 6226.2939 | Z76: 1
A77: C4-4 | B77: 상황대처 | C77: 소란·민원·폭력 | D77: 집회·시위 발생 시 출입 통제 | E77: 작업 | F77: 공통 | G77: 120 | H77: 1 | I77: 건 | J77: 1 | K77: 매년 | L77: 0.0833 | M77: 0.1917 | N77: 2.3 | O77: 0.0001 | P77: 32483.478 | Q77: 5015 | R77: 616 | S77: 189 | T77: 291 | U77: 115 | V77: =SUM(Q77:U77) -> 6226 | W77: =V77*12 -> 74712 | X77: 74712 | Z77: 1
A78: C5 | B78: 상황대처 | C78: 설비 이상·재난 | E78: 4개 업무 | M78: 3.7375 | N78: 44.85 | O78: 0.0021 | P78: 32484.816 | Q78: 97790 | R78: 12016 | S78: 3686 | T78: 5675 | U78: 2245 | V78: =SUM(Q78:U78) -> 121412 | W78: =V78*12 -> 1456944 | Z78: 0
A79: C5-1 | B79: 상황대처 | C79: 설비 이상·재난 | D79: 정전 시 비상조명 확인·설비팀 연락 | E79: 작업 | F79: 공통 | G79: 30 | H79: 1 | I79: 건 | J79: 2 | K79: 매년 | L79: 0.1667 | M79: 0.0958 | N79: 1.15 | O79: 0.0001 | P79: 32493.913 | Q79: 2507 | R79: 308 | S79: 95 | T79: 146 | U79: 58 | V79: =SUM(Q79:U79) -> 3114 | W79: =V79*12 -> 37368 | X79: 18684 | Z79: 1
A80: C5-2 | B80: 상황대처 | C80: 설비 이상·재난 | D80: 누수·배관 파열 초동 조치 | E80: 작업 | F80: 공통 | G80: 30 | H80: 1 | I80: 건 | J80: 3 | K80: 매월 | L80: 3 | M80: 1.725 | N80: 20.7 | O80: 0.001 | P80: 32484.638 | Q80: 45134 | R80: 5546 | S80: 1701 | T80: 2619 | U80: 1036 | V80: =SUM(Q80:U80) -> 56036 | W80: =V80*12 -> 672432 | X80: 18678.667 | Z80: 1
A81: C5-3 | B81: 상황대처 | C81: 설비 이상·재난 | D81: 가스·화학물질 누출 초동 조치 | E81: 작업 | F81: 공통 | G81: 60 | H81: 1 | I81: 건 | J81: 2 | K81: 매년 | L81: 0.1667 | M81: 0.1917 | N81: 2.3 | O81: 0.0001 | P81: 32483.478 | Q81: 5015 | R81: 616 | S81: 189 | T81: 291 | U81: 115 | V81: =SUM(Q81:U81) -> 6226 | W81: =V81*12 -> 74712 | X81: 37356 | Z81: 1
A82: C5-4 | B82: 상황대처 | C82: 설비 이상·재난 | D82: 태풍·폭우 대비 시설물 결박·배수구 점검 | E82: 작업 | F82: 공통 | G82: 60 | H82: 6 | I82: 동 | J82: 3 | K82: 매년 | L82: 1.5 | M82: 1.725 | N82: 20.7 | O82: 0.001 | P82: 32484.638 | Q82: 45134 | R82: 5546 | S82: 1701 | T82: 2619 | U82: 1036 | V82: =SUM(Q82:U82) -> 56036 | W82: =V82*12 -> 672432 | X82: 37357.333 | Z82: 1
A83: C6 | B83: 상황대처 | C83: 교통·주차 사고 | E83: 2개 업무 | M83: 18.2467 | N83: 218.96 | O83: 0.0104 | P83: 32485.057 | Q83: 477420 | R83: 58663 | S83: 17993 | T83: 27705 | U83: 10963 | V83: =SUM(Q83:U83) -> 592744 | W83: =V83*12 -> 7112928 | Z83: 0
A84: C6-1 | B84: 상황대처 | C84: 교통·주차 사고 | D84: 구내 교통사고 현장 통제·보고 | E84: 작업 | F84: 공통 | G84: 40 | H84: 1 | I84: 건 | J84: 1 | K84: 매월 | L84: 1 | M84: 0.7667 | N84: 9.2 | O84: 0.0004 | P84: 32486.087 | Q84: 20060 | R84: 2465 | S84: 756 | T84: 1164 | U84: 461 | V84: =SUM(Q84:U84) -> 24906 | W84: =V84*12 -> 298872 | X84: 24906 | Z84: 1
A85: C6-2 | B85: 상황대처 | C85: 교통·주차 사고 | D85: 통행 방해·불법주차 차량 조치 | E85: 작업 | F85: 공통 | G85: 5 | H85: 6 | I85: 건 | J85: 1 | K85: 매일 | L85: 182.4 | M85: 17.48 | N85: 209.76 | O85: 0.01 | P85: 32485.011 | Q85: 457360 | R85: 56198 | S85: 17237 | T85: 26541 | U85: 10502 | V85: =SUM(Q85:U85) -> 567838 | W85: =V85*12 -> 6814056 | X85: 3113.1469 | Z85: 1
A86: D | B86: 관제·방재 | E86: 9개 업무 | M86: 85.3848 | N86: 1024.6171 | O86: 0.0487 | P86: 32484.965 | Q86: 2234073 | R86: 274508 | S86: 84200 | T86: 129642 | U86: 51298 | V86: =SUM(Q86:U86) -> 2773721 | W86: =V86*12 -> 33284652 | Z86: 0
A87: D1 | B87: 관제·방재 | C87: CCTV 관제 | E87: 3개 업무 | M87: 47.254 | N87: 567.0486 | O87: 0.027 | P87: 32484.963 | Q87: 1236391 | R87: 151920 | S87: 46598 | T87: 71747 | U87: 28390 | V87: =SUM(Q87:U87) -> 1535046 | W87: =V87*12 -> 18420552 | Z87: 0
A88: D1-1 | B88: 관제·방재 | C88: CCTV 관제 | D88: CCTV 모니터링 (정문 초소 겸무) | E88: 작업 | F88: 공통 | G88: 10 | H88: 1 | I88: 회 | J88: 6 | K88: 매일 | L88: 182.4 | M88: 34.96 | N88: 419.52 | O88: 0.0199 | P88: 32484.983 | Q88: 914720 | R88: 112395 | S88: 34475 | T88: 53081 | U88: 21004 | V88: =SUM(Q88:U88) -> 1135675 | W88: =V88*12 -> 13628100 | X88: 6226.2884 | Z88: 1
A89: D1-2 | B89: 관제·방재 | C89: CCTV 관제 | D89: CCTV 녹화 상태·카메라 점검 | E89: 작업 | F89: 공통 | G89: 1 | H89: 120 | I89: 대 | J89: 1 | K89: 매주 | L89: 521.4286 | M89: 9.994 | N89: 119.9286 | O89: 0.0057 | P89: 32484.936 | Q89: 261492 | R89: 32131 | S89: 9855 | T89: 15174 | U89: 6004 | V89: =SUM(Q89:U89) -> 324656 | W89: =V89*12 -> 3895872 | X89: 622.6279 | Z89: 1
A90: D1-3 | B90: 관제·방재 | C90: CCTV 관제 | D90: 영상 열람·반출 요청 처리 | E90: 작업 | F90: 공통 | G90: 30 | H90: 1 | I90: 건 | J90: 4 | K90: 매월 | L90: 4 | M90: 2.3 | N90: 27.6 | O90: 0.0013 | P90: 32484.783 | Q90: 60179 | R90: 7394 | S90: 2268 | T90: 3492 | U90: 1382 | V90: =SUM(Q90:U90) -> 74715 | W90: =V90*12 -> 896580 | X90: 18678.75 | Z90: 1
A91: D2 | B91: 관제·방재 | C91: 방재·설비 감시 | E91: 3개 업무 | M91: 32.0467 | N91: 384.56 | O91: 0.0183 | P91: 32484.97 | Q91: 838494 | R91: 103029 | S91: 31602 | T91: 48657 | U91: 19253 | V91: =SUM(Q91:U91) -> 1041035 | W91: =V91*12 -> 12492420 | Z91: 0
A92: D2-1 | B92: 관제·방재 | C92: 방재·설비 감시 | D92: 화재수신기·방재반 감시 기록 | E92: 작업 | F92: 공통 | G92: 10 | H92: 1 | I92: 회 | J92: 3 | K92: 매일 | L92: 91.2 | M92: 17.48 | N92: 209.76 | O92: 0.01 | P92: 32484.954 | Q92: 457360 | R92: 56198 | S92: 17237 | T92: 26540 | U92: 10502 | V92: =SUM(Q92:U92) -> 567837 | W92: =V92*12 -> 6814044 | X92: 6226.2829 | Z92: 1
A93: D2-2 | B93: 관제·방재 | C93: 방재·설비 감시 | D93: 무인경비·침입감지 알람 확인 | E93: 작업 | F93: 공통 | G93: 10 | H93: 1 | I93: 건 | J93: 2 | K93: 매일 | L93: 60.8 | M93: 11.6533 | N93: 139.84 | O93: 0.0066 | P93: 32485.04 | Q93: 304907 | R93: 37465 | S93: 11492 | T93: 17694 | U93: 7001 | V93: =SUM(Q93:U93) -> 378559 | W93: =V93*12 -> 4542708 | X93: 6226.2993 | Z93: 1
A94: D2-3 | B94: 관제·방재 | C94: 방재·설비 감시 | D94: 비상방송·안내방송 송출 | E94: 작업 | F94: 공통 | G94: 5 | H94: 1 | I94: 회 | J94: 1 | K94: 매일 | L94: 30.4 | M94: 2.9133 | N94: 34.96 | O94: 0.0017 | P94: 32484.783 | Q94: 76227 | R94: 9366 | S94: 2873 | T94: 4423 | U94: 1750 | V94: =SUM(Q94:U94) -> 94639 | W94: =V94*12 -> 1135668 | X94: 3113.125 | Z94: 1
A95: D3 | B95: 관제·방재 | C95: 소방시설 일상점검 | E95: 3개 업무 | M95: 6.084 | N95: 73.0086 | O95: 0.0035 | P95: 32484.953 | Q95: 159188 | R95: 19559 | S95: 6000 | T95: 9238 | U95: 3655 | V95: =SUM(Q95:U95) -> 197640 | W95: =V95*12 -> 2371680 | Z95: 0
A96: D3-1 | B96: 관제·방재 | C96: 소방시설 일상점검 | D96: 소화기·옥내소화전 외관 점검 | E96: 작업 | F96: 공통 | G96: 1 | H96: 125 | I96: 개 | J96: 1 | K96: 매월 | L96: 125 | M96: 2.3958 | N96: 28.75 | O96: 0.0014 | P96: 32484.73 | Q96: 62686 | R96: 7702 | S96: 2363 | T96: 3638 | U96: 1439 | V96: =SUM(Q96:U96) -> 77828 | W96: =V96*12 -> 933936 | X96: 622.624 | Z96: 1
A97: D3-2 | B97: 관제·방재 | C97: 소방시설 일상점검 | D97: 방화문·피난통로 적치물 확인 | E97: 작업 | F97: 공통 | G97: 2 | H97: 18 | I97: 층 | J97: 1 | K97: 매주 | L97: 78.2143 | M97: 2.9982 | N97: 35.9786 | O97: 0.0017 | P97: 32485.003 | Q97: 78448 | R97: 9639 | S97: 2957 | T97: 4552 | U97: 1801 | V97: =SUM(Q97:U97) -> 97397 | W97: =V97*12 -> 1168764 | X97: 1245.2584 | Z97: 1
A98: D3-3 | B98: 관제·방재 | C98: 소방시설 일상점검 | D98: 유도등·비상조명 점등 확인 | E98: 작업 | F98: 공통 | G98: 0.5 | H98: 72 | I98: 개 | J98: 1 | K98: 매월 | L98: 72 | M98: 0.69 | N98: 8.28 | O98: 0.0004 | P98: 32485.507 | Q98: 18054 | R98: 2218 | S98: 680 | T98: 1048 | U98: 415 | V98: =SUM(Q98:U98) -> 22415 | W98: =V98*12 -> 268980 | X98: 311.3194 | Z98: 1
A99: E | B99: 고객사 업무 지원 | E99: 11개 업무 | M99: 118.6394 | N99: 1423.6726 | O99: 0.0677 | P99: 32484.997 | Q99: 3104173 | R99: 381423 | S99: 116992 | T99: 180134 | U99: 71278 | V99: =SUM(Q99:U99) -> 3854000 | W99: =V99*12 -> 46248000 | Z99: 0
A100: E1 | B100: 고객사 업무 지원 | C100: 안내·의전 | E100: 3개 업무 | M100: 9.3917 | N100: 112.7 | O100: 0.0054 | P100: 32484.862 | Q100: 245731 | R100: 30194 | S100: 9261 | T100: 14259 | U100: 5642 | V100: =SUM(Q100:U100) -> 305087 | W100: =V100*12 -> 3661044 | Z100: 0
A101: E1-1 | B101: 고객사 업무 지원 | C101: 안내·의전 | D101: VIP·귀빈 영접 및 차량 안내 | E101: 작업 | F101: 공통 | G101: 20 | H101: 2 | I101: 건 | J101: 4 | K101: 매월 | L101: 8 | M101: 3.0667 | N101: 36.8 | O101: 0.0017 | P101: 32484.783 | Q101: 80239 | R101: 9859 | S101: 3024 | T101: 4656 | U101: 1842 | V101: =SUM(Q101:U101) -> 99620 | W101: =V101*12 -> 1195440 | X101: 12452.5 | Z101: 1
A102: E1-2 | B102: 고객사 업무 지원 | C102: 안내·의전 | D102: 회의·행사장 출입 통제 | E102: 작업 | F102: 공통 | G102: 120 | H102: 2 | I102: 회 | J102: 1 | K102: 매월 | L102: 2 | M102: 4.6 | N102: 55.2 | O102: 0.0026 | P102: 32485 | Q102: 120358 | R102: 14789 | S102: 4536 | T102: 6984 | U102: 2764 | V102: =SUM(Q102:U102) -> 149431 | W102: =V102*12 -> 1793172 | X102: 74715.5 | Z102: 1
...

Sheet 업무량 산출내역
B1: 현대자동차 울산공장 정문 보안용역 도급업무 업무량 산출내역 (Workload) | R1: No. 261021-2703
B2: Location: 현대자동차 울산공장 정문 · 울산 북구 염포로 700 | R2: 작성일 2026. 10. 21
B3: 2027년 · 평일: 246일 / 주말: 104일 / 공휴일: 15일 · 주간 06~22시 · 야간 22~06시
B5: 도급 업무 (분류별 세부업무) | C5: 시간당 단가 | D5: Work scope (시간) | K5: Amount (노무비, 원) | R5: 비고
D6: TOTAL | E6: 주중 주간 | F6: 주중 야간 | G6: 주말 주간 | H6: 주말 야간 | I6: 공휴일 주간 | J6: 공휴일 야간 | K6: TOTAL | L6: 주중 주간 | M6: 주중 야간 | N6: 주말 주간 | O6: 주말 야간 | P6: 공휴일 주간 | Q6: 공휴일 야간
B7: A 출입통제 | C7: 29379.743 | D7: =SUM(E7:J7) -> 12108.542 | E7: 7806.2826 | F7: 1247.4927 | G7: 2142.3164 | H7: 527.3953 | I7: 308.9879 | J7: 76.0666 | K7: =SUM(L7:Q7) -> 355745844 | L7: 229346575 | M7: 36651018 | N7: 62940707 | O7: 15494740 | P7: 9077986 | Q7: 2234818 | T7: 0
B8: A1 정문 초소 | C8: 29379.744 | D8: =SUM(E8:J8) -> 8755.2 | E8: 4747.5205 | F8: 1153.2444 | G8: 2007.0818 | H8: 487.5505 | I8: 289.483 | J8: 70.3198 | K8: =SUM(L8:Q8) -> 257225532 | L8: 139480935 | M8: 33882026 | N8: 58967551 | O8: 14324109 | P8: 8504934 | Q8: 2065977 | T8: 0
B9: A1-1 정문 상주 근무 (24시간 경계·대기) | C9: 29379.745 | D9: =SUM(E9:J9) -> 5133.344 | E9: 2306.4888 | F9: 1153.2444 | G9: 975.101 | H9: 487.5505 | I9: 140.6396 | J9: 70.3198 | K9: =SUM(L9:Q9) -> 150816336 | L9: 67764052 | M9: 33882026 | N9: 28648217 | O9: 14324109 | P9: 4131955 | Q9: 2065977 | R9: 상주 시간 중 다른 업무를 뺀 경계·대기 | T9: 1
B10: A1-2-a 입문 차량 확인·출입 기록 | C10: 29379.736 | D10: =SUM(E10:J10) -> 377.568 | E10: 254.4705 | F10: 0 | G10: 107.581 | H10: 0 | I10: 15.5165 | J10: 0 | K10: =SUM(L10:Q10) -> 11092848 | L10: 7476276 | M10: 0 | N10: 3160702 | O10: 0 | P10: 455870 | Q10: 0 | T10: 1
B11: A1-2-b 출문 차량 적재물 확인 | C11: 29379.736 | D11: =SUM(E11:J11) -> 377.568 | E11: 254.4705 | F11: 0 | G11: 107.581 | H11: 0 | I11: 15.5165 | J11: 0 | K11: =SUM(L11:Q11) -> 11092848 | L11: 7476276 | M11: 0 | N11: 3160702 | O11: 0 | P11: 455870 | Q11: 0 | T11: 1
B12: A1-2-c 협력업체·납품차량 출입 통제 | C12: 29379.736 | D12: =SUM(E12:J12) -> 377.568 | E12: 254.4705 | F12: 0 | G12: 107.581 | H12: 0 | I12: 15.5165 | J12: 0 | K12: =SUM(L12:Q12) -> 11092848 | L12: 7476276 | M12: 0 | N12: 3160702 | O12: 0 | P12: 455870 | Q12: 0 | T12: 1
B13: A1-2-d 긴급·관공서 차량 우선 통행 안내 | C13: 29379.863 | D13: =SUM(E13:J13) -> 41.952 | E13: 28.2745 | F13: 0 | G13: 11.9534 | H13: 0 | I13: 1.7241 | J13: 0 | K13: =SUM(L13:Q13) -> 1232544 | L13: 830701 | M13: 0 | N13: 351191 | O13: 0 | P13: 50652 | Q13: 0 | T13: 1
B14: A1-3-a 방문객 신원확인·출입증 발급 | C14: 29379.748 | D14: =SUM(E14:J14) -> 839.04 | E14: 565.49 | F14: 0 | G14: 239.0689 | H14: 0 | I14: 34.4811 | J14: 0 | K14: =SUM(L14:Q14) -> 24650784 | L14: 16613953 | M14: 0 | N14: 7023785 | O14: 0 | P14: 1013046 | Q14: 0 | T14: 1
B15: A1-3-b 출입증 회수·방문 대장 정리 | C15: 29379.748 | D15: =SUM(E15:J15) -> 209.76 | E15: 141.3725 | F15: 0 | G15: 59.7672 | H15: 0 | I15: 8.6203 | J15: 0 | K15: =SUM(L15:Q15) -> 6162696 | L15: 4153488 | M15: 0 | N15: 1755946 | O15: 0 | P15: 253262 | Q15: 0 | T15: 1
B16: A1-3-c 사전 방문예약 확인·접견자 연락 | C16: 29379.72 | D16: =SUM(E16:J16) -> 167.808 | E16: 113.098 | F16: 0 | G16: 47.8138 | H16: 0 | I16: 6.8962 | J16: 0 | K16: =SUM(L16:Q16) -> 4930152 | L16: 3322787 | M16: 0 | N16: 1404756 | O16: 0 | P16: 202609 | Q16: 0 | T16: 1
B17: A1-4-a 반출입증 확인·물품 대조 | C17: 29379.74 | D17: =SUM(E17:J17) -> 293.664 | E17: 197.9215 | F17: 0 | G17: 83.6741 | H17: 0 | I17: 12.0684 | J17: 0 | K17: =SUM(L17:Q17) -> 8627772 | L17: 5814882 | M17: 0 | N17: 2458324 | O17: 0 | P17: 354566 | Q17: 0 | T17: 1
B18: A1-4-b 반입 금지물품(화기·위험물) 검색 | C18: 29379.72 | D18: =SUM(E18:J18) -> 419.52 | E18: 282.745 | F18: 0 | G18: 119.5345 | H18: 0 | I18: 17.2405 | J18: 0 | K18: =SUM(L18:Q18) -> 12325380 | L18: 8306968 | M18: 0 | N18: 3511889 | O18: 0 | P18: 506523 | Q18: 0 | T18: 1
B19: A1-5-a 택배 수령·보관 등록 | C19: 29379.748 | D19: =SUM(E19:J19) -> 279.68 | E19: 188.4967 | F19: 0 | G19: 79.6896 | H19: 0 | I19: 11.4937 | J19: 0 | K19: =SUM(L19:Q19) -> 8216928 | L19: 5537984 | M19: 0 | N19: 2341262 | O19: 0 | P19: 337682 | Q19: 0 | T19: 1
B20: A1-5-b 수령자 연락·인계 확인 | C20: 29379.761 | D20: =SUM(E20:J20) -> 195.776 | E20: 131.9477 | F20: 0 | G20: 55.7828 | H20: 0 | I20: 8.0456 | J20: 0 | K20: =SUM(L20:Q20) -> 5751852 | L20: 3876591 | M20: 0 | N20: 1638884 | O20: 0 | P20: 236377 | Q20: 0 | T20: 1
B21: A1-5-c 등기·우편물 분류 | C21: 29379.863 | D21: =SUM(E21:J21) -> 41.952 | E21: 28.2745 | F21: 0 | G21: 11.9534 | H21: 0 | I21: 1.7241 | J21: 0 | K21: =SUM(L21:Q21) -> 1232544 | L21: 830701 | M21: 0 | N21: 351191 | O21: 0 | P21: 50652 | Q21: 0 | T21: 1
B22: A2 후문·부출입구 | C22: 29379.74 | D22: =SUM(E22:J22) -> 3128.5714 | E22: 2890.9814 | F22: 94.2483 | G22: 85.4286 | H22: 39.8448 | I22: 12.3214 | J22: 5.7468 | K22: =SUM(L22:Q22) -> 91916616 | L22: 84936284 | M22: 2768992 | N22: 2509868 | O22: 1170631 | P22: 362000 | Q22: 168841 | T22: 0
B23: A2-1 후문 주간 상주 (07~19시) | C23: 29379.741 | D23: =SUM(E23:J23) -> 2688.91 | E23: 2688.91 | F23: 0 | G23: 0 | H23: 0 | I23: 0 | J23: 0 | K23: =SUM(L23:Q23) -> 78999480 | L23: 78999480 | M23: 0 | N23: 0 | O23: 0 | P23: 0 | Q23: 0 | R23: 상주 시간 중 다른 업무를 뺀 경계·대기 | T23: 1
B24: A2-2 출퇴근 시간 출입 통제 | C24: 29379.728 | D24: =SUM(E24:J24) -> 299.8214 | E24: 202.0714 | F24: 0 | G24: 85.4286 | H24: 0 | I24: 12.3214 | J24: 0 | K24: =SUM(L24:Q24) -> 8808672 | L24: 5936804 | M24: 0 | N24: 2509868 | O24: 0 | P24: 362000 | Q24: 0 | T24: 1
B25: A2-3 야간 출입문 시건·개방 | C25: 29379.748 | D25: =SUM(E25:J25) -> 139.84 | E25: 0 | F25: 94.2483 | G25: 0 | H25: 39.8448 | I25: 0 | J25: 5.7468 | K25: =SUM(L25:Q25) -> 4108464 | L25: 0 | M25: 2768992 | N25: 0 | O25: 1170631 | P25: 0 | Q25: 168841 | T25: 1
B26: A3 출입보안시스템 | C26: 29379.762 | D26: =SUM(E26:J26) -> 224.7702 | E26: 167.7806 | F26: 0 | G26: 49.806 | H26: 0 | I26: 7.1836 | J26: 0 | K26: =SUM(L26:Q26) -> 6603696 | L26: 4929356 | M26: 0 | N26: 1463288 | O26: 0 | P26: 211052 | Q26: 0 | T26: 0
B27: A3-1 출입카드 발급·회수·분실 처리 | C27: 29379.808 | D27: =SUM(E27:J27) -> 49.9702 | E27: 49.9702 | F27: 0 | G27: 0 | H27: 0 | I27: 0 | J27: 0 | K27: =SUM(L27:Q27) -> 1468116 | L27: 1468116 | M27: 0 | N27: 0 | O27: 0 | P27: 0 | Q27: 0 | T27: 1
B28: A3-2 출입기록 확인·이상 출입 조치 | C28: 29379.748 | D28: =SUM(E28:J28) -> 104.88 | E28: 70.6862 | F28: 0 | G28: 29.8836 | H28: 0 | I28: 4.3101 | J28: 0 | K28: =SUM(L28:Q28) -> 3081348 | L28: 2076744 | M28: 0 | N28: 877973 | O28: 0 | P28: 126631 | Q28: 0 | T28: 1
B29: A3-3 스피드게이트·출입통제기 작동 확인 | C29: 29379.748 | D29: =SUM(E29:J29) -> 69.92 | E29: 47.1242 | F29: 0 | G29: 19.9224 | H29: 0 | I29: 2.8734 | J29: 0 | K29: =SUM(L29:Q29) -> 2054232 | L29: 1384496 | M29: 0 | N29: 585315 | O29: 0 | P29: 84421 | Q29: 0 | T29: 1
B30: B 순찰 | C30: 29379.743 | D30: =SUM(E30:J30) -> 5015.472 | E30: 3242.7989 | F30: 254.4705 | G30: 1219.2516 | H30: 107.581 | I30: 175.8536 | J30: 15.5165 | K30: =SUM(L30:Q30) -> 147353280 | L30: 95272599 | M30: 7476276 | N30: 35821299 | O30: 3160702 | P30: 5166534 | Q30: 455870 | T30: 0
B31: B1 정기순찰 | C31: 29379.743 | D31: =SUM(E31:J31) -> 3817.632 | E31: 2318.5089 | F31: 254.4705 | G31: 980.1826 | H31: 107.581 | I31: 141.3725 | J31: 15.5165 | K31: =SUM(L31:Q31) -> 112161048 | L31: 68117198 | M31: 7476276 | N31: 28797514 | O31: 3160702 | P31: 4153488 | Q31: 455870 | T31: 0
B32: B1-1 외곽 울타리·담장 순찰 | C32: 29379.741 | D32: =SUM(E32:J32) -> 1678.08 | E32: 1130.9799 | F32: 0 | G32: 478.1379 | H32: 0 | I32: 68.9622 | J32: 0 | K32: =SUM(L32:Q32) -> 49301556 | L32: 33227898 | M32: 0 | N32: 14047567 | O32: 0 | P32: 2026091 | Q32: 0 | T32: 1
B33: B1-2 건물 내부 층별 순찰 | C33: 29379.748 | D33: =SUM(E33:J33) -> 1258.56 | E33: 848.235 | F33: 0 | G33: 358.6034 | H33: 0 | I33: 51.7216 | J33: 0 | K33: =SUM(L33:Q33) -> 36976176 | L33: 24920930 | M33: 0 | N33: 10535677 | O33: 0 | P33: 1519569 | Q33: 0 | T33: 1
B34: B1-3 주차장 순찰 | C34: 29379.744 | D34: =SUM(E34:J34) -> 503.424 | E34: 339.294 | F34: 0 | G34: 143.4414 | H34: 0 | I34: 20.6887 | J34: 0 | K34: =SUM(L34:Q34) -> 14790468 | L34: 9968370 | M34: 0 | N34: 4214270 | O34: 0 | P34: 607828 | Q34: 0 | T34: 1
B35: B1-4 야간 문단속·소등·전열기구 확인 | C35: 29379.736 | D35: =SUM(E35:J35) -> 377.568 | E35: 0 | F35: 254.4705 | G35: 0 | H35: 107.581 | I35: 0 | J35: 15.5165 | K35: =SUM(L35:Q35) -> 11092848 | L35: 0 | M35: 7476276 | N35: 0 | O35: 3160702 | P35: 0 | Q35: 455870 | T35: 1
... B103: F4 경비원 직무교육·소방훈련 참여 | C103: 29379.783 | D103: =SUM(E103:J103) -> 18.4 | E103: 18.4 | F103: 0 | G103: 0 | H103: 0 | I103: 0 | J103: 0 | K103: =SUM(L103:Q103) -> 540588 | L103: 540588 | M103: 0 | N103: 0 | O103: 0 | P103: 0 | Q103: 0 | T103: 1
B104: 소 계 (노무비) | C104: 29379.744 | D104: =SUMIF($T$7:$T$103,1,D7:D103) -> 21029.277 | E104: =SUMIF($T$7:$T$103,1,E7:E103) -> 14076.705 | F104: =SUMIF($T$7:$T$103,1,F7:F103) -> 1501.9632 | G104: =SUMIF($T$7:$T$103,1,G7:G103) -> 4128.5808 | H104: =SUMIF($T$7:$T$103,1,H7:H103) -> 634.9763 | I104: =SUMIF($T$7:$T$103,1,I7:I103) -> 595.4684 | J104: =SUMIF($T$7:$T$103,1,J7:J103) -> 91.5831 | K104: =SUMIF($T$7:$T$103,1,K7:K103) -> 617834760 | ... Q104: =SUMIF($T$7:$T$103,1,Q7:Q103) -> 2690688
B105: 경비 (피복·복리후생·교육·위험부담 등) | K105: 20737320
B106: 일반관리비 | K106: 31929480
B107: 기업이윤 · 단수조정 | K107: 12634440
B108: 도급비 합계 (연 · VAT 별도) | K108: =SUM(K104:K107) -> 683136000 | R108: = 견적서 계약기간 총액
B109: 월 환산 (÷12) | K109: =K108/12 -> 56928000
B110: 검증: 견적서 연 총액 · 차이 | K110: ='견적서'!I34 -> 683136000 | L110: =K108-K110 -> 0
B112: Work scope = 업무별 연간 업무시간을 평일·주말·공휴일 및 주간(06~22시)·야간(22~06시)으로 나눈 값입니다. 24시간 상주는 야간 8시간, 이름에 ‘야간’이 있는 업무는 전부 야간으로 봅니다.
B113: Amount = 업무별 노무비(직접+간접) 연간 배분액을 같은 비율로 나눈 금액이며, 경비·일반관리비·이윤을 더한 도급비 합계는 견적서 계약기간 총액과 같습니다.
B114: Produced by RatRae Choi – October 21, 2026 · Workload-Based Cost and Labor Estimation Method v1.6

Sheet _stec_data
A1: {"meta":{"client":"현대자동차 울산공장 정문","addr":"울산 북구 염포로 700","svc":"보안용역 도급업무","year":2027,"date":"2026-10-21","from":"2027-01-01","to":"2027-12-31","valid":"작성일로부터 1개월","mode":"new","branch":"부경본부","grpCo":"에스텍시스템","siteId":null,"lat":35.54323224110387,"lng":129.38463055208857,"geoName":"현대자동차 울산공장 정문","geoSrc":"카카오맵","geoInfo":{"src":"카카오맵","name":"현대자동차 울산공장 정문","type":"입출구","addr":"울산 북구 염포로 700","region":"울산 북구 양정동","postcode":"","osm":"","lat":35.54323224110387,"lng":129.38463055208857,"tags":{},"wiki":{"title":"정주영","extract":"정주영(鄭周永, 1915년 11월 25일~2001년 3월 21일)은 현대그룹 창업주로 대한민국의 기업인, 정치인이다. 제14대 국회의원을 지냈다. 본관은 하동(河東), 아호(雅號)는 아산(峨山)이다.","url":"https://ko.wikipedia.org/wiki/%EC%A0%95%EC%A3%BC%EC%98%81","thumb":"https://thumb.wikimedia.org/wikipedia/commons/thumb/c/c3/Chung_Ju-yung_%28Cropped%29.jpg/330px-Chung_Ju-yung_%28Cropped%29.jpg?utm_source=ko.wikipedia.org&utm_campaign=api&utm_content=thumbnail"},"loading":false,"category":"교통,수송 > 입출구","road":"울산 북구 염포로 700","jibun":"울산 북구 양정동 700","phone":"","kakaoUrl":"http://place.map.kakao.com/394445757","kid":"394445757"}},"roles":[{"id":"r1000ibzc","cat":"sec","rank":"실장","detail":"","gender":"M","shift":"day5_11","count":1,"wage":10700,"base":209,"ot":65,"night":0,"dayH":12,"rest":1,"watch":true,"pos":0,"adj":0,"duty":500000,"meal":0,"holDays":0,"leave":15,"laborDay":true,"retire":true,"bonusPct":0,"bonusBase":"basic","pensionPct":100,"special":"auto","uniform":30000,"months":12,"prev":0,"note":"","addonEx":false,"title":"실장"},{"id":"r1001vcmk","cat":"sec","rank":"팀장","detail":"","gender":"M","shift":"day5_11","count":3,"wage":10700,"base":209,"ot":65,"night":0,"dayH":12,"rest":1,"watch":true,"pos":0,"adj":0,"duty":300000,"meal":0,"holDays":0,"leave":15,"laborDay":true,"retire":true,"bonusPct":0,"bonusBase":"basic","pensionPct":100,"special":"auto","uniform":30000,"months":12,"prev":0,"note":"","addonEx":false,"title":"팀장"},{"id":"r1002p9ns","cat":"sec","rank":"요원","detail":"","gender":"M","shift":"s32","count":9,"wage":10700,"base":209,"ot":25,"night":82,"dayH":12,"rest":1,"watch":true,"pos":0,"adj":100000,"duty":0,"meal":0,"holDays":0,"leave":15,"laborDay":true,"retire":true,"bonusPct":0,"bonusBase":"basic","pensionPct":100,"special":"auto","uniform":30000,"months":12,"prev":0,"note":"","addonEx":false,"title":"요원"}],"vehicles":[],"equips":[],"others":[],"addonMode":"spread","addonMargin":true,"set":{"minWage":10700,"health":3.595,"ltc":13.14,"pension":5,"empSize":"o1000","emp":1.85,"indBase":0.8,"indCom":0.06,"ind":0.86,"wageClaim":0.09,"asb":0.006,"otGen":1.5,"otWatch":1,"nightRate":0.5,"specialExam":80000,"disOn":true,"disRate":3.1,"disBase":1360000,"disRatio":100,"gift":100000,"meeting":10000,"condol":4000,"reliefH":12,"reliefDays":1.8,"resTax":62500,"resSites":1,"edu":1,"eduFix":0,"risk":0.5,"riskFix":0,"leaveH":8,"ga":5,"profit":2,"profitBase":"direct","gaRound":true,"priceRound":"down3","vat":10,"coKey":"에스텍시스템","coName":"㈜에스텍시스템","coCeo":"이병화","coBizNo":"202-81-62708","coCorpNo":"110111-1627144","coAddr":"서울특별시 강남구 개포로 619, 8층(개포동, 서울강남우체국청사)","coType":"서비스","coItem":"시설경비·신변보호·기계경비·호송경비, 건물(시설)관리용역, 위생관리, 주차관리","coLic":"","coBranch":"에스텍 그룹","coPerson":"","coPersonTitle":"","coPersonTel":"","cond":"○ 견적 기준 : {연도}년 최저임금({최저시급}원) 및 통상시급 적용\n 단, 매년 법정최저임금(4대보험 포함) 등 관계법령이 변경될 경우 그 즉시 변경된 내용에 따라 적용합니다.\n○ 납입 조건 : 전자세금계산서 발행(당월 20일 청구, 익월 5일 납입, 현금결제)\n○ 손해배상 : 총 2억원 (당사의 귀책사유로 인한 사고 발생시 손해배상 책임보험에 의거)\n 1) 대인배상 : 1인 2천만원 한도 총 1억원(1사고당), 2) 대물배상 : 1억원한도(사고당)\n○ 상기 금액은 피복, 장비, 복리후생 등 포함한 금액입니다.\n○ 업무 수행에 필요한 근무실, 휴게실, 청소용품(소모품 포함), 집기류, 통신, 식사는 고객사 제공조건"},"wbe":{"v":"1.6","mode":"B","ind":"factory","job":"sec","year":2027,"H":1752.4,"add":0,"tree":[{"id":"n27","name":"출입통제","kids":[{"id":"n18","name":"정문 초소","kids":[{"id":"n1","name":"정문 상주 근무 (24시간 경계·대기)","kids":[],"t":{"min":1440,"qty":1,"unit":"개소","freq":1,"per":"d","type":"post","g":"C","pick":true}},{"id":"n6","name":"차량 출입관리","kids":[{"id":"n2","name":"입문 차량 확인·출입 기록","kids":[],"t":{"min":0.5,"qty":108,"unit":"대","freq":1,"per":"d","type":"work","g":"C","pick":true}},{"id":"n3","name":"출문 차량 적재물 확인","kids":[],"t":{"min":1,"qty":54,"unit":"대","freq":1,"per":"d","type":"work","g":"C","pick":true}},{"id":"n4","name":"협력업체·납품차량 출입 통제","kids":[],"t":{"min":3,"qty":18,"unit":"대","freq":1,"per":"d","type":"work","g":"C","pick":true}},{"id":"n5","name":"긴급·관공서 차량 우선 통행 안내","kids":[],"t":{"min":3,"qty":2,"unit":"대","freq":1,"per":"d","type":"work","g":"C","pick":true}}],"t":{"min":0,"qty":1,"unit":"회","freq":1,"per":"d","type":"work","g":"C"}},{"id":"n10","name":"방문객 관리","kids":[{"id":"n7","name":"방문객 신원확인·출입증 발급","kids":[],"t":{"min":2,"qty":60,"unit":"명","freq":1,"per":"d","type":"work","g":"C","pick":true}},{"id":"n8","name":"출입증 회수·방문 대장 정리","kids":[],"t":{"min":0.5,"qty":60,"unit":"명","freq":1,"per":"d","type":"work","g":"C","pick":true}},{"id":"n9","name":"사전 방문예약 확인·접견자 연락","kids":[],"t":{"min":1,"qty":24,"unit":"건","freq":1,"per":"d","type":"work","g":"C","pick":true}}],"t":{"min":0,"qty":1,"unit":"회","freq":1,"per":"d","type":"work","g":"C"}},{"id":"n13","name":"물품 반출입 관리","kids":[{"id":"n11","name":"반출입증 확인·물품 대조","kids":[],"t":{"min":3,"qty":14,"unit":"건","freq":1,"per":"d","type":"work","g":"C","pick":true}},{"id":"n12","name":"반입 금지물품(화기·위험물) 검색","kids":[],"t":{"min":1,"qty":60,"unit":"명","freq":1,"per":"d","type":"work","g":"C","pick":true}}],"t":{"min":0,"qty":1,"unit":"회","freq":1,"per":"d","type":"work","g":"C"}},{"id":"n17","name":"택배·우편 관리","kids":[{"id":"n14","name":"택배 수령·보관 등록","kids":[],"t":{"min":1,"qty":40,"unit":"건","freq":1,"per":"d","type":"work","g":"C","pick":true}},{"id":"n15","name":"수령자 연락·인계 확인","kids":[],"t":{"min":0.7,"qty":40,"unit":"건","freq":1,"per":"d","type":"work","g":"C","pick":true}},{"id":"n16","name":"등기·우편물 분류","kids":[],"t":{"min":0.5,"qty":12,"unit":"건","freq":1,"per":"d","type":"work","g":"C","pick":true}}],"t":{"min":0,"qty":1,"unit":"회","freq":1,"per":"d","type":"work","g":"C"}}],"t":{"min":0,"qty":1,"unit":"회","freq":1,"per":"d","type":"work","g":"C"}},{"id":"n22","name":"후문·부출입구","kids":[{"id":"n19","name":"후문 주간 상주 (07~19시)","kids":[],"t":{"min":720,"qty":1,"unit":"개소","freq":5,"per":"w","type":"post","g":"C","pick":true}},{"id":"n20","name":"출퇴근 시간 출입 통제","kids":[],"t":{"min":30,"qty":1,"unit":"개소","freq":10,"per":"w","type":"work","g":"C","pick":true}},{"id":"n21","name":"야간 출입문 시건·개방","kids":[],"t":{"min":10,"qty":1,"unit":"개소","freq":2,"per":"d","type":"work","g":"C","pick":true}}],"t":{"min":0,"qty":1,"unit":"회","freq":1,"per":"d","type":"work","g":"C"}},{"id":"n26","name":"출입보안시스템","kids":[{"id":"n23","name":"출입카드 발급·회수·분실 처리","kids":[],"t":{"min":5,"qty":10,"unit":"건","freq":1,"per":"w","type":"work","g":"C","pick":true}},{"id":"n24","name":"출입기록 확인·이상 출입 조치","kids":[],"t":{"min":15,"qty":1,"unit":"회","freq":1,"per":"d","type":"work","g":"C","pick":true}},{"id":"n25","name":"스피드게이트·출입통제기 작동 확인","kids":[],"t":{"min":5,"qty":2,"unit":"대","freq":1,"per":"d","type":"work","g":"C","pick":true}}],"t":{"min":0,"qty":1,"unit":"회","freq":1,"per":"d","type":"work","g":"C"}}],"t":{"min":0,"qty":1,"unit":"회","freq":1,"per":"d","type":"work","g":"C"}},{"id":"n37","name":"순찰","kids":[{"id":"n32","name":"정기순찰","kids":[{"id":"n28","name":"외곽 울타리·담장 순찰","kids":[],"t":{"min":30,"qty":2,"unit":"구역","freq":4,"per":"d","type":"work","g":"C","pick":true}},{"id":"n29","name":"건물 내부 층별 순찰","kids":[],"t":{"min":5,"qty":18,"unit":"층","freq":2,"per":"d","type":"work","g":"C","pick":true}},{"id":"n30","name":"주차장 순찰","kids":[],"t":{"min":8,"qty":3,"unit":"구역","freq":3,"per":"d","type":"work","g":"C","pick":true}},{"id":"n31","name":"야간 문단속·소등·전열기구 확인","kids":[],"t":{"min":3,"qty":18,"unit":"층","freq":1,"per":"d","type":"work","g":"C","pick":true}}],"t":{"min":0,"qty":1,"unit":"회","freq":1,"per":"d","type":"work","g":"C"}},{"id":"n36","name":"특별순찰","kids":[{"id":"n33","name":"취약지역·사각지대 집중 순찰","kids":[],"t":{"min":20,"qty":3,"unit":"개소","freq":2,"per":"d","type":"work","g":"C","pick":true}},{"id":"n34","name":"휴일·공휴일 전수 점검","kids":[],"t":{"min":30,"qty":6,"unit":"동","freq":8,"per":"m","type":"work","g":"C","pick":true}},{"id":"n35","name":"기상특보(태풍·폭우·폭설) 비상 순찰","kids":[],"t":{"min":60,"qty":6,"unit":"동","freq":4,"per":"y","type":"work","g":"C","pick":true}}],"t":{"min":0,"qty":1,"unit":"회","freq":1,"per":"d","type":"work","g":"C"}}],"t":{"min":0,"qty":1,"unit":"회","freq":1,"per":"d","type":"work","g":"C"}},{"id":"n67","name":"상황대처","kids":[{"id":"n42","name":"화재·소방","kids":[{"id":"n38","name":"화재경보 발생 시 현장 출동·확인","kids":[],"t":{"min":15,"qty":1,"unit":"건","freq":6,"per":"m","type":"work","g":"C","pick":true}},{"id":"n39","name":"비화재보 복구·수신기 리셋","kids":[],"t":{"min":10,"qty":1,"unit":"건","freq":4,"per":"m","type":"work","g":"C","pick":true}},{"id":"n40","name":"초기 소화·피난 유도","kids":[],"t":{"min":60,"qty":1,"unit":"건","freq":1,"per":"y","type":"work","g":"C","pick":true}},{"id":"n41","name":"소방서 신고·소방차 진입 안내","kids":[],"t":{"min":20,"qty":1,"unit":"건","freq":1,"per":"q","type":"work","g":"C","pick":true}}],"t":{"min":0,"qty":1,"unit":"회","freq":1,"per":"d","type":"work","g":"C"}},{"id":"n48","name":"응급·안전사고","kids":[{"id":"n43","name":"응급환자 응급조치·119 신고·인계","kids":[],"t":{"min":30,"qty":1,"unit":"건","freq":1,"per":"m","type":"work","g":"C","pick":true}},{"id":"n44","name":"AED·구급함 점검","kids":[],"t":{"min":5,"qty":6,"unit":"개소","freq":1,"per":"m","type":"work","g":"C","pick":true}},{"id":"n45","name":"산업재해 발생 시 현장 통제·보고","kids":[],"t":{"min":60,"qty":1,"unit":"건","freq":2,"per":"y","type":"work","g":"C","pick":true}},{"id":"n46","name":"승강기 갇힘 사고 대응·구조 연계","kids":[],"t":{"min":30,"qty":1,"unit":"건","freq":1,"per":"m","type":"work","g":"C","pick":true}},{"id":"n47","name":"넘어짐·추락 사고 현장 조치","kids":[],"t":{"min":20,"qty":1,"unit":"건","freq":1,"per":"m","type":"work","g":"C","pick":true}}],"t":{"min":0,"qty":1,"unit":"회","freq":1,"per":"d","type":"work","g":"C"}},{"id":"n53","name":"침입·도난·범죄","kids":[{"id":"n49","name":"무단침입 발생 시 대응·경찰 신고","kids":[],"t":{"min":40,"qty":1,"unit":"건","freq":2,"per":"m","type":"work","g":"C","pick":true}},{"id":"n50","name":"도난·분실 신고 접수·조사 협조","kids":[],"t":{"min":30,"qty":1,"unit":"건","freq":1,"per":"m","type":"work","g":"C","pick":true}},{"id":"n51","name":"CCTV 영상 확인·증거 보존 지원","kids":[],"t":{"min":30,"qty":1,"unit":"건","freq":4,"per":"m","type":"work","g":"C","pick":true}},{"id":"n52","name":"수상한 물건·거동 수상자 확인","kids":[],"t":{"min":15,"qty":1,"unit":"건","freq":8,"per":"m","type":"work","g":"C","pick":true}}],"t":{"min":0,"qty":1,"unit":"회","freq":1,"per":"d","type":"work","g":"C"}},{"id":"n58","name":"소란·민원·폭력","kids":[{"id":"n54","name":"소란·난동 발생 시 제지·분리","kids":[],"t":{"min":30,"qty":1,"unit":"건","freq":1,"per":"m","type":"work","g":"C","pick":true}},{"id":"n55","name":"주취자·노숙인 대응","kids":[],"t":{"min":20,"qty":1,"unit":"건","freq":1,"per":"m","type":"work","g":"C","pick":true}},{"id":"n56","name":"현장 민원 접수·응대","kids":[],"t":{"min":10,"qty":3,"unit":"건","freq":1,"per":"d","type":"work","g":"C","pick":true}},{"id":"n57","name":"집회·시위 발생 시 출입 통제","kids":[],"t":{"min":120,"qty":1,"unit":"건","freq":1,"per":"y","type":"work","g":"C","pick":true}}],"t":{"min":0,"qty":1,"unit":"회","freq":1,"per":"d","type":"work","g":"C"}},{"id":"n63","name":"설비 이상·재난","kids":[{"id":"n59","name":"정전 시 비상조명 확인·설비팀 연락","kids":[],"t":{"min":30,"qty":1,"unit":"건","freq":2,"per":"y","type":"work","g":"C","pick":true}},{"id":"n60","name":"누수·배관 파열 초동 조치","kids":[],"t":{"min":30,"qty":1,"unit":"건","freq":3,"per":"m","type":"work","g":"C","pick":true}},{"id":"n61","name":"가스·화학물질 누출 초동 조치","kids":[],"t":{"min":60,"qty":1,"unit":"건","freq":2,"per":"y","type":"work","g":"C","pick":true}},{"id":"n62","name":"태풍·폭우 대비 시설물 결박·배수구 점검","kids":[],"t":{"min":60,"qty":6,"unit":"동","freq":3,"per":"y","type":"work","g":"C","pick":true}}],"t":{"min":0,"qty":1,"unit":"회","freq":1,"per":"d","type":"work","g":"C"}},{"id":"n66","name":"교통·주차 사고","kids":[{"id":"n64","name":"구내 교통사고 현장 통제·보고","kids":[],"t":{"min":40,"qty":1,"unit":"건","freq":1,"per":"m","type":"work","g":"C","pick":true}},{"id":"n65","name":"통행 방해·불법주차 차량 조치","kids":[],"t":{"min":5,"qty":6,"unit":"건","freq":1,"per":"d","type":"work","g":"C","pick":true}}],"t":{"min":0,"qty":1,"unit":"회","freq":1,"per":"d","type":"work","g":"C"}}],"t":{"min":0,"qty":1,"unit":"회","freq":1,"per":"d","type":"work","g":"C"}},{"id":"n80","name":"관제·방재","kids":[{"id":"n71","name":"CCTV 관제","kids":[{"id":"n68","name":"CCTV 모니터링 (정문 초소 겸무)","kids":[],"t":{"min":10,"qty":1,"unit":"회","freq":6,"per":"d","type":"work","g":"C","pick":true}},{"id":"n69","name":"CCTV 녹화 상태·카메라 점검","kids":[],"t":{"min":1,"qty":120,"unit":"대","freq":1,"per":"w","type":"work","g":"C","pick":true}},{"id":"n70","name":"영상 열람·반출 요청 처리","kids":[],"t":{"min":30,"qty":1,"unit":"건","freq":4,"per":"m","type":"work","g":"C","pick":true}}],"t":{"min":0,"qty":1,"unit":"회","freq":1,"per":"d","type":"work","g":"C"}},{"id":"n75","name":"방재·설비 감시","kids":[{"id":"n72","name":"화재수신기·방재반 감시 기록","kids":[],"t":{"min":10,"qty":1,"unit":"회","freq":3,"per":"d","type":"work","g":"C","pick":true}},{"id":"n73","name":"무인경비·침입감지 알람 확인","kids":[],"t":{"min":10,"qty":1,"unit":"건","freq":2,"per":"d","type":"work","g":"C","pick":true}},{"id":"n74","name":"비상방송·안내방송 송출","kids":[],"t":{"min":5,"qty":1,"unit":"회","freq":1,"per":"d","type":"work","g":"C","pick":true}}],"t":{"min":0,"qty":1,"unit":"회","freq":1,"per":"d","type":"work","g":"C"}},{"id":"n79","name":"소방시설 일상점검","kids":[{"id":"n76","name":"소화기·옥내소화전 외관 점검","kids":[],"t":{"min":1,"qty":125,"unit":"개","freq":1,"per":"m","type":"work","g":"C","pick":true}},{"id":"n77","name":"방화문·피난통로 적치물 확인","kids":[],"t":{"min":2,"qty":18,"unit":"층","freq":1,"per":"w","type":"work","g":"C","pick":true}},{"id":"n78","name":"유도등·비상조명 점등 확인","kids":[],"t":{"min":0.5,"qty":72,"unit":"개","freq":1,"per":"m","type":"work","g":"C","pick":true}}],"t":{"min":0,"qty":1,"unit":"회","freq":1,"per":"d","type":"work","g":"C"}}],"t":{"min":0,"qty":1,"unit":"회","freq":1,"per":"d","type":"work","g":"C"}},{"id":"n96","name":"고객사 업무 지원","kids":[{"id":"n84","name":"안내·의전","kids":[{"id":"n81","name":"VIP·귀빈 영접 및 차량 안내","kids":[],"t":{"min":20,"qty":2,"unit":"건","freq":4,"per":"m","type":"work","g":"C","pick":true}},{"id":"n82","name":"회의·행사장 출입 통제","kids":[],"t":{"min":120,"qty":2,"unit":"회","freq":1,"per":"m","type":"work","g":"C","pick":true}},{"id":"n83","name":"행사 주차 안내·교통 정리","kids":[],"t":{"min":90,"qty":1,"unit":"회","freq":1,"per":"m","type":"work","g":"C","pick":true}}],"t":{"min":0,"qty":1,"unit":"회","freq":1,"per":"d","type":"work","g":"C"}},{"id":"n89","name":"행정 지원","kids":[{"id":"n85","name":"열쇠·출입카드 보관·대여 관리","kids":[],"t":{"min":2,"qty":20,"unit":"건","freq":1,"per":"d","type":"work","g":"C","pick":true}},{"id":"n86","name":"분실물·습득물 접수·보관·반환","kids":[],"t":{"min":5,"qty":2,"unit":"건","freq":1,"per":"d","type":"work","g":"C","pick":true}},{"id":"n87","name":"공지문·게시물 부착·회수","kids":[],"t":{"min":20,"qty":6,"unit":"동","freq":2,"per":"m","type":"work","g":"C","pick":true}},{"id":"n88","name":"고객사 요청 문서·물품 전달","kids":[],"t":{"min":15,"qty":2,"unit":"건","freq":1,"per":"d","type":"work","g":"C","pick":true}}],"t":{"min":0,"qty":1,"unit":"회","freq":1,"per":"d","type":"work","g":"C"}},{"id":"n92","name":"시설·환경 지원","kids":[{"id":"n90","name":"제설·염화칼슘 살포 지원","kids":[],"t":{"min":60,"qty":2,"unit":"구역","freq":3,"per":"y","type":"work","g":"C","pick":true}},{"id":"n91","name":"시설 고장 접수·설비팀 연계","kids":[],"t":{"min":10,"qty":2,"unit":"건","freq":1,"per":"d","type":"work","g":"C","pick":true}}],"t":{"min":0,"qty":1,"unit":"회","freq":1,"per":"d","type":"work","g":"C"}},{"id":"n95","name":"업종별 특수 지원","kids":[{"id":"n93","name":"출퇴근 통근버스 통제","kids":[],"t":{"min":30,"qty":2,"unit":"회","freq":5,"per":"w","type":"work","g":"C","pick":true}},{"id":"n94","name":"협력업체 작업허가서 확인","kids":[],"t":{"min":5,"qty":10,"unit":"건","freq":5,"per":"w","type":"work","g":"C","pick":true}}],"t":{"min":0,"qty":1,"unit":"회","freq":1,"per":"d","type":"work","g":"C"}}],"t":{"min":0,"qty":1,"unit":"회","freq":1,"per":"d","type":"work","g":"C"}},{"id":"n101","name":"보고·행정·교육","kids":[{"id":"n97","name":"근무일지·인수인계","kids":[],"t":{"min":15,"qty":2,"unit":"개소","freq":3,"per":"d","type":"work","g":"C","pick":true}},{"id":"n98","name":"사건·사고 보고서 작성","kids":[],"t":{"min":30,"qty":1,"unit":"건","freq":6,"per":"m","type":"work","g":"C","pick":true}},{"id":"n99","name":"고객사 일일 업무보고","kids":[],"t":{"min":20,"qty":1,"unit":"회","freq":1,"per":"d","type":"work","g":"C","pick":true}},{"id":"n100","name":"경비원 직무교육·소방훈련 참여","kids":[],"t":{"min":240,"qty":1,"unit":"회","freq":1,"per":"q","type":"work","g":"C","pick":true}}],"t":{"min":0,"qty":1,"unit":"회","freq":1,"per":"d","type":"work","g":"C"}}],"params":{"days":30.4,"allow":15,"week":40,"loss":6,"wage":10700,"otH":0,"nightH":0,"allowance":0,"bonus":0,"pension":5,"health":3.595,"ltc":13.139999999999999,"emp":1.8499999999999999,"acc":0.86,"expense":430000,"mgmt":5,"profit":5,"plan":"precise","cFull":10,"cPartN":0,"cPartH":20}}} | B1: STEC-QUOTE v1 | C1: 3583
