Workbook
Name 부대비용월계: '6. 부대비용'!$D$10

Sheet 1. 표지
F3: 에스텍베스트
A5: 공장 ○○사업장 보안용역 도급업무
A6: 見 積 書
A7: 2027년 용역 도급 견적서 · Q U O T A T I O N
A30: 투입 인력 구성
A35: ="보안(경비) "&(N('2. 견적서'!F28)+N('2. 견적서'!F29)+N('2. 견적서'!F30))&"명"&" ("&"경비원 "&(N('2. 견적서'!F28))&" · "&"단시간 경비원 "&(N('2. 견적서'!F29))&" · "&"— "&(N('2. 견적서'!F30))&")" -> 보안(경비) 11명 (경비원 10 · 단시간 경비원 1 · — 0)
B37: 수 신 | D37: 공장 ○○사업장 貴中
B38: 용 역 명 | D38: 보안용역 도급업무
B39: 용역기간 | D39: 2027. 1. 1 ~ 2027. 12. 31 (12개월)
B40: 견적금액 | D40: ="월 "&TEXT('2. 견적서'!I31,"#,##0")&"원 (VAT 별도) · "&'2. 견적서'!F31&"명" -> 월 34,603,000원 (VAT 별도) · 11명
B41: 전년 대비 | D41: =IF(N('2. 견적서'!G31)=0,"신규 견적 · 전년 대비 해당 없음","전년 월 "&TEXT('2. 견적서'!G31,"#,##0")&"원 → 월 "&TEXT('2. 견적서'!I31,"#,##0")&"원 ("&IF('2. 견적서'!I31>='2. 견적서'!G31,"▲ ","▼ ")&TEXT(ABS('2. 견적서'!I31/'2. 견적서'!G31-1)*100,"0.0")&"%)") -> 신규 견적 · 전년 대비 해당 없음
B42: 견적기준 | D42: 2027년 최저임금 10,700원 · 4대보험 에스텍시스템 요율
D45: 견적 담당
D47: 에스텍베스트
A50: 2026년 10월
F52: ㈜에스텍베스트
A54: 부산시 부산진구 중앙대로 920, 2층(설비건설회관) · 경찰청 허가 제243호 / 위생관리 신고증 제139호

Sheet 2. 견적서
D1: 견 적 서 | J1: No. 261029-0425
J2: 작성일 2026. 10. 29
D3: Q U O T A T I O N · 2027년 견적
A7: 공장 ○○사업장 貴中 | F7: 등록번호 | G7: 607-81-56605
A8: 용 역 명 | C8: 보안용역 도급업무 | F8: 상 호 | G8: ㈜에스텍베스트 | H8: 대 표 | I8: 정규상 (인)
A9: 용역기간 | C9: 2027. 1. 1 ~ 2027. 12. 31 (12개월) | F9: 주 소 | G9: 부산시 부산진구 중앙대로 920, 2층(설비건설회관)
A10: 유효기간 | C10: 작성일로부터 1개월 | F10: 업 태 | G10: 서비스 | H10: 종 목 | I10: 경비용역,시설관리,위생관리
A11: 사 업 장 | F11: 허가·신고 | G11: 경찰청 허가 제243호 / 위생관리 신고증 제139호
A12: 귀사의 무궁한 발전을 기원하며, 아래와 같이 견적합니다. | F12: 담 당 | G12: 에스텍베스트
A14: 견적금액 · 월 (VAT 별도) | G14: ="부가세 포함 월 "&TEXT(I33,"#,##0")&"원 · "&F31&"명 / 평균 "&TEXT(IF(N(F31)=0,0,SUM(I28:I30)/F31),"#,##0")&"원" -> 부가세 포함 월 38,063,300원 · 11명 / 평균 3,145,727원
A15: =I31 -> 34603000 | D15: ="일금 "&IF(ROUND(ABS(N(I31)),0)=0,"영",CHOOSE(VALUE(MID(TEXT(ROUND(ABS(N(I31)),0),"000000000000"),1,1))+1,"","일","이","삼","사","오","육","칠","팔","구")&IF(MID(TEXT(ROUND(ABS(N(I31)),0),"000000000000"),1,1)="0","","천")&CHOOSE(VALUE(MID(TEXT(ROUND(ABS(N(I31)),0),"000000000000"),2,1))+1,"","일","이","삼","사","오","육","칠","팔","구")&IF(MID(TEXT(ROUND(ABS(N(I31)),0),"000000000000"),2,1)="0","","백")&CHOOSE(VALUE(MID(TEXT(ROUND(ABS(N(I31)),0),"000000000000"),3,1))+1,"","일","이","삼","사","오","육","칠","팔","구")&IF(MID(TEXT(ROUND(ABS(N(I31)),0),"000000000000"),3,1)="0","","십")&CHOOSE(VALUE(MID(TEXT(ROUND(ABS(N(I31)),0),"000000000000"),4,1))+1,"","일","이","삼","사","오","육","칠","팔","구")&IF(MID(TEXT(ROUND(ABS(N(I31)),0),"000000000000"),4,1)="0","","")&IF(MID(TEXT(ROUND(ABS(N(I31)),0),"000000000000"),1,4)="0000","","억")&CHOOSE(VALUE(MID(TEXT(ROUND(ABS(N(I31)),0),"000000000000"),5,1))+1,"","일","이","삼","사","오","육","칠","팔","구")&IF(MID(TEXT(ROUND(ABS(N(I31)),0),"000000000000"),5,1)="0","","천")&CHOOSE(VALUE(MID(TEXT(ROUND(ABS(N(I31)),0),"000000000000"),6,1))+1,"","일","이","삼","사","오","육","칠","팔","구")&IF(MID(TEXT(ROUND(ABS(N(I31)),0),"000000000000"),6,1)="0","","백")&CHOOSE(VALUE(MID(TEXT(ROUND(ABS(N(I31)),0),"000000000000"),7,1))+1,"","일","이","삼","사","오","육","칠","팔","구")&IF(MID(TEXT(ROUND(ABS(N(I31)),0),"000000000000"),7,1)="0","","십")&CHOOSE(VALUE(MID(TEXT(ROUND(ABS(N(I31)),0),"000000000000"),8,1))+1,"","일","이","삼","사","오","육","칠","팔","구")&IF(MID(TEXT(ROUND(ABS(N(I31)),0),"000000000000"),8,1)="0","","")&IF(MID(TEXT(ROUND(ABS(N(I31)),0),"000000000000"),5,4)="0000","","만")&CHOOSE(VALUE(MID(TEXT(ROUND(ABS(N(I31)),0),"000000000000"),9,1))+1,"","일","이","삼","사","오","육","칠","팔","구")&IF(MID(TEXT(ROUND(ABS(N(I31)),0),"000000000000"),9,1)="0","","천")&CHOOSE(VALUE(MID(TEXT(ROUND(ABS(N(I31)),0),"000000000000"),10,1))+1,"","일","이","삼","사","오","육","칠","팔","구")&IF(MID(TEXT(ROUND(ABS(N(I31)),0),"000000000000"),10,1)="0","","백")&CHOOSE(VALUE(MID(TEXT(ROUND(ABS(N(I31)),0),"000000000000"),11,1))+1,"","일","이","삼","사","오","육","칠","팔","구")&IF(MID(TEXT(ROUND(ABS(N(I31)),0),"000000000000"),11,1)="0","","십")&CHOOSE(VALUE(MID(TEXT(ROUND(ABS(N(I31)),0),"000000000000"),12,1))+1,"","일","이","삼","사","오","육","칠","팔","구")&IF(MID(TEXT(ROUND(ABS(N(I31)),0),"000000000000"),12,1)="0","",""))&"원정" -> 일금 삼천사백육십만삼천원정 | G15: ="계약기간 12개월 총액 "&TEXT(I34,"#,##0")&"원 (VAT 별도)" -> 계약기간 12개월 총액 274,524,000원 (VAT 별도)
A17: ■ 투입 인력 구성
A22: ="보안(경비) "&(N(F28)+N(F29)+N(F30))&"명" -> 보안(경비) 11명
A23: ="경비원 "&(N(F28))&" · "&"단시간 경비원 "&(N(F29))&" · "&"— "&(N(F30)) -> 경비원 10 · 단시간 경비원 1 · — 0
A24: ="월 "&TEXT(N(I28)+N(I29)+N(I30),"#,##0")&"원" -> 월 34,603,000원
A26: ■ 견적 내역 | K26: (단위: 명, 원 / VAT 별도)
A27: No | B27: 직종 | C27: 직책 | D27: 근무지·직무 | E27: 운영형태 | F27: 인원 | G27: 2026년 단가 | H27: 2027년 단가 | I27: 월 합계 | J27: 인상액 | K27: 비고
A28: 1 | B28: 보안 | C28: 경비원 | E28: 주간 주5일 (8h/일) | F28: ='5. 산출내역서'!C10 -> 10 | H28: ='5. 산출내역서'!C73 -> 3216000 | I28: =F28*H28 -> 32160000 | J28: =IF(N(G28)>0,I28-F28*G28,"") | K28: =IF(N(G28)>0,IF(H28>=G28,"▲ ","▼ ")&TEXT(ABS(H28/G28-1)*100,"0.0")&"%","")
A29: 2 | B29: 보안 | C29: 단시간 경비원 | E29: 단시간 (주 29.5h) | F29: ='5. 산출내역서'!D10 -> 1 | H29: ='5. 산출내역서'!D73 -> 2443000 | I29: =F29*H29 -> 2443000 | J29: =IF(N(G29)>0,I29-F29*G29,"") | K29: =IF(N(G29)>0,IF(H29>=G29,"▲ ","▼ ")&TEXT(ABS(H29/G29-1)*100,"0.0")&"%","")
A30: 3 | F30: ='5. 산출내역서'!E10 -> 0 | H30: ='5. 산출내역서'!E73 -> 3216000 | I30: =F30*H30 -> 0 | J30: =IF(N(G30)>0,I30-F30*G30,"") | K30: =IF(N(G30)>0,IF(H30>=G30,"▲ ","▼ ")&TEXT(ABS(H30/G30-1)*100,"0.0")&"%","")
A31: 월 합계 | F31: =SUM(F28:F30) -> 11 | G31: =SUMPRODUCT(F28:F30,G28:G30) -> 0 | I31: =SUM(I28:I30) -> 34603000 | J31: =IF(N(G31)=0,"",I31-G31) | K31: =IFERROR(SUMPRODUCT((G28:G30>0)*F28:F30*H28:H30)/G31-1,"")
A32: 부가가치세 (10%) | I32: =ROUND(I31*0.1,0) -> 3460300
A33: 월 총계 (VAT 포함) | I33: =I31+I32 -> 38063300
A34: 계약기간 총액 (VAT 별도 · 12개월) | I34: =I31*12 -> 415236000
A36: ■ 견적 조건
A37: ○ 견적 기준 : 2027년 최저임금(10,700원) 및 통상시급 적용
A38: 단, 매년 법정최저임금(4대보험 포함) 등 관계법령이 변경될 경우 그 즉시 변경된 내용에 따라 적용합니다.
A39: ○ 납입 조건 : 전자세금계산서 발행(당월 20일 청구, 익월 5일 납입, 현금결제)
A40: ○ 손해배상 : 총 2억원 (당사의 귀책사유로 인한 사고 발생시 손해배상 책임보험에 의거)
A41: 1) 대인배상 : 1인 2천만원 한도 총 1억원(1사고당), 2) 대물배상 : 1억원한도(사고당)
A42: ○ 상기 금액은 피복, 장비, 복리후생 등 포함한 금액입니다.
A43: ○ 업무 수행에 필요한 근무실, 휴게실, 청소용품(소모품 포함), 집기류, 통신, 식사는 고객사 제공조건
C46: ㈜에스텍베스트 부산시 부산진구 중앙대로 920, 2층(설비건설회관) | J46: 견적 담당 에스텍베스트

Sheet 3. 업무별 비용 배분
A1: 업무별 비용 배분 (업무량 기반) | X1: No. 261029-0425
X2: 작성일 2026. 10. 29
A3: 공장 ○○사업장 · 보안용역 도급업무 · 단위: 원, VAT 별도
A5: ■ 산정 요약 | N5: ■ 견적 금액 구성 (월)
A6: 산정 방식 | D6: A. 업무량 기반 비용 및 인력 산정 | N6: 직접노무비 ① (산출내역서 45행) | Q6: 27457010 | R6: 0.7935
A7: 사업장 유형 · 직종 | D7: 공장 · 보안 | N7: 간접노무비 ② (산출내역서 55행) | Q7: 3533478 | R7: 0.1021
A8: 견적 연도 | D8: 2027년 | N8: 경비 (산출내역서 67행) | Q8: 1345040 | R8: 0.0389
A9: 월 총 업무시간 (h) | D9: 1752.4397 | N9: 일반관리비 (산출내역서 69행) | Q9: 1616820 | R9: 0.0467
A10: 업무량 기준 필요 인원 (명) | D10: 10.7261 | N10: 기업이윤 · 단수조정 (65행 + 견적단가 1,000원 미만 절사) | Q10: 650652 | R10: 0.0188
A11: 견적 인원 (명) | D11: 11 | N11: 월 합계 (= 견적서 월 합계) | Q11: =SUM(Q6:Q10) -> 34603000 | R11: 1
A12: 견적 인원 월 근무시간 (h) | D12: 1757.8
A13: 1인 업무부하 (업무시간 ÷ 근무시간) | D13: 0.997
A14: 견적 월 합계 (원) | D14: 34603000
A15: 계약기간 총액 (원) | D15: 415236000
A16: 시간당 단가 (월 합계 ÷ 월 업무시간) | D16: 19745.615
A17: 원 견적 인원 (명) | D17: 11
A18: 수행 가능 업무량 (원 견적 인원 기준) | D18: 1
A19: 부족 인력 (명) | D19: 0
A20: 부족 인력 반영 | D20: 해당 없음
A22: 코드 | B22: 대분류 | C22: 중분류 | D22: 업무명 | E22: 구분 | F22: 투입 | G22: 단위시간(분) | H22: 수량 | I22: 단위 | J22: 빈도 | K22: 주기 | L22: 월 횟수 | M22: 월 업무시간(h) | N22: 연 업무시간(h) | O22: 시간 비중 | P22: 시간당 단가 | Q22: 직접노무비 | R22: 간접노무비 | S22: 경비 | T22: 일반관리비 | U22: 이윤·단수 | V22: 월 배분액 | W22: 연 배분액 | X22: 단위당 단가
A23: A | B23: 출입통제 | E23: 19개 업무 | M23: 1009.0451 | N23: 12108.542 | O23: 0.5758 | P23: 19745.615 | Q23: 15809596 | R23: 2034558 | S23: 774467 | T23: 930955 | U23: 374641 | V23: =SUM(Q23:U23) -> 19924217 | W23: =V23*12 -> 239090604 | Z23: 0
A24: A1 | B24: 출입통제 | C24: 정문 초소 | E24: 13개 업무 | M24: 729.6 | N24: 8755.2 | O24: 0.4163 | P24: 19745.613 | Q24: 11431283 | R24: 1471108 | S24: 559986 | T24: 673135 | U24: 270887 | V24: =SUM(Q24:U24) -> 14406399 | W24: =V24*12 -> 172876788 | Z24: 0
A25: A1-1 | B25: 출입통제 | C25: 정문 초소 | D25: 정문 상주 근무 (24시간 경계·대기) | E25: 상주(잔여) | F25: 공통 | G25: 1440 | H25: 1 | I25: 개소 | J25: 1 | K25: 매일 | L25: 30.4 | M25: 427.7787 | N25: 5133.344 | O25: 0.2441 | P25: 19745.615 | Q25: 6702384 | R25: 862538 | S25: 328331 | T25: 394673 | U25: 158827 | V25: =SUM(Q25:U25) -> 8446753 | W25: =V25*12 -> 101361036 | X25: 277853.72 | Z25: 1
A26: A1-2-a | B26: 출입통제 | C26: 정문 초소 | D26: 입문 차량 확인·출입 기록 | E26: 작업 | F26: 공통 | G26: 0.5 | H26: 108 | I26: 대 | J26: 1 | K26: 매일 | L26: 3283.2 | M26: 31.464 | N26: 377.568 | O26: 0.018 | P26: 19745.646 | Q26: 492974 | R26: 63442 | S26: 24150 | T26: 29029 | U26: 11682 | V26: =SUM(Q26:U26) -> 621277 | W26: =V26*12 -> 7455324 | X26: 189.2291 | Z26: 1
A27: A1-2-b | B27: 출입통제 | C27: 정문 초소 | D27: 출문 차량 적재물 확인 | E27: 작업 | F27: 공통 | G27: 1 | H27: 54 | I27: 대 | J27: 1 | K27: 매일 | L27: 1641.6 | M27: 31.464 | N27: 377.568 | O27: 0.018 | P27: 19745.614 | Q27: 492974 | R27: 63442 | S27: 24149 | T27: 29029 | U27: 11682 | V27: =SUM(Q27:U27) -> 621276 | W27: =V27*12 -> 7455312 | X27: 378.4576 | Z27: 1
A28: A1-2-c | B28: 출입통제 | C28: 정문 초소 | D28: 협력업체·납품차량 출입 통제 | E28: 작업 | F28: 공통 | G28: 3 | H28: 18 | I28: 대 | J28: 1 | K28: 매일 | L28: 547.2 | M28: 31.464 | N28: 377.568 | O28: 0.018 | P28: 19745.614 | Q28: 492974 | R28: 63442 | S28: 24149 | T28: 29029 | U28: 11682 | V28: =SUM(Q28:U28) -> 621276 | W28: =V28*12 -> 7455312 | X28: 1135.3728 | Z28: 1
A29: A1-2-d | B29: 출입통제 | C29: 정문 초소 | D29: 긴급·관공서 차량 우선 통행 안내 | E29: 작업 | F29: 공통 | G29: 3 | H29: 2 | I29: 대 | J29: 1 | K29: 매일 | L29: 60.8 | M29: 3.496 | N29: 41.952 | O29: 0.002 | P29: 19745.423 | Q29: 54775 | R29: 7049 | S29: 2683 | T29: 3225 | U29: 1298 | V29: =SUM(Q29:U29) -> 69030 | W29: =V29*12 -> 828360 | X29: 1135.3618 | Z29: 1
A30: A1-3-a | B30: 출입통제 | C30: 정문 초소 | D30: 방문객 신원확인·출입증 발급 | E30: 작업 | F30: 공통 | G30: 2 | H30: 60 | I30: 명 | J30: 1 | K30: 매일 | L30: 1824 | M30: 69.92 | N30: 839.04 | O30: 0.0399 | P30: 19745.609 | Q30: 1095498 | R30: 140981 | S30: 53665 | T30: 64509 | U30: 25960 | V30: =SUM(Q30:U30) -> 1380613 | W30: =V30*12 -> 16567356 | X30: 756.915 | Z30: 1
A31: A1-3-b | B31: 출입통제 | C31: 정문 초소 | D31: 출입증 회수·방문 대장 정리 | E31: 작업 | F31: 공통 | G31: 0.5 | H31: 60 | I31: 명 | J31: 1 | K31: 매일 | L31: 1824 | M31: 17.48 | N31: 209.76 | O31: 0.01 | P31: 19745.538 | Q31: 273874 | R31: 35245 | S31: 13416 | T31: 16127 | U31: 6490 | V31: =SUM(Q31:U31) -> 345152 | W31: =V31*12 -> 4141824 | X31: 189.2281 | Z31: 1
A32: A1-3-c | B32: 출입통제 | C32: 정문 초소 | D32: 사전 방문예약 확인·접견자 연락 | E32: 작업 | F32: 공통 | G32: 1 | H32: 24 | I32: 건 | J32: 1 | K32: 매일 | L32: 729.6 | M32: 13.984 | N32: 167.808 | O32: 0.008 | P32: 19745.638 | Q32: 219100 | R32: 28196 | S32: 10733 | T32: 12902 | U32: 5192 | V32: =SUM(Q32:U32) -> 276123 | W32: =V32*12 -> 3313476 | X32: 378.4581 | Z32: 1
A33: A1-4-a | B33: 출입통제 | C33: 정문 초소 | D33: 반출입증 확인·물품 대조 | E33: 작업 | F33: 공통 | G33: 3 | H33: 14 | I33: 건 | J33: 1 | K33: 매일 | L33: 425.6 | M33: 24.472 | N33: 293.664 | O33: 0.014 | P33: 19745.587 | Q33: 383424 | R33: 49343 | S33: 18783 | T33: 22578 | U33: 9086 | V33: =SUM(Q33:U33) -> 483214 | W33: =V33*12 -> 5798568 | X33: 1135.3712 | Z33: 1
A34: A1-4-b | B34: 출입통제 | C34: 정문 초소 | D34: 반입 금지물품(화기·위험물) 검색 | E34: 작업 | F34: 공통 | G34: 1 | H34: 60 | I34: 명 | J34: 1 | K34: 매일 | L34: 1824 | M34: 34.96 | N34: 419.52 | O34: 0.0199 | P34: 19745.624 | Q34: 547749 | R34: 70491 | S34: 26833 | T34: 32254 | U34: 12980 | V34: =SUM(Q34:U34) -> 690307 | W34: =V34*12 -> 8283684 | X34: 378.4578 | Z34: 1
A35: A1-5-a | B35: 출입통제 | C35: 정문 초소 | D35: 택배 수령·보관 등록 | E35: 작업 | F35: 공통 | G35: 1 | H35: 40 | I35: 건 | J35: 1 | K35: 매일 | L35: 1216 | M35: 23.3067 | N35: 279.68 | O35: 0.0133 | P35: 19745.638 | Q35: 365166 | R35: 46994 | S35: 17889 | T35: 21503 | U35: 8653 | V35: =SUM(Q35:U35) -> 460205 | W35: =V35*12 -> 5522460 | X35: 378.4581 | Z35: 1
A36: A1-5-b | B36: 출입통제 | C36: 정문 초소 | D36: 수령자 연락·인계 확인 | E36: 작업 | F36: 공통 | G36: 0.7 | H36: 40 | I36: 건 | J36: 1 | K36: 매일 | L36: 1216 | M36: 16.3147 | N36: 195.776 | O36: 0.0093 | P36: 19745.607 | Q36: 255616 | R36: 32896 | S36: 12522 | T36: 15052 | U36: 6057 | V36: =SUM(Q36:U36) -> 322143 | W36: =V36*12 -> 3865716 | X36: 264.9202 | Z36: 1
A37: A1-5-c | B37: 출입통제 | C37: 정문 초소 | D37: 등기·우편물 분류 | E37: 작업 | F37: 공통 | G37: 0.5 | H37: 12 | I37: 건 | J37: 1 | K37: 매일 | L37: 364.8 | M37: 3.496 | N37: 41.952 | O37: 0.002 | P37: 19745.423 | Q37: 54775 | R37: 7049 | S37: 2683 | T37: 3225 | U37: 1298 | V37: =SUM(Q37:U37) -> 69030 | W37: =V37*12 -> 828360 | X37: 189.227 | Z37: 1
A38: A2 | B38: 출입통제 | C38: 후문·부출입구 | E38: 3개 업무 | M38: 260.7143 | N38: 3128.5714 | O38: 0.1488 | P38: 19745.623 | Q38: 4084840 | R38: 525683 | S38: 200105 | T38: 240538 | U38: 96800 | V38: =SUM(Q38:U38) -> 5147966 | W38: =V38*12 -> 61775592 | Z38: 0
A39: A2-1 | B39: 출입통제 | C39: 후문·부출입구 | D39: 후문 주간 상주 (07~19시) | E39: 상주(잔여) | F39: 공통 | G39: 720 | H39: 1 | I39: 개소 | J39: 5 | K39: 매주 | L39: 21.7262 | M39: 224.0758 | N39: 2688.91 | O39: 0.1279 | P39: 19745.619 | Q39: 3510793 | R39: 451808 | S39: 171984 | T39: 206735 | U39: 83196 | V39: =SUM(Q39:U39) -> 4424516 | W39: =V39*12 -> 53094192 | X39: 203648.96 | Z39: 1
A40: A2-2 | B40: 출입통제 | C40: 후문·부출입구 | D40: 출퇴근 시간 출입 통제 | E40: 작업 | F40: 공통 | G40: 30 | H40: 1 | I40: 개소 | J40: 10 | K40: 매주 | L40: 43.4524 | M40: 24.9851 | N40: 299.8214 | O40: 0.0143 | P40: 19745.673 | Q40: 391464 | R40: 50378 | S40: 19177 | T40: 23052 | U40: 9277 | V40: =SUM(Q40:U40) -> 493348 | W40: =V40*12 -> 5920176 | X40: 11353.762 | Z40: 1
A41: A2-3 | B41: 출입통제 | C41: 후문·부출입구 | D41: 야간 출입문 시건·개방 | E41: 작업 | F41: 공통 | G41: 10 | H41: 1 | I41: 개소 | J41: 2 | K41: 매일 | L41: 60.8 | M41: 11.6533 | N41: 139.84 | O41: 0.0066 | P41: 19745.595 | Q41: 182583 | R41: 23497 | S41: 8944 | T41: 10751 | U41: 4327 | V41: =SUM(Q41:U41) -> 230102 | W41: =V41*12 -> 2761224 | X41: 3784.5724 | Z41: 1
A42: A3 | B42: 출입통제 | C42: 출입보안시스템 | E42: 3개 업무 | M42: 18.7309 | N42: 224.7702 | O42: 0.0107 | P42: 19745.604 | Q42: 293473 | R42: 37767 | S42: 14376 | T42: 17282 | U42: 6954 | V42: =SUM(Q42:U42) -> 369852 | W42: =V42*12 -> 4438224 | Z42: 0
A43: A3-1 | B43: 출입통제 | C43: 출입보안시스템 | D43: 출입카드 발급·회수·분실 처리 | E43: 작업 | F43: 공통 | G43: 5 | H43: 10 | I43: 건 | J43: 1 | K43: 매주 | L43: 43.4524 | M43: 4.1642 | N43: 49.9702 | O43: 0.0024 | P43: 19745.513 | Q43: 65244 | R43: 8396 | S43: 3196 | T43: 3842 | U43: 1546 | V43: =SUM(Q43:U43) -> 82224 | W43: =V43*12 -> 986688 | X43: 1892.2784 | Z43: 1
A44: A3-2 | B44: 출입통제 | C44: 출입보안시스템 | D44: 출입기록 확인·이상 출입 조치 | E44: 작업 | F44: 공통 | G44: 15 | H44: 1 | I44: 회 | J44: 1 | K44: 매일 | L44: 30.4 | M44: 8.74 | N44: 104.88 | O44: 0.005 | P44: 19745.652 | Q44: 136937 | R44: 17623 | S44: 6708 | T44: 8064 | U44: 3245 | V44: =SUM(Q44:U44) -> 172577 | W44: =V44*12 -> 2070924 | X44: 5676.875 | Z44: 1
A45: A3-3 | B45: 출입통제 | C45: 출입보안시스템 | D45: 스피드게이트·출입통제기 작동 확인 | E45: 작업 | F45: 공통 | G45: 5 | H45: 2 | I45: 대 | J45: 1 | K45: 매일 | L45: 60.8 | M45: 5.8267 | N45: 69.92 | O45: 0.0033 | P45: 19745.595 | Q45: 91292 | R45: 11748 | S45: 4472 | T45: 5376 | U45: 2163 | V45: =SUM(Q45:U45) -> 115051 | W45: =V45*12 -> 1380612 | X45: 1892.2862 | Z45: 1
A46: B | B46: 순찰 | E46: 7개 업무 | M46: 417.956 | N46: 5015.472 | O46: 0.2385 | P46: 19745.612 | Q46: 6548483 | R46: 842734 | S46: 320791 | T46: 385610 | U46: 155179 | V46: =SUM(Q46:U46) -> 8252797 | W46: =V46*12 -> 99033564 | Z46: 0
A47: B1 | B47: 순찰 | C47: 정기순찰 | E47: 4개 업무 | M47: 318.136 | N47: 3817.632 | O47: 0.1815 | P47: 19745.615 | Q47: 4984516 | R47: 641465 | S47: 244177 | T47: 293515 | U47: 118118 | V47: =SUM(Q47:U47) -> 6281791 | W47: =V47*12 -> 75381492 | Z47: 0
A48: B1-1 | B48: 순찰 | C48: 정기순찰 | D48: 외곽 울타리·담장 순찰 | E48: 작업 | F48: 공통 | G48: 30 | H48: 2 | I48: 구역 | J48: 4 | K48: 매일 | L48: 243.2 | M48: 139.84 | N48: 1678.08 | O48: 0.0798 | P48: 19745.616 | Q48: 2190996 | R48: 281962 | S48: 107331 | T48: 129018 | U48: 51920 | V48: =SUM(Q48:U48) -> 2761227 | W48: =V48*12 -> 33134724 | X48: 11353.729 | Z48: 1
A49: B1-2 | B49: 순찰 | C49: 정기순찰 | D49: 건물 내부 층별 순찰 | E49: 작업 | F49: 공통 | G49: 5 | H49: 18 | I49: 층 | J49: 2 | K49: 매일 | L49: 1094.4 | M49: 104.88 | N49: 1258.56 | O49: 0.0598 | P49: 19745.614 | Q49: 1643247 | R49: 211472 | S49: 80498 | T49: 96763 | U49: 38940 | V49: =SUM(Q49:U49) -> 2070920 | W49: =V49*12 -> 24851040 | X49: 1892.288 | Z49: 1
A50: B1-3 | B50: 순찰 | C50: 정기순찰 | D50: 주차장 순찰 | E50: 작업 | F50: 공통 | G50: 8 | H50: 3 | I50: 구역 | J50: 3 | K50: 매일 | L50: 273.6 | M50: 41.952 | N50: 503.424 | O50: 0.0239 | P50: 19745.614 | Q50: 657299 | R50: 84589 | S50: 32199 | T50: 38705 | U50: 15576 | V50: =SUM(Q50:U50) -> 828368 | W50: =V50*12 -> 9940416 | X50: 3027.6608 | Z50: 1
A51: B1-4 | B51: 순찰 | C51: 정기순찰 | D51: 야간 문단속·소등·전열기구 확인 | E51: 작업 | F51: 공통 | G51: 3 | H51: 18 | I51: 층 | J51: 1 | K51: 매일 | L51: 547.2 | M51: 31.464 | N51: 377.568 | O51: 0.018 | P51: 19745.614 | Q51: 492974 | R51: 63442 | S51: 24149 | T51: 29029 | U51: 11682 | V51: =SUM(Q51:U51) -> 621276 | W51: =V51*12 -> 7455312 | X51: 1135.3728 | Z51: 1
A52: B2 | B52: 순찰 | C52: 특별순찰 | E52: 3개 업무 | M52: 99.82 | N52: 1197.84 | O52: 0.057 | P52: 19745.602 | Q52: 1563967 | R52: 201269 | S52: 76614 | T52: 92095 | U52: 37061 | V52: =SUM(Q52:U52) -> 1971006 | W52: =V52*12 -> 23652072 | Z52: 0
A53: B2-1 | B53: 순찰 | C53: 특별순찰 | D53: 취약지역·사각지대 집중 순찰 | E53: 작업 | F53: 공통 | G53: 20 | H53: 3 | I53: 개소 | J53: 2 | K53: 매일 | L53: 182.4 | M53: 69.92 | N53: 839.04 | O53: 0.0399 | P53: 19745.609 | Q53: 1095498 | R53: 140981 | S53: 53665 | T53: 64509 | U53: 25960 | V53: =SUM(Q53:U53) -> 1380613 | W53: =V53*12 -> 16567356 | X53: 7569.1502 | Z53: 1
A54: B2-2 | B54: 순찰 | C54: 특별순찰 | D54: 휴일·공휴일 전수 점검 | E54: 작업 | F54: 공통 | G54: 30 | H54: 6 | I54: 동 | J54: 8 | K54: 매월 | L54: 48 | M54: 27.6 | N54: 331.2 | O54: 0.0157 | P54: 19745.58 | Q54: 432433 | R54: 55650 | S54: 21184 | T54: 25464 | U54: 10247 | V54: =SUM(Q54:U54) -> 544978 | W54: =V54*12 -> 6539736 | X54: 11353.708 | Z54: 1
A55: B2-3 | B55: 순찰 | C55: 특별순찰 | D55: 기상특보(태풍·폭우·폭설) 비상 순찰 | E55: 작업 | F55: 공통 | G55: 60 | H55: 6 | I55: 동 | J55: 4 | K55: 매년 | L55: 2 | M55: 2.3 | N55: 27.6 | O55: 0.0013 | P55: 19745.652 | Q55: 36036 | R55: 4638 | S55: 1765 | T55: 2122 | U55: 854 | V55: =SUM(Q55:U55) -> 45415 | W55: =V55*12 -> 544980 | X55: 22707.5 | Z55: 1
A56: C | B56: 상황대처 | E56: 23개 업무 | M56: 52.3378 | N56: 628.0533 | O56: 0.0299 | P56: 19745.603 | Q56: 820021 | R56: 105528 | S56: 40169 | T56: 48290 | U56: 19433 | V56: =SUM(Q56:U56) -> 1033441 | W56: =V56*12 -> 12401292 | Z56: 0
A57: C1 | B57: 상황대처 | C57: 화재·소방 | E57: 4개 업무 | M57: 2.7153 | N57: 32.5833 | O57: 0.0015 | P57: 19746.046 | Q57: 42543 | R57: 5475 | S57: 2085 | T57: 2505 | U57: 1008 | V57: =SUM(Q57:U57) -> 53616 | W57: =V57*12 -> 643392 | Z57: 0
A58: C1-1 | B58: 상황대처 | C58: 화재·소방 | D58: 화재경보 발생 시 현장 출동·확인 | E58: 작업 | F58: 공통 | G58: 15 | H58: 1 | I58: 건 | J58: 6 | K58: 매월 | L58: 6 | M58: 1.725 | N58: 20.7 | O58: 0.001 | P58: 19745.507 | Q58: 27027 | R58: 3478 | S58: 1324 | T58: 1592 | U58: 640 | V58: =SUM(Q58:U58) -> 34061 | W58: =V58*12 -> 408732 | X58: 5676.8333 | Z58: 1
A59: C1-2 | B59: 상황대처 | C59: 화재·소방 | D59: 비화재보 복구·수신기 리셋 | E59: 작업 | F59: 공통 | G59: 10 | H59: 1 | I59: 건 | J59: 4 | K59: 매월 | L59: 4 | M59: 0.7667 | N59: 9.2 | O59: 0.0004 | P59: 19746.522 | Q59: 12012 | R59: 1546 | S59: 589 | T59: 707 | U59: 285 | V59: =SUM(Q59:U59) -> 15139 | W59: =V59*12 -> 181668 | X59: 3784.75 | Z59: 1
A60: C1-3 | B60: 상황대처 | C60: 화재·소방 | D60: 초기 소화·피난 유도 | E60: 작업 | F60: 공통 | G60: 60 | H60: 1 | I60: 건 | J60: 1 | K60: 매년 | L60: 0.0833 | M60: 0.0958 | N60: 1.15 | O60: 0.0001 | P60: 19753.043 | Q60: 1502 | R60: 193 | S60: 74 | T60: 88 | U60: 36 | V60: =SUM(Q60:U60) -> 1893 | W60: =V60*12 -> 22716 | X60: 22716 | Z60: 1
A61: C1-4 | B61: 상황대처 | C61: 화재·소방 | D61: 소방서 신고·소방차 진입 안내 | E61: 작업 | F61: 공통 | G61: 20 | H61: 1 | I61: 건 | J61: 1 | K61: 분기 | L61: 0.3333 | M61: 0.1278 | N61: 1.5333 | O61: 0.0001 | P61: 19745.217 | Q61: 2002 | R61: 258 | S61: 98 | T61: 118 | U61: 47 | V61: =SUM(Q61:U61) -> 2523 | W61: =V61*12 -> 30276 | X61: 7569 | Z61: 1
A62: C2 | B62: 상황대처 | C62: 응급·안전사고 | E62: 5개 업무 | M62: 2.3 | N62: 27.6 | O62: 0.0013 | P62: 19746.087 | Q62: 36036 | R62: 4637 | S62: 1764 | T62: 2124 | U62: 855 | V62: =SUM(Q62:U62) -> 45416 | W62: =V62*12 -> 544992 | Z62: 0
A63: C2-1 | B63: 상황대처 | C63: 응급·안전사고 | D63: 응급환자 응급조치·119 신고·인계 | E63: 작업 | F63: 공통 | G63: 30 | H63: 1 | I63: 건 | J63: 1 | K63: 매월 | L63: 1 | M63: 0.575 | N63: 6.9 | O63: 0.0003 | P63: 19746.087 | Q63: 9009 | R63: 1159 | S63: 441 | T63: 531 | U63: 214 | V63: =SUM(Q63:U63) -> 11354 | W63: =V63*12 -> 136248 | X63: 11354 | Z63: 1
A64: C2-2 | B64: 상황대처 | C64: 응급·안전사고 | D64: AED·구급함 점검 | E64: 작업 | F64: 공통 | G64: 5 | H64: 6 | I64: 개소 | J64: 1 | K64: 매월 | L64: 6 | M64: 0.575 | N64: 6.9 | O64: 0.0003 | P64: 19746.087 | Q64: 9009 | R64: 1159 | S64: 441 | T64: 531 | U64: 214 | V64: =SUM(Q64:U64) -> 11354 | W64: =V64*12 -> 136248 | X64: 1892.3333 | Z64: 1
A65: C2-3 | B65: 상황대처 | C65: 응급·안전사고 | D65: 산업재해 발생 시 현장 통제·보고 | E65: 작업 | F65: 공통 | G65: 60 | H65: 1 | I65: 건 | J65: 2 | K65: 매년 | L65: 0.1667 | M65: 0.1917 | N65: 2.3 | O65: 0.0001 | P65: 19747.826 | Q65: 3003 | R65: 387 | S65: 147 | T65: 177 | U65: 71 | V65: =SUM(Q65:U65) -> 3785 | W65: =V65*12 -> 45420 | X65: 22710 | Z65: 1
A66: C2-4 | B66: 상황대처 | C66: 응급·안전사고 | D66: 승강기 갇힘 사고 대응·구조 연계 | E66: 작업 | F66: 공통 | G66: 30 | H66: 1 | I66: 건 | J66: 1 | K66: 매월 | L66: 1 | M66: 0.575 | N66: 6.9 | O66: 0.0003 | P66: 19746.087 | Q66: 9009 | R66: 1159 | S66: 441 | T66: 531 | U66: 214 | V66: =SUM(Q66:U66) -> 11354 | W66: =V66*12 -> 136248 | X66: 11354 | Z66: 1
A67: C2-5 | B67: 상황대처 | C67: 응급·안전사고 | D67: 넘어짐·추락 사고 현장 조치 | E67: 작업 | F67: 공통 | G67: 20 | H67: 1 | I67: 건 | J67: 1 | K67: 매월 | L67: 1 | M67: 0.3833 | N67: 4.6 | O67: 0.0002 | P67: 19745.217 | Q67: 6006 | R67: 773 | S67: 294 | T67: 354 | U67: 142 | V67: =SUM(Q67:U67) -> 7569 | W67: =V67*12 -> 90828 | X67: 7569 | Z67: 1
A68: C3 | B68: 상황대처 | C68: 침입·도난·범죄 | E68: 4개 업무 | M68: 6.7083 | N68: 80.5 | O68: 0.0038 | P68: 19745.739 | Q68: 105105 | R68: 13527 | S68: 5148 | T68: 6190 | U68: 2491 | V68: =SUM(Q68:U68) -> 132461 | W68: =V68*12 -> 1589532 | Z68: 0
A69: C3-1 | B69: 상황대처 | C69: 침입·도난·범죄 | D69: 무단침입 발생 시 대응·경찰 신고 | E69: 작업 | F69: 공통 | G69: 40 | H69: 1 | I69: 건 | J69: 2 | K69: 매월 | L69: 2 | M69: 1.5333 | N69: 18.4 | O69: 0.0009 | P69: 19745.87 | Q69: 24024 | R69: 3092 | S69: 1177 | T69: 1415 | U69: 569 | V69: =SUM(Q69:U69) -> 30277 | W69: =V69*12 -> 363324 | X69: 15138.5 | Z69: 1
A70: C3-2 | B70: 상황대처 | C70: 침입·도난·범죄 | D70: 도난·분실 신고 접수·조사 협조 | E70: 작업 | F70: 공통 | G70: 30 | H70: 1 | I70: 건 | J70: 1 | K70: 매월 | L70: 1 | M70: 0.575 | N70: 6.9 | O70: 0.0003 | P70: 19746.087 | Q70: 9009 | R70: 1159 | S70: 441 | T70: 531 | U70: 214 | V70: =SUM(Q70:U70) -> 11354 | W70: =V70*12 -> 136248 | X70: 11354 | Z70: 1
A71: C3-3 | B71: 상황대처 | C71: 침입·도난·범죄 | D71: CCTV 영상 확인·증거 보존 지원 | E71: 작업 | F71: 공통 | G71: 30 | H71: 1 | I71: 건 | J71: 4 | K71: 매월 | L71: 4 | M71: 2.3 | N71: 27.6 | O71: 0.0013 | P71: 19745.652 | Q71: 36036 | R71: 4638 | S71: 1765 | T71: 2122 | U71: 854 | V71: =SUM(Q71:U71) -> 45415 | W71: =V71*12 -> 544980 | X71: 11353.75 | Z71: 1
A72: C3-4 | B72: 상황대처 | C72: 침입·도난·범죄 | D72: 수상한 물건·거동 수상자 확인 | E72: 작업 | F72: 공통 | G72: 15 | H72: 1 | I72: 건 | J72: 8 | K72: 매월 | L72: 8 | M72: 2.3 | N72: 27.6 | O72: 0.0013 | P72: 19745.652 | Q72: 36036 | R72: 4638 | S72: 1765 | T72: 2122 | U72: 854 | V72: =SUM(Q72:U72) -> 45415 | W72: =V72*12 -> 544980 | X72: 5676.875 | Z72: 1
A73: C4 | B73: 상황대처 | C73: 소란·민원·폭력 | E73: 4개 업무 | M73: 18.63 | N73: 223.56 | O73: 0.0106 | P73: 19745.464 | Q73: 291892 | R73: 37563 | S73: 14298 | T73: 17188 | U73: 6917 | V73: =SUM(Q73:U73) -> 367858 | W73: =V73*12 -> 4414296 | Z73: 0
A74: C4-1 | B74: 상황대처 | C74: 소란·민원·폭력 | D74: 소란·난동 발생 시 제지·분리 | E74: 작업 | F74: 공통 | G74: 30 | H74: 1 | I74: 건 | J74: 1 | K74: 매월 | L74: 1 | M74: 0.575 | N74: 6.9 | O74: 0.0003 | P74: 19744.348 | Q74: 9009 | R74: 1159 | S74: 441 | T74: 530 | U74: 214 | V74: =SUM(Q74:U74) -> 11353 | W74: =V74*12 -> 136236 | X74: 11353 | Z74: 1
A75: C4-2 | B75: 상황대처 | C75: 소란·민원·폭력 | D75: 주취자·노숙인 대응 | E75: 작업 | F75: 공통 | G75: 20 | H75: 1 | I75: 건 | J75: 1 | K75: 매월 | L75: 1 | M75: 0.3833 | N75: 4.6 | O75: 0.0002 | P75: 19745.217 | Q75: 6006 | R75: 773 | S75: 294 | T75: 354 | U75: 142 | V75: =SUM(Q75:U75) -> 7569 | W75: =V75*12 -> 90828 | X75: 7569 | Z75: 1
A76: C4-3 | B76: 상황대처 | C76: 소란·민원·폭력 | D76: 현장 민원 접수·응대 | E76: 작업 | F76: 공통 | G76: 10 | H76: 3 | I76: 건 | J76: 1 | K76: 매일 | L76: 91.2 | M76: 17.48 | N76: 209.76 | O76: 0.01 | P76: 19745.538 | Q76: 273874 | R76: 35245 | S76: 13416 | T76: 16127 | U76: 6490 | V76: =SUM(Q76:U76) -> 345152 | W76: =V76*12 -> 4141824 | X76: 3784.5614 | Z76: 1
A77: C4-4 | B77: 상황대처 | C77: 소란·민원·폭력 | D77: 집회·시위 발생 시 출입 통제 | E77: 작업 | F77: 공통 | G77: 120 | H77: 1 | I77: 건 | J77: 1 | K77: 매년 | L77: 0.0833 | M77: 0.1917 | N77: 2.3 | O77: 0.0001 | P77: 19742.609 | Q77: 3003 | R77: 386 | S77: 147 | T77: 177 | U77: 71 | V77: =SUM(Q77:U77) -> 3784 | W77: =V77*12 -> 45408 | X77: 45408 | Z77: 1
A78: C5 | B78: 상황대처 | C78: 설비 이상·재난 | E78: 4개 업무 | M78: 3.7375 | N78: 44.85 | O78: 0.0021 | P78: 19745.552 | Q78: 58559 | R78: 7535 | S78: 2869 | T78: 3449 | U78: 1387 | V78: =SUM(Q78:U78) -> 73799 | W78: =V78*12 -> 885588 | Z78: 0
A79: C5-1 | B79: 상황대처 | C79: 설비 이상·재난 | D79: 정전 시 비상조명 확인·설비팀 연락 | E79: 작업 | F79: 공통 | G79: 30 | H79: 1 | I79: 건 | J79: 2 | K79: 매년 | L79: 0.1667 | M79: 0.0958 | N79: 1.15 | O79: 0.0001 | P79: 19753.043 | Q79: 1502 | R79: 193 | S79: 74 | T79: 88 | U79: 36 | V79: =SUM(Q79:U79) -> 1893 | W79: =V79*12 -> 22716 | X79: 11358 | Z79: 1
A80: C5-2 | B80: 상황대처 | C80: 설비 이상·재난 | D80: 누수·배관 파열 초동 조치 | E80: 작업 | F80: 공통 | G80: 30 | H80: 1 | I80: 건 | J80: 3 | K80: 매월 | L80: 3 | M80: 1.725 | N80: 20.7 | O80: 0.001 | P80: 19745.507 | Q80: 27027 | R80: 3478 | S80: 1324 | T80: 1592 | U80: 640 | V80: =SUM(Q80:U80) -> 34061 | W80: =V80*12 -> 408732 | X80: 11353.667 | Z80: 1
A81: C5-3 | B81: 상황대처 | C81: 설비 이상·재난 | D81: 가스·화학물질 누출 초동 조치 | E81: 작업 | F81: 공통 | G81: 60 | H81: 1 | I81: 건 | J81: 2 | K81: 매년 | L81: 0.1667 | M81: 0.1917 | N81: 2.3 | O81: 0.0001 | P81: 19742.609 | Q81: 3003 | R81: 386 | S81: 147 | T81: 177 | U81: 71 | V81: =SUM(Q81:U81) -> 3784 | W81: =V81*12 -> 45408 | X81: 22704 | Z81: 1
A82: C5-4 | B82: 상황대처 | C82: 설비 이상·재난 | D82: 태풍·폭우 대비 시설물 결박·배수구 점검 | E82: 작업 | F82: 공통 | G82: 60 | H82: 6 | I82: 동 | J82: 3 | K82: 매년 | L82: 1.5 | M82: 1.725 | N82: 20.7 | O82: 0.001 | P82: 19745.507 | Q82: 27027 | R82: 3478 | S82: 1324 | T82: 1592 | U82: 640 | V82: =SUM(Q82:U82) -> 34061 | W82: =V82*12 -> 408732 | X82: 22707.333 | Z82: 1
A83: C6 | B83: 상황대처 | C83: 교통·주차 사고 | E83: 2개 업무 | M83: 18.2467 | N83: 218.96 | O83: 0.0104 | P83: 19745.579 | Q83: 285886 | R83: 36791 | S83: 14005 | T83: 16834 | U83: 6775 | V83: =SUM(Q83:U83) -> 360291 | W83: =V83*12 -> 4323492 | Z83: 0
A84: C6-1 | B84: 상황대처 | C84: 교통·주차 사고 | D84: 구내 교통사고 현장 통제·보고 | E84: 작업 | F84: 공통 | G84: 40 | H84: 1 | I84: 건 | J84: 1 | K84: 매월 | L84: 1 | M84: 0.7667 | N84: 9.2 | O84: 0.0004 | P84: 19746.522 | Q84: 12012 | R84: 1546 | S84: 589 | T84: 707 | U84: 285 | V84: =SUM(Q84:U84) -> 15139 | W84: =V84*12 -> 181668 | X84: 15139 | Z84: 1
A85: C6-2 | B85: 상황대처 | C85: 교통·주차 사고 | D85: 통행 방해·불법주차 차량 조치 | E85: 작업 | F85: 공통 | G85: 5 | H85: 6 | I85: 건 | J85: 1 | K85: 매일 | L85: 182.4 | M85: 17.48 | N85: 209.76 | O85: 0.01 | P85: 19745.538 | Q85: 273874 | R85: 35245 | S85: 13416 | T85: 16127 | U85: 6490 | V85: =SUM(Q85:U85) -> 345152 | W85: =V85*12 -> 4141824 | X85: 1892.2807 | Z85: 1
A86: D | B86: 관제·방재 | E86: 9개 업무 | M86: 85.3848 | N86: 1024.6171 | O86: 0.0487 | P86: 19745.631 | Q86: 1337799 | R86: 172163 | S86: 65535 | T86: 78776 | U86: 31703 | V86: =SUM(Q86:U86) -> 1685976 | W86: =V86*12 -> 20231712 | Z86: 0
A87: D1 | B87: 관제·방재 | C87: CCTV 관제 | E87: 3개 업무 | M87: 47.254 | N87: 567.0486 | O87: 0.027 | P87: 19745.652 | Q87: 740371 | R87: 95280 | S87: 36269 | T87: 43597 | U87: 17545 | V87: =SUM(Q87:U87) -> 933062 | W87: =V87*12 -> 11196744 | Z87: 0
A88: D1-1 | B88: 관제·방재 | C88: CCTV 관제 | D88: CCTV 모니터링 (정문 초소 겸무) | E88: 작업 | F88: 공통 | G88: 10 | H88: 1 | I88: 회 | J88: 6 | K88: 매일 | L88: 182.4 | M88: 34.96 | N88: 419.52 | O88: 0.0199 | P88: 19745.624 | Q88: 547749 | R88: 70491 | S88: 26833 | T88: 32254 | U88: 12980 | V88: =SUM(Q88:U88) -> 690307 | W88: =V88*12 -> 8283684 | X88: 3784.5779 | Z88: 1
A89: D1-2 | B89: 관제·방재 | C89: CCTV 관제 | D89: CCTV 녹화 상태·카메라 점검 | E89: 작업 | F89: 공통 | G89: 1 | H89: 120 | I89: 대 | J89: 1 | K89: 매주 | L89: 521.4286 | M89: 9.994 | N89: 119.9286 | O89: 0.0057 | P89: 19745.753 | Q89: 156586 | R89: 20151 | S89: 7671 | T89: 9221 | U89: 3711 | V89: =SUM(Q89:U89) -> 197340 | W89: =V89*12 -> 2368080 | X89: 378.4603 | Z89: 1
A90: D1-3 | B90: 관제·방재 | C90: CCTV 관제 | D90: 영상 열람·반출 요청 처리 | E90: 작업 | F90: 공통 | G90: 30 | H90: 1 | I90: 건 | J90: 4 | K90: 매월 | L90: 4 | M90: 2.3 | N90: 27.6 | O90: 0.0013 | P90: 19745.652 | Q90: 36036 | R90: 4638 | S90: 1765 | T90: 2122 | U90: 854 | V90: =SUM(Q90:U90) -> 45415 | W90: =V90*12 -> 544980 | X90: 11353.75 | Z90: 1
A91: D2 | B91: 관제·방재 | C91: 방재·설비 감시 | E91: 3개 업무 | M91: 32.0467 | N91: 384.56 | O91: 0.0183 | P91: 19745.579 | Q91: 502103 | R91: 64616 | S91: 24596 | T91: 29566 | U91: 11899 | V91: =SUM(Q91:U91) -> 632780 | W91: =V91*12 -> 7593360 | Z91: 0
A92: D2-1 | B92: 관제·방재 | C92: 방재·설비 감시 | D92: 화재수신기·방재반 감시 기록 | E92: 작업 | F92: 공통 | G92: 10 | H92: 1 | I92: 회 | J92: 3 | K92: 매일 | L92: 91.2 | M92: 17.48 | N92: 209.76 | O92: 0.01 | P92: 19745.538 | Q92: 273874 | R92: 35245 | S92: 13416 | T92: 16127 | U92: 6490 | V92: =SUM(Q92:U92) -> 345152 | W92: =V92*12 -> 4141824 | X92: 3784.5614 | Z92: 1
A93: D2-2 | B93: 관제·방재 | C93: 방재·설비 감시 | D93: 무인경비·침입감지 알람 확인 | E93: 작업 | F93: 공통 | G93: 10 | H93: 1 | I93: 건 | J93: 2 | K93: 매일 | L93: 60.8 | M93: 11.6533 | N93: 139.84 | O93: 0.0066 | P93: 19745.595 | Q93: 182583 | R93: 23497 | S93: 8944 | T93: 10751 | U93: 4327 | V93: =SUM(Q93:U93) -> 230102 | W93: =V93*12 -> 2761224 | X93: 3784.5724 | Z93: 1
A94: D2-3 | B94: 관제·방재 | C94: 방재·설비 감시 | D94: 비상방송·안내방송 송출 | E94: 작업 | F94: 공통 | G94: 5 | H94: 1 | I94: 회 | J94: 1 | K94: 매일 | L94: 30.4 | M94: 2.9133 | N94: 34.96 | O94: 0.0017 | P94: 19745.767 | Q94: 45646 | R94: 5874 | S94: 2236 | T94: 2688 | U94: 1082 | V94: =SUM(Q94:U94) -> 57526 | W94: =V94*12 -> 690312 | X94: 1892.3026 | Z94: 1
A95: D3 | B95: 관제·방재 | C95: 소방시설 일상점검 | E95: 3개 업무 | M95: 6.084 | N95: 73.0086 | O95: 0.0035 | P95: 19745.736 | Q95: 95325 | R95: 12267 | S95: 4670 | T95: 5613 | U95: 2259 | V95: =SUM(Q95:U95) -> 120134 | W95: =V95*12 -> 1441608 | Z95: 0
A96: D3-1 | B96: 관제·방재 | C96: 소방시설 일상점검 | D96: 소화기·옥내소화전 외관 점검 | E96: 작업 | F96: 공통 | G96: 1 | H96: 125 | I96: 개 | J96: 1 | K96: 매월 | L96: 125 | M96: 2.3958 | N96: 28.75 | O96: 0.0014 | P96: 19745.948 | Q96: 37538 | R96: 4831 | S96: 1839 | T96: 2210 | U96: 890 | V96: =SUM(Q96:U96) -> 47308 | W96: =V96*12 -> 567696 | X96: 378.464 | Z96: 1
A97: D3-2 | B97: 관제·방재 | C97: 소방시설 일상점검 | D97: 방화문·피난통로 적치물 확인 | E97: 작업 | F97: 공통 | G97: 2 | H97: 18 | I97: 층 | J97: 1 | K97: 매주 | L97: 78.2143 | M97: 2.9982 | N97: 35.9786 | O97: 0.0017 | P97: 19745.42 | Q97: 46976 | R97: 6045 | S97: 2301 | T97: 2766 | U97: 1113 | V97: =SUM(Q97:U97) -> 59201 | W97: =V97*12 -> 710412 | X97: 756.9078 | Z97: 1
A98: D3-3 | B98: 관제·방재 | C98: 소방시설 일상점검 | D98: 유도등·비상조명 점등 확인 | E98: 작업 | F98: 공통 | G98: 0.5 | H98: 72 | I98: 개 | J98: 1 | K98: 매월 | L98: 72 | M98: 0.69 | N98: 8.28 | O98: 0.0004 | P98: 19746.377 | Q98: 10811 | R98: 1391 | S98: 530 | T98: 637 | U98: 256 | V98: =SUM(Q98:U98) -> 13625 | W98: =V98*12 -> 163500 | X98: 189.2361 | Z98: 1
A99: E | B99: 고객사 업무 지원 | E99: 11개 업무 | M99: 118.6394 | N99: 1423.6726 | O99: 0.0677 | P99: 19745.618 | Q99: 1858827 | R99: 239214 | S99: 91060 | T99: 109458 | U99: 44049 | V99: =SUM(Q99:U99) -> 2342608 | W99: =V99*12 -> 28111296 | Z99: 0
A100: E1 | B100: 고객사 업무 지원 | C100: 안내·의전 | E100: 3개 업무 | M100: 9.3917 | N100: 112.7 | O100: 0.0054 | P100: 19745.59 | Q100: 147147 | R100: 18936 | S100: 7209 | T100: 8665 | U100: 3487 | V100: =SUM(Q100:U100) -> 185444 | W100: =V100*12 -> 2225328 | Z100: 0
A101: E1-1 | B101: 고객사 업무 지원 | C101: 안내·의전 | D101: VIP·귀빈 영접 및 차량 안내 | E101: 작업 | F101: 공통 | G101: 20 | H101: 2 | I101: 건 | J101: 4 | K101: 매월 | L101: 8 | M101: 3.0667 | N101: 36.8 | O101: 0.0017 | P101: 19745.543 | Q101: 48048 | R101: 6183 | S101: 2354 | T101: 2829 | U101: 1139 | V101: =SUM(Q101:U101) -> 60553 | W101: =V101*12 -> 726636 | X101: 7569.125 | Z101: 1
A102: E1-2 | B102: 고객사 업무 지원 | C102: 안내·의전 | D102: 회의·행사장 출입 통제 | E102: 작업 | F102: 공통 | G102: 120 | H102: 2 | I102: 회 | J102: 1 | K102: 매월 | L102: 2 | M102: 4.6 | N102: 55.2 | O102: 0.0026 | P102: 19745.652 | Q102: 72072 | R102: 9275 | S102: 3531 | T102: 4244 | U102: 1708 | V102: =SUM(Q102:U102) -> 90830 | W102: =V102*12 -> 1089960 | X102: 45415 | Z102: 1
...

Sheet 4. 업무량 산출내역
B1: 공장 ○○사업장 보안용역 도급업무 업무량 산출내역 (Workload) | R1: No. 261029-0425
B2: Location: 공장 ○○사업장 | R2: 작성일 2026. 10. 29
B3: 2027년 · 평일: 246일 / 주말: 104일 / 공휴일: 15일 · 주간 06~22시 · 야간 22~06시
B5: 도급 업무 (분류별 세부업무) | C5: 시간당 단가 | D5: Work scope (연간 업무시간, h) | K5: Amount (연간 노무비, 원) | R5: 비고
D6: TOTAL | E6: 주중 주간 | F6: 주중 야간 | G6: 주말 주간 | H6: 주말 야간 | I6: 공휴일 주간 | J6: 공휴일 야간 | K6: TOTAL | L6: 주중 주간 | M6: 주중 야간 | N6: 주말 주간 | O6: 주말 야간 | P6: 공휴일 주간 | Q6: 공휴일 야간
B7: A 출입통제 | C7: 17684.198 | D7: =SUM(E7:J7) -> 12108.542 | E7: 7806.2826 | F7: 1247.4927 | G7: 2142.3164 | H7: 527.3953 | I7: 308.9879 | J7: 76.0666 | K7: =SUM(L7:Q7) -> 214129848 | L7: 138047847 | M7: 22060908 | N7: 37885149 | O7: 9326562 | P7: 5464204 | Q7: 1345178 | T7: 0
B8: A1 정문 초소 | C8: 17684.198 | D8: =SUM(E8:J8) -> 8755.2 | E8: 4747.5205 | F8: 1153.2444 | G8: 2007.0818 | H8: 487.5505 | I8: 289.483 | J8: 70.3198 | K8: =SUM(L8:Q8) -> 154828692 | L8: 83956097 | M8: 20394201 | N8: 35493633 | O8: 8621938 | P8: 5119274 | Q8: 1243549 | T8: 0
B9: A1-1 정문 상주 근무 (24시간 경계·대기) | C9: 17684.196 | D9: =SUM(E9:J9) -> 5133.344 | E9: 2306.4888 | F9: 1153.2444 | G9: 975.101 | H9: 487.5505 | I9: 140.6396 | J9: 70.3198 | K9: =SUM(L9:Q9) -> 90779064 | L9: 40788401 | M9: 20394201 | N9: 17243877 | O9: 8621938 | P9: 2487098 | Q9: 1243549 | R9: 상주 시간 중 다른 업무를 뺀 경계·대기 | T9: 1
B10: A1-2-a 입문 차량 확인·출입 기록 | C10: 17684.211 | D10: =SUM(E10:J10) -> 377.568 | E10: 254.4705 | F10: 0 | G10: 107.581 | H10: 0 | I10: 15.5165 | J10: 0 | K10: =SUM(L10:Q10) -> 6676992 | L10: 4500110 | M10: 0 | N10: 1902485 | O10: 0 | P10: 274397 | Q10: 0 | T10: 1
B11: A1-2-b 출문 차량 적재물 확인 | C11: 17684.211 | D11: =SUM(E11:J11) -> 377.568 | E11: 254.4705 | F11: 0 | G11: 107.581 | H11: 0 | I11: 15.5165 | J11: 0 | K11: =SUM(L11:Q11) -> 6676992 | L11: 4500110 | M11: 0 | N11: 1902485 | O11: 0 | P11: 274397 | Q11: 0 | T11: 1
B12: A1-2-c 협력업체·납품차량 출입 통제 | C12: 17684.211 | D12: =SUM(E12:J12) -> 377.568 | E12: 254.4705 | F12: 0 | G12: 107.581 | H12: 0 | I12: 15.5165 | J12: 0 | K12: =SUM(L12:Q12) -> 6676992 | L12: 4500110 | M12: 0 | N12: 1902485 | O12: 0 | P12: 274397 | Q12: 0 | T12: 1
B13: A1-2-d 긴급·관공서 차량 우선 통행 안내 | C13: 17684.211 | D13: =SUM(E13:J13) -> 41.952 | E13: 28.2745 | F13: 0 | G13: 11.9534 | H13: 0 | I13: 1.7241 | J13: 0 | K13: =SUM(L13:Q13) -> 741888 | L13: 500012 | M13: 0 | N13: 211387 | O13: 0 | P13: 30489 | Q13: 0 | T13: 1
B14: A1-3-a 방문객 신원확인·출입증 발급 | C14: 17684.196 | D14: =SUM(E14:J14) -> 839.04 | E14: 565.49 | F14: 0 | G14: 239.0689 | H14: 0 | I14: 34.4811 | J14: 0 | K14: =SUM(L14:Q14) -> 14837748 | L14: 10000236 | M14: 0 | N14: 4227742 | O14: 0 | P14: 609770 | Q14: 0 | T14: 1
B15: A1-3-b 출입증 회수·방문 대장 정리 | C15: 17684.153 | D15: =SUM(E15:J15) -> 209.76 | E15: 141.3725 | F15: 0 | G15: 59.7672 | H15: 0 | I15: 8.6203 | J15: 0 | K15: =SUM(L15:Q15) -> 3709428 | L15: 2500053 | M15: 0 | N15: 1056933 | O15: 0 | P15: 152442 | Q15: 0 | T15: 1
B16: A1-3-c 사전 방문예약 확인·접견자 연락 | C16: 17684.211 | D16: =SUM(E16:J16) -> 167.808 | E16: 113.098 | F16: 0 | G16: 47.8138 | H16: 0 | I16: 6.8962 | J16: 0 | K16: =SUM(L16:Q16) -> 2967552 | L16: 2000049 | M16: 0 | N16: 845549 | O16: 0 | P16: 121954 | Q16: 0 | T16: 1
B17: A1-4-a 반출입증 확인·물품 대조 | C17: 17684.17 | D17: =SUM(E17:J17) -> 293.664 | E17: 197.9215 | F17: 0 | G17: 83.6741 | H17: 0 | I17: 12.0684 | J17: 0 | K17: =SUM(L17:Q17) -> 5193204 | L17: 3500077 | M17: 0 | N17: 1479708 | O17: 0 | P17: 213419 | Q17: 0 | T17: 1
B18: A1-4-b 반입 금지물품(화기·위험물) 검색 | C18: 17684.211 | D18: =SUM(E18:J18) -> 419.52 | E18: 282.745 | F18: 0 | G18: 119.5345 | H18: 0 | I18: 17.2405 | J18: 0 | K18: =SUM(L18:Q18) -> 7418880 | L18: 5000122 | M18: 0 | N18: 2113873 | O18: 0 | P18: 304885 | Q18: 0 | T18: 1
B19: A1-5-a 택배 수령·보관 등록 | C19: 17684.211 | D19: =SUM(E19:J19) -> 279.68 | E19: 188.4967 | F19: 0 | G19: 79.6896 | H19: 0 | I19: 11.4937 | J19: 0 | K19: =SUM(L19:Q19) -> 4945920 | L19: 3333415 | M19: 0 | N19: 1409248 | O19: 0 | P19: 203257 | Q19: 0 | T19: 1
B20: A1-5-b 수령자 연락·인계 확인 | C20: 17684.211 | D20: =SUM(E20:J20) -> 195.776 | E20: 131.9477 | F20: 0 | G20: 55.7828 | H20: 0 | I20: 8.0456 | J20: 0 | K20: =SUM(L20:Q20) -> 3462144 | L20: 2333390 | M20: 0 | N20: 986474 | O20: 0 | P20: 142280 | Q20: 0 | T20: 1
B21: A1-5-c 등기·우편물 분류 | C21: 17684.211 | D21: =SUM(E21:J21) -> 41.952 | E21: 28.2745 | F21: 0 | G21: 11.9534 | H21: 0 | I21: 1.7241 | J21: 0 | K21: =SUM(L21:Q21) -> 741888 | L21: 500012 | M21: 0 | N21: 211387 | O21: 0 | P21: 30489 | Q21: 0 | T21: 1
B22: A2 후문·부출입구 | C22: 17684.198 | D22: =SUM(E22:J22) -> 3128.5714 | E22: 2890.9814 | F22: 94.2483 | G22: 85.4286 | H22: 39.8448 | I22: 12.3214 | J22: 5.7468 | K22: =SUM(L22:Q22) -> 55326276 | L22: 51124685 | M22: 1666707 | N22: 1510736 | O22: 704624 | P22: 217895 | Q22: 101629 | T22: 0
B23: A2-1 후문 주간 상주 (07~19시) | C23: 17684.196 | D23: =SUM(E23:J23) -> 2688.91 | E23: 2688.91 | F23: 0 | G23: 0 | H23: 0 | I23: 0 | J23: 0 | K23: =SUM(L23:Q23) -> 47551212 | L23: 47551212 | M23: 0 | N23: 0 | O23: 0 | P23: 0 | Q23: 0 | R23: 상주 시간 중 다른 업무를 뺀 경계·대기 | T23: 1
B24: A2-2 출퇴근 시간 출입 통제 | C24: 17684.206 | D24: =SUM(E24:J24) -> 299.8214 | E24: 202.0714 | F24: 0 | G24: 85.4286 | H24: 0 | I24: 12.3214 | J24: 0 | K24: =SUM(L24:Q24) -> 5302104 | L24: 3573473 | M24: 0 | N24: 1510736 | O24: 0 | P24: 217895 | Q24: 0 | T24: 1
B25: A2-3 야간 출입문 시건·개방 | C25: 17684.211 | D25: =SUM(E25:J25) -> 139.84 | E25: 0 | F25: 94.2483 | G25: 0 | H25: 39.8448 | I25: 0 | J25: 5.7468 | K25: =SUM(L25:Q25) -> 2472960 | L25: 0 | M25: 1666707 | N25: 0 | O25: 704624 | P25: 0 | Q25: 101629 | T25: 1
B26: A3 출입보안시스템 | C26: 17684.192 | D26: =SUM(E26:J26) -> 224.7702 | E26: 167.7806 | F26: 0 | G26: 49.806 | H26: 0 | I26: 7.1836 | J26: 0 | K26: =SUM(L26:Q26) -> 3974880 | L26: 2967065 | M26: 0 | N26: 880780 | O26: 0 | P26: 127035 | Q26: 0 | T26: 0
B27: A3-1 출입카드 발급·회수·분실 처리 | C27: 17684.126 | D27: =SUM(E27:J27) -> 49.9702 | E27: 49.9702 | F27: 0 | G27: 0 | H27: 0 | I27: 0 | J27: 0 | K27: =SUM(L27:Q27) -> 883680 | L27: 883680 | M27: 0 | N27: 0 | O27: 0 | P27: 0 | Q27: 0 | T27: 1
B28: A3-2 출입기록 확인·이상 출입 조치 | C28: 17684.211 | D28: =SUM(E28:J28) -> 104.88 | E28: 70.6862 | F28: 0 | G28: 29.8836 | H28: 0 | I28: 4.3101 | J28: 0 | K28: =SUM(L28:Q28) -> 1854720 | L28: 1250031 | M28: 0 | N28: 528468 | O28: 0 | P28: 76221 | Q28: 0 | T28: 1
B29: A3-3 스피드게이트·출입통제기 작동 확인 | C29: 17684.211 | D29: =SUM(E29:J29) -> 69.92 | E29: 47.1242 | F29: 0 | G29: 19.9224 | H29: 0 | I29: 2.8734 | J29: 0 | K29: =SUM(L29:Q29) -> 1236480 | L29: 833354 | M29: 0 | N29: 352312 | O29: 0 | P29: 50814 | Q29: 0 | T29: 1
B30: B 순찰 | C30: 17684.199 | D30: =SUM(E30:J30) -> 5015.472 | E30: 3242.7989 | F30: 254.4705 | G30: 1219.2516 | H30: 107.581 | I30: 175.8536 | J30: 15.5165 | K30: =SUM(L30:Q30) -> 88694604 | L30: 57346294 | M30: 4500110 | N30: 21561488 | O30: 1902485 | P30: 3109830 | Q30: 274397 | T30: 0
B31: B1 정기순찰 | C31: 17684.201 | D31: =SUM(E31:J31) -> 3817.632 | E31: 2318.5089 | F31: 254.4705 | G31: 980.1826 | H31: 107.581 | I31: 141.3725 | J31: 15.5165 | K31: =SUM(L31:Q31) -> 67511772 | L31: 41000974 | M31: 4500110 | N31: 17333746 | O31: 1902485 | P31: 2500060 | Q31: 274397 | T31: 0
B32: B1-1 외곽 울타리·담장 순찰 | C32: 17684.196 | D32: =SUM(E32:J32) -> 1678.08 | E32: 1130.9799 | F32: 0 | G32: 478.1379 | H32: 0 | I32: 68.9622 | J32: 0 | K32: =SUM(L32:Q32) -> 29675496 | L32: 20000471 | M32: 0 | N32: 8455484 | O32: 0 | P32: 1219541 | Q32: 0 | T32: 1
B33: B1-2 건물 내부 층별 순찰 | C33: 17684.201 | D33: =SUM(E33:J33) -> 1258.56 | E33: 848.235 | F33: 0 | G33: 358.6034 | H33: 0 | I33: 51.7216 | J33: 0 | K33: =SUM(L33:Q33) -> 22256628 | L33: 15000357 | M33: 0 | N33: 6341615 | O33: 0 | P33: 914656 | Q33: 0 | T33: 1
B34: B1-3 주차장 순찰 | C34: 17684.211 | D34: =SUM(E34:J34) -> 503.424 | E34: 339.294 | F34: 0 | G34: 143.4414 | H34: 0 | I34: 20.6887 | J34: 0 | K34: =SUM(L34:Q34) -> 8902656 | L34: 6000146 | M34: 0 | N34: 2536647 | O34: 0 | P34: 365863 | Q34: 0 | T34: 1
B35: B1-4 야간 문단속·소등·전열기구 확인 | C35: 17684.211 | D35: =SUM(E35:J35) -> 377.568 | E35: 0 | F35: 254.4705 | G35: 0 | H35: 107.581 | I35: 0 | J35: 15.5165 | K35: =SUM(L35:Q35) -> 6676992 | L35: 0 | M35: 4500110 | N35: 0 | O35: 1902485 | P35: 0 | Q35: 274397 | T35: 1
... B103: F4 경비원 직무교육·소방훈련 참여 | C103: 17684.348 | D103: =SUM(E103:J103) -> 18.4 | E103: 18.4 | F103: 0 | G103: 0 | H103: 0 | I103: 0 | J103: 0 | K103: =SUM(L103:Q103) -> 325392 | L103: 325392 | M103: 0 | N103: 0 | O103: 0 | P103: 0 | Q103: 0 | T103: 1
B104: ① 노무비 소계 (연간 · 직접+간접) | C104: 17684.196 | D104: =SUMIF($T$7:$T$103,1,D7:D103) -> 21029.277 | E104: =SUMIF($T$7:$T$103,1,E7:E103) -> 14076.705 | F104: =SUMIF($T$7:$T$103,1,F7:F103) -> 1501.9632 | G104: =SUMIF($T$7:$T$103,1,G7:G103) -> 4128.5808 | H104: =SUMIF($T$7:$T$103,1,H7:H103) -> 634.9763 | I104: =SUMIF($T$7:$T$103,1,I7:I103) -> 595.4684 | J104: =SUMIF($T$7:$T$103,1,J7:J103) -> 91.5831 | K104: =SUMIF($T$7:$T$103,1,K7:K103) -> 371885856 | ... Q104: =SUMIF($T$7:$T$103,1,Q7:Q103) -> 1619575 | R104: 월 30,990,488원 · 합계의 89.6%
B105: ② 경비 (연간 · 피복·복리후생·교육 등) | K105: 16140480 | R105: 월 1,345,040원 · 합계의 3.9%
B106: ③ 일반관리비 (연간) | K106: 19401840 | R106: 월 1,616,820원 · 합계의 4.7%
B107: ④ 기업이윤 · 단수조정 (연간) | K107: 7807824 | R107: 월 650,652원 · 합계의 1.9%
B108: 도급비 합계 ①+②+③+④ (연간 · VAT 별도) | K108: =SUM(K104:K107) -> 415236000 | R108: = 견적서 계약기간 총액 (월 34,603,000원 × 12)
B109: 월 도급비 (연간 ÷ 12) = 견적서 월 합계 | K109: =K108/12 -> 34603000 | R109: 견적서 시트 월 합계(I31)와 같음
B110: 검증: 견적서 연 총액 · 차이 | K110: ='2. 견적서'!I34 -> 415236000 | L110: =K108-K110 -> 0 | R110: L열 = 차이 (- 는 0원, 일치)
B112: Work scope = 업무별 연간 업무시간을 평일·주말·공휴일 및 주간(06~22시)·야간(22~06시)으로 나눈 값입니다. 24시간 상주는 야간 8시간, 이름에 ‘야간’이 있는 업무는 전부 야간으로 봅니다.
B113: Amount = 업무별 노무비(직접+간접) 연간 배분액을 같은 비율로 나눈 금액이며, 경비·일반관리비·이윤을 더한 도급비 합계는 견적서 계약기간 총액과 같습니다.
B114: Produced by RatRae Choi – October 21, 2026 · Workload-Based Cost and Labor Estimation Method v1.17

Sheet 5. 산출내역서
D1: 2027년 공장 ○○사업장 산출내역서 | H1: No. 261029-0425
H2: 작성일 2026. 10. 29
D3: 보안용역 도급업무 · 용역기간 2027. 1. 1 ~ 2027. 12. 31 (12개월) · 단위: 원, VAT 별도 · 노란 칸 = 입력값(수정 시 자동 재계산) · 산출 기준은 인력별(열별)로 따로 적용
A7: 구 분 | C7: 보안 | D7: 보안 | F7: 월간총액 | G7: 평균단가 | H7: 계약기간 계 | I7: 산출 근거 (수식)
C8: 경비원 | D8: 단시간 경비원
C9: 주간 주5일 (8h/일) | D9: 단시간 (주 29.5h)
A10: 기초자료 | B10: 인원(명) | C10: 10 | D10: 1 | E10: 0 | F10: =SUM(C10:E10) -> 11 | I10: 입력값
B11: 시급 | C11: 10700 | D11: 10700 | E11: 10700 | I11: 입력값
B12: 기본시간(주휴포함) | C12: 209 | D12: 154 | E12: 209 | I12: 입력값
B13: 연장근로시간 (실제) | C13: 0 | D13: 0 | E13: 0 | I13: 입력값
B14: 감시단속(1=승인) | C14: 0 | D14: 0 | E14: 0 | I14: 입력값
B15: 야간근로시간 (실제) | C15: 0 | D15: 0 | E15: 0 | I15: 입력값
B16: 공휴일근무(일/년) | C16: 0 | D16: 0 | E16: 0 | I16: 입력값
B17: 연차적치일수 | C17: 16 | D17: 16 | E17: 16 | I17: 입력값
B18: 상여율(연, 기본급 대비) | C18: 0 | D18: 0 | E18: 0 | I18: 입력값
B19: 상여 기준(0=기본급,1=통상임금) | C19: 0 | D19: 0 | E19: 0 | I19: 입력값
B20: 상여 월정액(0이면 상여율) | C20: 0 | D20: 0 | E20: 0 | I20: 입력값
B21: 근로자의날 유급시간 | C21: 8 | D21: 8 | E21: 8 | I21: 입력값
B22: 퇴직충당금(1=반영) | C22: 1 | D22: 1 | E22: 1 | I22: 입력값
... B27: 연간 근무개월 | C27: 12 | D27: 12 | E27: 12 | I27: 입력값
B28: 연장 환산시간 (가산 포함) | C28: =C13*IF(C14=1,C$87,C$86) -> 0 | D28: =D13*IF(D14=1,D$87,D$86) -> 0 | E28: =E13*IF(E14=1,E$87,E$86) -> 0 | I28: 연장근로시간 × 가산배율(감시단속 승인 시 감시단속 배율)
B29: 야간가산 환산시간 | C29: =C15*C$88 -> 0 | D29: =D15*D$88 -> 0 | E29: =E15*E$88 -> 0 | I29: 야간근로시간 × 야간 가산율
B30: 공휴일 환산시간 (월) | C30: =C16*8*0.5/12 -> 0 | D30: =D16*8*0.5/12 -> 0 | E30: =E16*8*0.5/12 -> 0 | I30: 공휴일 일수 × 8h × 50% ÷ 12
B31: 통상시급 | C31: =IF(C12=0,0,(C32+C39+C38+C36)/C12) -> 10700 | D31: =IF(D12=0,0,(D32+D39+D38+D36)/D12) -> 10700 | E31: =IF(E12=0,0,(E32+E39+E38+E36)/E12) -> 10700 | I31: (기본급여+직책+조정+직무) ÷ 기본시간
A32: 직접인건비 | B32: 기본급여 | C32: =ROUNDUP(C12*C11,-1) -> 2236300 | D32: =ROUNDUP(D12*D11,-1) -> 1647800 | E32: =ROUNDUP(E12*E11,-1) -> 2236300 | F32: =SUMPRODUCT(C32:E32,C10:E10) -> 24010800 | G32: =IF($C$118=0,0,F32/$C$118) -> 2182800 | H32: =SUMPRODUCT(C32:E32,C10:E10,C27:E27) -> 288129600 | I32: ROUNDUP(시급 × 기본시간, -1)
B33: 시간외 수당 | C33: =IF(C28=0,0,ROUNDUP(C28*C31,-1)) -> 0 | D33: =IF(D28=0,0,ROUNDUP(D28*D31,-1)) -> 0 | E33: =IF(E28=0,0,ROUNDUP(E28*E31,-1)) -> 0 | F33: =SUMPRODUCT(C33:E33,C10:E10) -> 0 | G33: =IF($C$118=0,0,F33/$C$118) -> 0 | H33: =SUMPRODUCT(C33:E33,C10:E10,C27:E27) -> 0 | I33: ROUNDUP(연장 환산시간 × 통상시급, -1)
B34: 야간가산수당 | C34: =IF(C29=0,0,ROUNDUP(C29*C31,-1)) -> 0 | D34: =IF(D29=0,0,ROUNDUP(D29*D31,-1)) -> 0 | E34: =IF(E29=0,0,ROUNDUP(E29*E31,-1)) -> 0 | F34: =SUMPRODUCT(C34:E34,C10:E10) -> 0 | G34: =IF($C$118=0,0,F34/$C$118) -> 0 | H34: =SUMPRODUCT(C34:E34,C10:E10,C27:E27) -> 0 | I34: ROUNDUP(야간가산 환산시간 × 통상시급, -1)
B35: 공휴일수당 | C35: =IF(C30=0,0,ROUNDUP(C30*C31,-1)) -> 0 | D35: =IF(D30=0,0,ROUNDUP(D30*D31,-1)) -> 0 | E35: =IF(E30=0,0,ROUNDUP(E30*E31,-1)) -> 0 | F35: =SUMPRODUCT(C35:E35,C10:E10) -> 0 | G35: =IF($C$118=0,0,F35/$C$118) -> 0 | H35: =SUMPRODUCT(C35:E35,C10:E10,C27:E27) -> 0 | I35: ROUNDUP(공휴일 환산시간 × 통상시급, -1)
B36: 직무수당 | C36: 0 | D36: 0 | E36: 0 | F36: =SUMPRODUCT(C36:E36,C10:E10) -> 0 | G36: =IF($C$118=0,0,F36/$C$118) -> 0 | H36: =SUMPRODUCT(C36:E36,C10:E10,C27:E27) -> 0
B37: 식대보조 | C37: 0 | D37: 0 | E37: 0 | F37: =SUMPRODUCT(C37:E37,C10:E10) -> 0 | G37: =IF($C$118=0,0,F37/$C$118) -> 0 | H37: =SUMPRODUCT(C37:E37,C10:E10,C27:E27) -> 0 | I37: 원본 항목명 · 식대(비과세)
B38: 조정수당 | C38: 0 | D38: 0 | E38: 0 | F38: =SUMPRODUCT(C38:E38,C10:E10) -> 0 | G38: =IF($C$118=0,0,F38/$C$118) -> 0 | H38: =SUMPRODUCT(C38:E38,C10:E10,C27:E27) -> 0
B39: 직책수당 | C39: 0 | D39: 0 | E39: 0 | F39: =SUMPRODUCT(C39:E39,C10:E10) -> 0 | G39: =IF($C$118=0,0,F39/$C$118) -> 0 | H39: =SUMPRODUCT(C39:E39,C10:E10,C27:E27) -> 0
B40: 소 계 | C40: =SUM(C32:C39) -> 2236300 | D40: =SUM(D32:D39) -> 1647800 | E40: =SUM(E32:E39) -> 2236300 | F40: =SUMPRODUCT(C40:E40,C10:E10) -> 24010800 | G40: =IF($C$118=0,0,F40/$C$118) -> 2182800 | H40: =SUMPRODUCT(C40:E40,C10:E10,C27:E27) -> 288129600 | I40: 기본급여 ~ 직책수당·기타수당 합계
B41: 연차수당 | C41: =ROUNDUP(C31*C$89*C17/12,-1) -> 114140 | D41: =ROUNDUP(D31*D$89*D17/12,-1) -> 114140 | E41: =ROUNDUP(E31*E$89*E17/12,-1) -> 114140 | F41: =SUMPRODUCT(C41:E41,C10:E10) -> 1255540 | G41: =IF($C$118=0,0,F41/$C$118) -> 114140 | H41: =SUMPRODUCT(C41:E41,C10:E10,C27:E27) -> 15066480 | I41: ROUNDUP(통상시급 × 연차1일시간 × 적치일수 ÷ 12, -1)
B42: 근로자의날 | C42: =ROUNDUP(C21/12*C31,-1) -> 7140 | D42: =ROUNDUP(D21/12*D31,-1) -> 7140 | E42: =ROUNDUP(E21/12*E31,-1) -> 7140 | F42: =SUMPRODUCT(C42:E42,C10:E10) -> 78540 | G42: =IF($C$118=0,0,F42/$C$118) -> 7140 | H42: =SUMPRODUCT(C42:E42,C10:E10,C27:E27) -> 942480 | I42: ROUNDUP(유급시간 ÷ 12 × 통상시급, -1)
B43: 상여급 | C43: =IF(C20>0,C20,IF(C18=0,0,ROUNDUP(IF(C19=1,C32+C39+C38+C36,C32)*C18/12,-1))) -> 0 | D43: =IF(D20>0,D20,IF(D18=0,0,ROUNDUP(IF(D19=1,D32+D39+D38+D36,D32)*D18/12,-1))) -> 0 | E43: =IF(E20>0,E20,IF(E18=0,0,ROUNDUP(IF(E19=1,E32+E39+E38+E36,E32)*E18/12,-1))) -> 0 | F43: =SUMPRODUCT(C43:E43,C10:E10) -> 0 | G43: =IF($C$118=0,0,F43/$C$118) -> 0 | H43: =SUMPRODUCT(C43:E43,C10:E10,C27:E27) -> 0 | I43: 월정액, 없으면 ROUNDUP(기본급(또는 통상임금) × 상여율 ÷ 12, -1)
B44: 퇴직충담금 | C44: =IF(C22=1,ROUNDUP((C40+C41+C42+C43)/12,-1),0) -> 196470 | D44: =IF(D22=1,ROUNDUP((D40+D41+D42+D43)/12,-1),0) -> 147430 | E44: =IF(E22=1,ROUNDUP((E40+E41+E42+E43)/12,-1),0) -> 196470 | F44: =SUMPRODUCT(C44:E44,C10:E10) -> 2112130 | G44: =IF($C$118=0,0,F44/$C$118) -> 192011.82 | H44: =SUMPRODUCT(C44:E44,C10:E10,C27:E27) -> 25345560 | I44: ROUNDUP((소계+연차+근로자의날+상여금) ÷ 12, -1)
B45: 직접비 계 ① | C45: =C40+C41+C42+C43+C44 -> 2554050 | D45: =D40+D41+D42+D43+D44 -> 1916510 | E45: =E40+E41+E42+E43+E44 -> 2554050 | F45: =SUMPRODUCT(C45:E45,C10:E10) -> 27457010 | G45: =IF($C$118=0,0,F45/$C$118) -> 2496091.8 | H45: =SUMPRODUCT(C45:E45,C10:E10,C27:E27) -> 329484120 | I45: 소계 + 연차 + 근로자의날 + 상여금 + 퇴직충당금
A46: 간접인건비 | B46: 건강보험료 | C46: =ROUNDUP((C45-C44-CHOOSE(C24+1,C37,C39,C39+C37,0))*C$79,-1) -> 84760 | D46: =ROUNDUP((D45-D44-CHOOSE(D24+1,D37,D39,D39+D37,0))*D$79,-1) -> 63600 | E46: =ROUNDUP((E45-E44-CHOOSE(E24+1,E37,E39,E39+E37,0))*E$79,-1) -> 84760 | F46: =SUMPRODUCT(C46:E46,C10:E10) -> 911200 | G46: =IF($C$118=0,0,F46/$C$118) -> 82836.364 | H46: =SUMPRODUCT(C46:E46,C10:E10,C27:E27) -> 10934400 | I46: ROUNDUP((직접비 계 − 퇴직충당금 − 제외항목) × 건강보험요율, -1)
B47: 노인장기요양보험 | C47: =ROUNDUP(C46*C$80,-1) -> 11140 | D47: =ROUNDUP(D46*D$80,-1) -> 8360 | E47: =ROUNDUP(E46*E$80,-1) -> 11140 | F47: =SUMPRODUCT(C47:E47,C10:E10) -> 119760 | G47: =IF($C$118=0,0,F47/$C$118) -> 10887.273 | H47: =SUMPRODUCT(C47:E47,C10:E10,C27:E27) -> 1437120 | I47: ROUNDUP(건강보험료 × 장기요양요율, -1)
B48: 국민연금 | C48: =ROUNDUP((C45-C44-CHOOSE(C24+1,C37,C39,C39+C37,0))*C$81*C23,-1) -> 117880 | D48: =ROUNDUP((D45-D44-CHOOSE(D24+1,D37,D39,D39+D37,0))*D$81*D23,-1) -> 88460 | E48: =ROUNDUP((E45-E44-CHOOSE(E24+1,E37,E39,E39+E37,0))*E$81*E23,-1) -> 117880 | F48: =SUMPRODUCT(C48:E48,C10:E10) -> 1267260 | G48: =IF($C$118=0,0,F48/$C$118) -> 115205.45 | H48: =SUMPRODUCT(C48:E48,C10:E10,C27:E27) -> 15207120 | I48: ROUNDUP((직접비−퇴직−제외항목) × 국민연금요율 × 적용률, -1)
B49: 고용보험료 | C49: =ROUNDUP((C45-C44-CHOOSE(C24+1,C37,C39,C39+C37,0))*C$82,-1) -> 43620 | D49: =ROUNDUP((D45-D44-CHOOSE(D24+1,D37,D39,D39+D37,0))*D$82,-1) -> 32730 | E49: =ROUNDUP((E45-E44-CHOOSE(E24+1,E37,E39,E39+E37,0))*E$82,-1) -> 43620 | F49: =SUMPRODUCT(C49:E49,C10:E10) -> 468930 | G49: =IF($C$118=0,0,F49/$C$118) -> 42630 | H49: =SUMPRODUCT(C49:E49,C10:E10,C27:E27) -> 5627160 | I49: ROUNDUP((직접비−퇴직−제외항목) × 고용보험요율, -1)
B50: 산재보험료 | C50: =ROUNDUP((C45-C44-CHOOSE(C24+1,C37,C39,C39+C37,0))*C$83,-1) -> 20280 | D50: =ROUNDUP((D45-D44-CHOOSE(D24+1,D37,D39,D39+D37,0))*D$83,-1) -> 15220 | E50: =ROUNDUP((E45-E44-CHOOSE(E24+1,E37,E39,E39+E37,0))*E$83,-1) -> 20280 | F50: =SUMPRODUCT(C50:E50,C10:E10) -> 218020 | G50: =IF($C$118=0,0,F50/$C$118) -> 19820 | H50: =SUMPRODUCT(C50:E50,C10:E10,C27:E27) -> 2616240 | I50: ROUNDUP((직접비−퇴직−제외항목) × 산재보험요율, -1)
B51: 임금채권부담금 | C51: =IF(C$84=0,0,ROUNDUP((C45-C44-CHOOSE(C24+1,C37,C39,C39+C37,0))*C$84,-1)) -> 2130 | D51: =IF(D$84=0,0,ROUNDUP((D45-D44-CHOOSE(D24+1,D37,D39,D39+D37,0))*D$84,-1)) -> 1600 | E51: =IF(E$84=0,0,ROUNDUP((E45-E44-CHOOSE(E24+1,E37,E39,E39+E37,0))*E$84,-1)) -> 2130 | F51: =SUMPRODUCT(C51:E51,C10:E10) -> 22900 | G51: =IF($C$118=0,0,F51/$C$118) -> 2081.8182 | H51: =SUMPRODUCT(C51:E51,C10:E10,C27:E27) -> 274800 | I51: ROUNDUP((직접비−퇴직−제외항목) × 임금채권요율, -1)
B52: 석면피해구제분담금 | C52: =IF(C$85=0,0,ROUNDUP((C45-C44-CHOOSE(C24+1,C37,C39,C39+C37,0))*C$85,-1)) -> 150 | D52: =IF(D$85=0,0,ROUNDUP((D45-D44-CHOOSE(D24+1,D37,D39,D39+D37,0))*D$85,-1)) -> 110 | E52: =IF(E$85=0,0,ROUNDUP((E45-E44-CHOOSE(E24+1,E37,E39,E39+E37,0))*E$85,-1)) -> 150 | F52: =SUMPRODUCT(C52:E52,C10:E10) -> 1610 | G52: =IF($C$118=0,0,F52/$C$118) -> 146.36364 | H52: =SUMPRODUCT(C52:E52,C10:E10,C27:E27) -> 19320 | I52: ROUNDUP((직접비−퇴직−제외항목) × 석면요율, -1)
B53: 특수검진 | C53: =IF(C25=1,ROUNDUP(C$90/12,-1),0) -> 7500 | D53: =IF(D25=1,ROUNDUP(D$90/12,-1),0) -> 7500 | E53: =IF(E25=1,ROUNDUP(E$90/12,-1),0) -> 7500 | F53: =SUMPRODUCT(C53:E53,C10:E10) -> 82500 | G53: =IF($C$118=0,0,F53/$C$118) -> 7500 | H53: =SUMPRODUCT(C53:E53,C10:E10,C27:E27) -> 990000 | I53: ROUNDUP(연 검진비 ÷ 12, -1)
B54: 장애인고용부담금 | C54: =IF(C$91=1,IF(C$95=1,ROUNDUP(C$92*C$93*C$94,-1),C$92*C$93*C$94),0) -> 40117.968 | D54: =IF(D$91=1,IF(D$95=1,ROUNDUP(D$92*D$93*D$94,-1),D$92*D$93*D$94),0) -> 40117.968 | E54: =IF(E$91=1,IF(E$95=1,ROUNDUP(E$92*E$93*E$94,-1),E$92*E$93*E$94),0) -> 40117.968 | F54: =SUMPRODUCT(C54:E54,C10:E10) -> 441297.65 | G54: =IF($C$118=0,0,F54/$C$118) -> 40117.968 | H54: =SUMPRODUCT(C54:E54,C10:E10,C27:E27) -> 5295571.8 | I54: 의무고용률 × 부담기초액 × 반영률 (10원 절상 선택)
B55: 간접비 계 ② | C55: =SUM(C46:C54) -> 327577.97 | D55: =SUM(D46:D54) -> 257697.97 | E55: =SUM(E46:E54) -> 327577.97 | F55: =SUMPRODUCT(C55:E55,C10:E10) -> 3533477.6 | G55: =IF($C$118=0,0,F55/$C$118) -> 321225.24 | H55: =SUMPRODUCT(C55:E55,C10:E10,C27:E27) -> 42401732 | I55: 건강보험 ~ 장애인부담금 합계
B56: 노무비 계 (1) | C56: =C45+C55 -> 2881628 | D56: =D45+D55 -> 2174208 | E56: =E45+E55 -> 2881628 | F56: =SUMPRODUCT(C56:E56,C10:E10) -> 30990488 | G56: =IF($C$118=0,0,F56/$C$118) -> 2817317.1 | H56: =SUMPRODUCT(C56:E56,C10:E10,C27:E27) -> 3.7188585e+08 | I56: 직접비 ① + 간접비 ②
A57: 경비 | B57: 피복장구비 | C57: 30000 | D57: 30000 | E57: 30000 | F57: =SUMPRODUCT(C57:E57,C10:E10) -> 330000 | G57: =IF($C$118=0,0,F57/$C$118) -> 30000 | H57: =SUMPRODUCT(C57:E57,C10:E10,C27:E27) -> 3960000
B58: 직원선물대 | C58: =IF(C$96=0,0,IF(C$97=1,ROUNDUP(C$96/12,-1),C$96/12)) -> 8333.3333 | D58: =IF(D$96=0,0,IF(D$97=1,ROUNDUP(D$96/12,-1),D$96/12)) -> 8333.3333 | E58: =IF(E$96=0,0,IF(E$97=1,ROUNDUP(E$96/12,-1),E$96/12)) -> 8333.3333 | F58: =SUMPRODUCT(C58:E58,C10:E10) -> 91666.667 | G58: =IF($C$118=0,0,F58/$C$118) -> 8333.3333 | H58: =SUMPRODUCT(C58:E58,C10:E10,C27:E27) -> 1100000 | I58: 명절선물 ÷ 12 (10원 절상 선택)
B59: 사업장운영비 | C59: =C$98 -> 10000 | D59: =D$98 -> 10000 | E59: =E$98 -> 10000 | F59: =SUMPRODUCT(C59:E59,C10:E10) -> 110000 | G59: =IF($C$118=0,0,F59/$C$118) -> 10000 | H59: =SUMPRODUCT(C59:E59,C10:E10,C27:E27) -> 1320000 | I59: 원본 항목명 · 직원회의비
B60: 경조비 | C60: =C$99 -> 3000 | D60: =D$99 -> 3000 | E60: =E$99 -> 3000 | F60: =SUMPRODUCT(C60:E60,C10:E10) -> 33000 | G60: =IF($C$118=0,0,F60/$C$118) -> 3000 | H60: =SUMPRODUCT(C60:E60,C10:E10,C27:E27) -> 396000
B61: 대치근무비 | C61: =C31*C$100*C$101/12 -> 8560 | D61: =D31*D$100*D$101/12 -> 8560 | E61: =E31*E$100*E$101/12 -> 8560 | F61: =SUMPRODUCT(C61:E61,C10:E10) -> 94160 | G61: =IF($C$118=0,0,F61/$C$118) -> 8560 | H61: =SUMPRODUCT(C61:E61,C10:E10,C27:E27) -> 1129920 | I61: 통상시급 × 기준시간 × 대치일수 ÷ 12
B62: 주민세(사업소분) | C62: =IF($C$118=0,0,C$102*C$103/12/$C$118) -> 416.66667 | D62: =IF($C$118=0,0,D$102*D$103/12/$C$118) -> 416.66667 | E62: =IF($C$118=0,0,E$102*E$103/12/$C$118) -> 416.66667 | F62: =SUMPRODUCT(C62:E62,C10:E10) -> 4583.3333 | G62: =IF($C$118=0,0,F62/$C$118) -> 416.66667 | H62: =SUMPRODUCT(C62:E62,C10:E10,C27:E27) -> 55000 | I62: 주민세 × 개소 ÷ 12 ÷ 총인원
B63: 교육훈련비 | C63: =IF(C$105>0,C$105,IF(C$106=1,ROUNDDOWN(C56*C$104,-1),C56*C$104)) -> 48980 | D63: =IF(D$105>0,D$105,IF(D$106=1,ROUNDDOWN(D56*D$104,-1),D56*D$104)) -> 36960 | E63: =IF(E$105>0,E$105,IF(E$106=1,ROUNDDOWN(E56*E$104,-1),E56*E$104)) -> 48980 | F63: =SUMPRODUCT(C63:E63,C10:E10) -> 526760 | G63: =IF($C$118=0,0,F63/$C$118) -> 47887.273 | H63: =SUMPRODUCT(C63:E63,C10:E10,C27:E27) -> 6321120 | I63: 고정액 또는 노무비 × 교육훈련비율 (10원 절사 선택)
B64: 위험부담금 | C64: =IF(C$108>0,C$108,IF(C$109=1,ROUNDDOWN(C56*C$107,-1),C56*C$107)) -> 14400 | D64: =IF(D$108>0,D$108,IF(D$109=1,ROUNDDOWN(D56*D$107,-1),D56*D$107)) -> 10870 | E64: =IF(E$108>0,E$108,IF(E$109=1,ROUNDDOWN(E56*E$107,-1),E56*E$107)) -> 14400 | F64: =SUMPRODUCT(C64:E64,C10:E10) -> 154870 | G64: =IF($C$118=0,0,F64/$C$118) -> 14079.091 | H64: =SUMPRODUCT(C64:E64,C10:E10,C27:E27) -> 1858440 | I64: 고정액 또는 노무비 × 위험부담율 (10원 절사 선택)
B65: 청소용품비 | C65: 0 | D65: 0 | E65: 0 | F65: =SUMPRODUCT(C65:E65,C10:E10) -> 0 | G65: =IF($C$118=0,0,F65/$C$118) -> 0 | H65: =SUMPRODUCT(C65:E65,C10:E10,C27:E27) -> 0 | I65: 제비용 · 기타 · 월정액(인당, 입력값)
B66: 부대비용 배분 | C66: =IF(OR($C$119=0,C26=1,$C$121=0),0,$C$120/$C$121) -> 0 | D66: =IF(OR($C$119=0,D26=1,$C$121=0),0,$C$120/$C$121) -> 0 | E66: =IF(OR($C$119=0,E26=1,$C$121=0),0,$C$120/$C$121) -> 0 | F66: =SUMPRODUCT(C66:E66,C10:E10) -> 0 | G66: =IF($C$118=0,0,F66/$C$118) -> 0 | H66: =SUMPRODUCT(C66:E66,C10:E10,C27:E27) -> 0 | I66: 부대비용 월계 ÷ 배분 인원
B67: 경비 계 (2) | C67: =SUM(C57:C66) -> 123690 | D67: =SUM(D57:D66) -> 108140 | E67: =SUM(E57:E66) -> 123690 | F67: =SUMPRODUCT(C67:E67,C10:E10) -> 1345040 | G67: =IF($C$118=0,0,F67/$C$118) -> 122276.36 | H67: =SUMPRODUCT(C67:E67,C10:E10,C27:E27) -> 16140480 | I67: 피복 ~ 부대비용 합계
A68: 원가 | B68: 1. 직접원가 | C68: =C56+C67 -> 3005318 | D68: =D56+D67 -> 2282348 | E68: =E56+E67 -> 3005318 | F68: =SUMPRODUCT(C68:E68,C10:E10) -> 32335528 | G68: =IF($C$118=0,0,F68/$C$118) -> 2939593.4 | H68: =SUMPRODUCT(C68:E68,C10:E10,C27:E27) -> 3.8802633e+08 | I68: 노무비 (1) + 경비 (2)
B69: 2. 일반관리비 | C69: =IF(C$111=1,ROUNDUP(C68*C$110,-1),C68*C$110) -> 150270 | D69: =IF(D$111=1,ROUNDUP(D68*D$110,-1),D68*D$110) -> 114120 | E69: =IF(E$111=1,ROUNDUP(E68*E$110,-1),E68*E$110) -> 150270 | F69: =SUMPRODUCT(C69:E69,C10:E10) -> 1616820 | G69: =IF($C$118=0,0,F69/$C$118) -> 146983.64 | H69: =SUMPRODUCT(C69:E69,C10:E10,C27:E27) -> 19401840 | I69: 직접원가 × 일반관리비율
B70: 3. 원가소계 | C70: =C68+C69 -> 3155588 | D70: =D68+D69 -> 2396468 | E70: =E68+E69 -> 3155588 | F70: =SUMPRODUCT(C70:E70,C10:E10) -> 33952348 | G70: =IF($C$118=0,0,F70/$C$118) -> 3086577.1 | H70: =SUMPRODUCT(C70:E70,C10:E10,C27:E27) -> 4.0742817e+08 | I70: 직접원가 + 일반관리비
B71: 4. 기업이윤 | C71: =IF(C$113=1,C70,C68)*C$112 -> 60106.359 | D71: =IF(D$113=1,D70,D68)*D$112 -> 45646.959 | E71: =IF(E$113=1,E70,E68)*E$112 -> 60106.359 | F71: =SUMPRODUCT(C71:E71,C10:E10) -> 646710.55 | G71: =IF($C$118=0,0,F71/$C$118) -> 58791.868 | H71: =SUMPRODUCT(C71:E71,C10:E10,C27:E27) -> 7760526.6 | I71: 직접원가(또는 원가소계) × 이윤율
B72: 5. 원가총계 | C72: =C70+C71 -> 3215694.3 | D72: =D70+D71 -> 2442114.9 | E72: =E70+E71 -> 3215694.3 | F72: =SUMPRODUCT(C72:E72,C10:E10) -> 34599058 | G72: =IF($C$118=0,0,F72/$C$118) -> 3145368.9 | H72: =SUMPRODUCT(C72:E72,C10:E10,C27:E27) -> 4.151887e+08 | I72: 원가소계 + 기업이윤
B73: 6. 견적금액(인당) | C73: =CHOOSE(C$114+1,ROUNDDOWN(C72,-3),ROUNDUP(C72,-3),ROUNDDOWN(C72,-2),ROUND(C72,0),ROUND(C72,-3)) -> 3216000 | D73: =CHOOSE(D$114+1,ROUNDDOWN(D72,-3),ROUNDUP(D72,-3),ROUNDDOWN(D72,-2),ROUND(D72,0),ROUND(D72,-3)) -> 2443000 | E73: =CHOOSE(E$114+1,ROUNDDOWN(E72,-3),ROUNDUP(E72,-3),ROUNDDOWN(E72,-2),ROUND(E72,0),ROUND(E72,-3)) -> 3216000 | F73: =SUMPRODUCT(C73:E73,C10:E10) -> 34603000 | G73: =IF($C$118=0,0,F73/$C$118) -> 3145727.3 | H73: =SUMPRODUCT(C73:E73,C10:E10,C27:E27) -> 415236000 | I73: 원가총계 단수처리(개인별 산출기준)
A76: ■ 산출 기준 (2027년 · 사업주 부담 · 인력별) — 노란 칸을 고치면 그 열(인력)의 산출내역만 다시 계산됩니다
B77: 항목 | C77: 경비원 | D77: 단시간 경비원 | F77: 비고
B78: 최저시급 (시간당) · 참고 | C78: 10700 | D78: 10700 | E78: 10700 | F78: 원 · 2027년 · 에스텍시스템 기준 · 법정 요율
B79: 건강보험 | C79: 0.03595 | D79: 0.03595 | E79: 0.03595 | F79: 사업주분 · 에스텍시스템 기준 · 법정 요율
B80: 노인장기요양 (건보료 대비) | C80: 0.1314 | D80: 0.1314 | E80: 0.1314
B81: 국민연금 | C81: 0.05 | D81: 0.05 | E81: 0.05
B82: 고용보험 | C82: 0.0185 | D82: 0.0185 | E82: 0.0185 | F82: 에스텍시스템 기준 · 실업급여 + 고용안정·직능(1,000인 이상 0.85%)
B83: 산재보험 | C83: 0.0086 | D83: 0.0086 | E83: 0.0086 | F83: 에스텍시스템 기준 · 시설관리·사업지원 0.8% + 출퇴근재해
B84: 임금채권부담금 | C84: 0.0009 | D84: 0.0009 | E84: 0.0009 | F84: 0이면 미반영
B85: 석면피해구제분담금 | C85: 6e-05 | D85: 6e-05 | E85: 6e-05 | F85: 0이면 미반영
B86: 연장 가산배율 (일반) | C86: 1.5 | D86: 1.5 | E86: 1.5 | F86: 연장 환산시간 = 시간 × 배율
B87: 연장 배율 (감시단속) | C87: 1 | D87: 1 | E87: 1
B88: 야간 가산율 | C88: 0.5 | D88: 0.5 | E88: 0.5 | F88: 야간 환산시간 = 시간 × 가산율
B89: 연차 1일 시간 | C89: 8 | D89: 8 | E89: 8
B90: 특수건강검진 (연/인) | C90: 90000 | D90: 90000 | E90: 90000
B91: 장애인부담금 반영 (1=반영) | C91: 1 | D91: 1 | E91: 1
B92: 장애인 의무고용률 | C92: 0.031 | D92: 0.031 | E92: 0.031
B93: 부담기초액 | C93: 1294128 | D93: 1294128 | E93: 1294128
B94: 부담금 반영률 | C94: 1 | D94: 1 | E94: 1
B95: 장애인부담금 10원 절상 (1=예) | C95: 0 | D95: 0 | E95: 0
B96: 명절선물대 (연/인) | C96: 100000 | D96: 100000 | E96: 100000
B97: 선물대 10원 절상 (1=예) | C97: 0 | D97: 0 | E97: 0
B98: 직원회의비 (월) | C98: 10000 | D98: 10000 | E98: 10000 | F98: 원본 항목명: 사업장운영비
B99: 경조비 (월) | C99: 3000 | D99: 3000 | E99: 3000
B100: 대치근무 기준시간 | C100: 12 | D100: 12 | E100: 12
B101: 대치근무 일수 (연) | C101: 0.8 | D101: 0.8 | E101: 0.8
B102: 주민세 사업소분 (연) | C102: 55000 | D102: 55000 | E102: 55000
B103: 주민세 개소 수 | C103: 1 | D103: 1 | E103: 1
B104: 교육훈련비율 (노무비 대비) | C104: 0.017 | D104: 0.017 | E104: 0.017
B105: 교육훈련비 고정액 | C105: 0 | D105: 0 | E105: 0 | F105: 0이면 비율 적용
B106: 교육훈련비 10원 절사 (1=예) | C106: 1 | D106: 1 | E106: 1
B107: 위험부담율 (노무비 대비) | C107: 0.005 | D107: 0.005 | E107: 0.005
B108: 위험부담금 고정액 | C108: 0 | D108: 0 | E108: 0 | F108: 0이면 비율 적용
B109: 위험부담금 10원 절사 (1=예) | C109: 1 | D109: 1 | E109: 1
...

Sheet 6. 부대비용
B1: 부대비용 산출 명세 | E1: No. 261029-0425
E2: 작성일 2026. 10. 29
B3: 공장 ○○사업장 · 반영방식 인당 단가 균등 배분 · 단위: 원, VAT 별도 · 노란 칸 = 입력값(고치면 월 금액·산출내역서가 다시 계산)
A7: 구분 | B7: 항목 | C7: 입력값 | D7: 월 금액 | E7: 산출 근거
A8: 반영된 부대비용이 없습니다. (차량·장비·기타를 추가하면 여기에 항목별로 산출됩니다)
A10: 합계 | B10: 부대비용 월계 (차량 + 장비 + 기타) | D10: =0 -> 0 | E10: → 산출내역서 ‘부대비용 월계’와 연결
B11: 인당 배분액 (배분 대상 인원) | D11: =IF(11=0,0,D10/11) -> 0 | E11: 11명에게 균등 배분 — 산출내역서 ‘부대비용 배분’ 행

Sheet _stec_data
A1: {"meta":{"client":"공장 ○○사업장","addr":"","svc":"보안용역 도급업무","year":2027,"valid":"작성일로부터 1개월","mode":"new","grpCo":"에스텍베스트","date":"2026-10-29"},"roles":[{"rank":"경비원","title":"경비원","count":10,"wage":10700,"base":209,"ot":0,"night":0,"note":""},{"rank":"단시간 경비원","title":"단시간 경비원","count":1,"wage":10700,"base":154,"ot":0,"night":0,"note":""},{"rank":"","title":"","count":0,"wage":10700,"base":209,"ot":0,"night":0,"note":""}],"wbe":{"v":"1.6","mode":"A","ind":"factory","job":"sec","year":2027,"H":1752.4,"fte":10.73,"tree":[{"id":"n27","name":"출입통제","kids":[{"id":"n18","name":"정문 초소","kids":[{"id":"n1","name":"정문 상주 근무 (24시간 경계·대기)","kids":[],"t":{"min":1440,"qty":1,"unit":"개소","freq":1,"per":"d","type":"post","g":"C"}},{"id":"n6","name":"차량 출입관리","kids":[{"id":"n2","name":"입문 차량 확인·출입 기록","kids":[],"t":{"min":0.5,"qty":108,"unit":"대","freq":1,"per":"d","type":"work","g":"C"}},{"id":"n3","name":"출문 차량 적재물 확인","kids":[],"t":{"min":1,"qty":54,"unit":"대","freq":1,"per":"d","type":"work","g":"C"}},{"id":"n4","name":"협력업체·납품차량 출입 통제","kids":[],"t":{"min":3,"qty":18,"unit":"대","freq":1,"per":"d","type":"work","g":"C"}},{"id":"n5","name":"긴급·관공서 차량 우선 통행 안내","kids":[],"t":{"min":3,"qty":2,"unit":"대","freq":1,"per":"d","type":"work","g":"C"}}],"t":{"min":0,"qty":1,"unit":"회","freq":1,"per":"d","type":"work","g":"C"}},{"id":"n10","name":"방문객 관리","kids":[{"id":"n7","name":"방문객 신원확인·출입증 발급","kids":[],"t":{"min":2,"qty":60,"unit":"명","freq":1,"per":"d","type":"work","g":"C"}},{"id":"n8","name":"출입증 회수·방문 대장 정리","kids":[],"t":{"min":0.5,"qty":60,"unit":"명","freq":1,"per":"d","type":"work","g":"C"}},{"id":"n9","name":"사전 방문예약 확인·접견자 연락","kids":[],"t":{"min":1,"qty":24,"unit":"건","freq":1,"per":"d","type":"work","g":"C"}}],"t":{"min":0,"qty":1,"unit":"회","freq":1,"per":"d","type":"work","g":"C"}},{"id":"n13","name":"물품 반출입 관리","kids":[{"id":"n11","name":"반출입증 확인·물품 대조","kids":[],"t":{"min":3,"qty":14,"unit":"건","freq":1,"per":"d","type":"work","g":"C"}},{"id":"n12","name":"반입 금지물품(화기·위험물) 검색","kids":[],"t":{"min":1,"qty":60,"unit":"명","freq":1,"per":"d","type":"work","g":"C"}}],"t":{"min":0,"qty":1,"unit":"회","freq":1,"per":"d","type":"work","g":"C"}},{"id":"n17","name":"택배·우편 관리","kids":[{"id":"n14","name":"택배 수령·보관 등록","kids":[],"t":{"min":1,"qty":40,"unit":"건","freq":1,"per":"d","type":"work","g":"C"}},{"id":"n15","name":"수령자 연락·인계 확인","kids":[],"t":{"min":0.7,"qty":40,"unit":"건","freq":1,"per":"d","type":"work","g":"C"}},{"id":"n16","name":"등기·우편물 분류","kids":[],"t":{"min":0.5,"qty":12,"unit":"건","freq":1,"per":"d","type":"work","g":"C"}}],"t":{"min":0,"qty":1,"unit":"회","freq":1,"per":"d","type":"work","g":"C"}}],"t":{"min":0,"qty":1,"unit":"회","freq":1,"per":"d","type":"work","g":"C"}},{"id":"n22","name":"후문·부출입구","kids":[{"id":"n19","name":"후문 주간 상주 (07~19시)","kids":[],"t":{"min":720,"qty":1,"unit":"개소","freq":5,"per":"w","type":"post","g":"C"}},{"id":"n20","name":"출퇴근 시간 출입 통제","kids":[],"t":{"min":30,"qty":1,"unit":"개소","freq":10,"per":"w","type":"work","g":"C"}},{"id":"n21","name":"야간 출입문 시건·개방","kids":[],"t":{"min":10,"qty":1,"unit":"개소","freq":2,"per":"d","type":"work","g":"C"}}],"t":{"min":0,"qty":1,"unit":"회","freq":1,"per":"d","type":"work","g":"C"}},{"id":"n26","name":"출입보안시스템","kids":[{"id":"n23","name":"출입카드 발급·회수·분실 처리","kids":[],"t":{"min":5,"qty":10,"unit":"건","freq":1,"per":"w","type":"work","g":"C"}},{"id":"n24","name":"출입기록 확인·이상 출입 조치","kids":[],"t":{"min":15,"qty":1,"unit":"회","freq":1,"per":"d","type":"work","g":"C"}},{"id":"n25","name":"스피드게이트·출입통제기 작동 확인","kids":[],"t":{"min":5,"qty":2,"unit":"대","freq":1,"per":"d","type":"work","g":"C"}}],"t":{"min":0,"qty":1,"unit":"회","freq":1,"per":"d","type":"work","g":"C"}}],"t":{"min":0,"qty":1,"unit":"회","freq":1,"per":"d","type":"work","g":"C"}},{"id":"n37","name":"순찰","kids":[{"id":"n32","name":"정기순찰","kids":[{"id":"n28","name":"외곽 울타리·담장 순찰","kids":[],"t":{"min":30,"qty":2,"unit":"구역","freq":4,"per":"d","type":"work","g":"C"}},{"id":"n29","name":"건물 내부 층별 순찰","kids":[],"t":{"min":5,"qty":18,"unit":"층","freq":2,"per":"d","type":"work","g":"C"}},{"id":"n30","name":"주차장 순찰","kids":[],"t":{"min":8,"qty":3,"unit":"구역","freq":3,"per":"d","type":"work","g":"C"}},{"id":"n31","name":"야간 문단속·소등·전열기구 확인","kids":[],"t":{"min":3,"qty":18,"unit":"층","freq":1,"per":"d","type":"work","g":"C"}}],"t":{"min":0,"qty":1,"unit":"회","freq":1,"per":"d","type":"work","g":"C"}},{"id":"n36","name":"특별순찰","kids":[{"id":"n33","name":"취약지역·사각지대 집중 순찰","kids":[],"t":{"min":20,"qty":3,"unit":"개소","freq":2,"per":"d","type":"work","g":"C"}},{"id":"n34","name":"휴일·공휴일 전수 점검","kids":[],"t":{"min":30,"qty":6,"unit":"동","freq":8,"per":"m","type":"work","g":"C"}},{"id":"n35","name":"기상특보(태풍·폭우·폭설) 비상 순찰","kids":[],"t":{"min":60,"qty":6,"unit":"동","freq":4,"per":"y","type":"work","g":"C"}}],"t":{"min":0,"qty":1,"unit":"회","freq":1,"per":"d","type":"work","g":"C"}}],"t":{"min":0,"qty":1,"unit":"회","freq":1,"per":"d","type":"work","g":"C"}},{"id":"n67","name":"상황대처","kids":[{"id":"n42","name":"화재·소방","kids":[{"id":"n38","name":"화재경보 발생 시 현장 출동·확인","kids":[],"t":{"min":15,"qty":1,"unit":"건","freq":6,"per":"m","type":"work","g":"C"}},{"id":"n39","name":"비화재보 복구·수신기 리셋","kids":[],"t":{"min":10,"qty":1,"unit":"건","freq":4,"per":"m","type":"work","g":"C"}},{"id":"n40","name":"초기 소화·피난 유도","kids":[],"t":{"min":60,"qty":1,"unit":"건","freq":1,"per":"y","type":"work","g":"C"}},{"id":"n41","name":"소방서 신고·소방차 진입 안내","kids":[],"t":{"min":20,"qty":1,"unit":"건","freq":1,"per":"q","type":"work","g":"C"}}],"t":{"min":0,"qty":1,"unit":"회","freq":1,"per":"d","type":"work","g":"C"}},{"id":"n48","name":"응급·안전사고","kids":[{"id":"n43","name":"응급환자 응급조치·119 신고·인계","kids":[],"t":{"min":30,"qty":1,"unit":"건","freq":1,"per":"m","type":"work","g":"C"}},{"id":"n44","name":"AED·구급함 점검","kids":[],"t":{"min":5,"qty":6,"unit":"개소","freq":1,"per":"m","type":"work","g":"C"}},{"id":"n45","name":"산업재해 발생 시 현장 통제·보고","kids":[],"t":{"min":60,"qty":1,"unit":"건","freq":2,"per":"y","type":"work","g":"C"}},{"id":"n46","name":"승강기 갇힘 사고 대응·구조 연계","kids":[],"t":{"min":30,"qty":1,"unit":"건","freq":1,"per":"m","type":"work","g":"C"}},{"id":"n47","name":"넘어짐·추락 사고 현장 조치","kids":[],"t":{"min":20,"qty":1,"unit":"건","freq":1,"per":"m","type":"work","g":"C"}}],"t":{"min":0,"qty":1,"unit":"회","freq":1,"per":"d","type":"work","g":"C"}},{"id":"n53","name":"침입·도난·범죄","kids":[{"id":"n49","name":"무단침입 발생 시 대응·경찰 신고","kids":[],"t":{"min":40,"qty":1,"unit":"건","freq":2,"per":"m","type":"work","g":"C"}},{"id":"n50","name":"도난·분실 신고 접수·조사 협조","kids":[],"t":{"min":30,"qty":1,"unit":"건","freq":1,"per":"m","type":"work","g":"C"}},{"id":"n51","name":"CCTV 영상 확인·증거 보존 지원","kids":[],"t":{"min":30,"qty":1,"unit":"건","freq":4,"per":"m","type":"work","g":"C"}},{"id":"n52","name":"수상한 물건·거동 수상자 확인","kids":[],"t":{"min":15,"qty":1,"unit":"건","freq":8,"per":"m","type":"work","g":"C"}}],"t":{"min":0,"qty":1,"unit":"회","freq":1,"per":"d","type":"work","g":"C"}},{"id":"n58","name":"소란·민원·폭력","kids":[{"id":"n54","name":"소란·난동 발생 시 제지·분리","kids":[],"t":{"min":30,"qty":1,"unit":"건","freq":1,"per":"m","type":"work","g":"C"}},{"id":"n55","name":"주취자·노숙인 대응","kids":[],"t":{"min":20,"qty":1,"unit":"건","freq":1,"per":"m","type":"work","g":"C"}},{"id":"n56","name":"현장 민원 접수·응대","kids":[],"t":{"min":10,"qty":3,"unit":"건","freq":1,"per":"d","type":"work","g":"C"}},{"id":"n57","name":"집회·시위 발생 시 출입 통제","kids":[],"t":{"min":120,"qty":1,"unit":"건","freq":1,"per":"y","type":"work","g":"C"}}],"t":{"min":0,"qty":1,"unit":"회","freq":1,"per":"d","type":"work","g":"C"}},{"id":"n63","name":"설비 이상·재난","kids":[{"id":"n59","name":"정전 시 비상조명 확인·설비팀 연락","kids":[],"t":{"min":30,"qty":1,"unit":"건","freq":2,"per":"y","type":"work","g":"C"}},{"id":"n60","name":"누수·배관 파열 초동 조치","kids":[],"t":{"min":30,"qty":1,"unit":"건","freq":3,"per":"m","type":"work","g":"C"}},{"id":"n61","name":"가스·화학물질 누출 초동 조치","kids":[],"t":{"min":60,"qty":1,"unit":"건","freq":2,"per":"y","type":"work","g":"C"}},{"id":"n62","name":"태풍·폭우 대비 시설물 결박·배수구 점검","kids":[],"t":{"min":60,"qty":6,"unit":"동","freq":3,"per":"y","type":"work","g":"C"}}],"t":{"min":0,"qty":1,"unit":"회","freq":1,"per":"d","type":"work","g":"C"}},{"id":"n66","name":"교통·주차 사고","kids":[{"id":"n64","name":"구내 교통사고 현장 통제·보고","kids":[],"t":{"min":40,"qty":1,"unit":"건","freq":1,"per":"m","type":"work","g":"C"}},{"id":"n65","name":"통행 방해·불법주차 차량 조치","kids":[],"t":{"min":5,"qty":6,"unit":"건","freq":1,"per":"d","type":"work","g":"C"}}],"t":{"min":0,"qty":1,"unit":"회","freq":1,"per":"d","type":"work","g":"C"}}],"t":{"min":0,"qty":1,"unit":"회","freq":1,"per":"d","type":"work","g":"C"}},{"id":"n80","name":"관제·방재","kids":[{"id":"n71","name":"CCTV 관제","kids":[{"id":"n68","name":"CCTV 모니터링 (정문 초소 겸무)","kids":[],"t":{"min":10,"qty":1,"unit":"회","freq":6,"per":"d","type":"work","g":"C"}},{"id":"n69","name":"CCTV 녹화 상태·카메라 점검","kids":[],"t":{"min":1,"qty":120,"unit":"대","freq":1,"per":"w","type":"work","g":"C"}},{"id":"n70","name":"영상 열람·반출 요청 처리","kids":[],"t":{"min":30,"qty":1,"unit":"건","freq":4,"per":"m","type":"work","g":"C"}}],"t":{"min":0,"qty":1,"unit":"회","freq":1,"per":"d","type":"work","g":"C"}},{"id":"n75","name":"방재·설비 감시","kids":[{"id":"n72","name":"화재수신기·방재반 감시 기록","kids":[],"t":{"min":10,"qty":1,"unit":"회","freq":3,"per":"d","type":"work","g":"C"}},{"id":"n73","name":"무인경비·침입감지 알람 확인","kids":[],"t":{"min":10,"qty":1,"unit":"건","freq":2,"per":"d","type":"work","g":"C"}},{"id":"n74","name":"비상방송·안내방송 송출","kids":[],"t":{"min":5,"qty":1,"unit":"회","freq":1,"per":"d","type":"work","g":"C"}}],"t":{"min":0,"qty":1,"unit":"회","freq":1,"per":"d","type":"work","g":"C"}},{"id":"n79","name":"소방시설 일상점검","kids":[{"id":"n76","name":"소화기·옥내소화전 외관 점검","kids":[],"t":{"min":1,"qty":125,"unit":"개","freq":1,"per":"m","type":"work","g":"C"}},{"id":"n77","name":"방화문·피난통로 적치물 확인","kids":[],"t":{"min":2,"qty":18,"unit":"층","freq":1,"per":"w","type":"work","g":"C"}},{"id":"n78","name":"유도등·비상조명 점등 확인","kids":[],"t":{"min":0.5,"qty":72,"unit":"개","freq":1,"per":"m","type":"work","g":"C"}}],"t":{"min":0,"qty":1,"unit":"회","freq":1,"per":"d","type":"work","g":"C"}}],"t":{"min":0,"qty":1,"unit":"회","freq":1,"per":"d","type":"work","g":"C"}},{"id":"n96","name":"고객사 업무 지원","kids":[{"id":"n84","name":"안내·의전","kids":[{"id":"n81","name":"VIP·귀빈 영접 및 차량 안내","kids":[],"t":{"min":20,"qty":2,"unit":"건","freq":4,"per":"m","type":"work","g":"C"}},{"id":"n82","name":"회의·행사장 출입 통제","kids":[],"t":{"min":120,"qty":2,"unit":"회","freq":1,"per":"m","type":"work","g":"C"}},{"id":"n83","name":"행사 주차 안내·교통 정리","kids":[],"t":{"min":90,"qty":1,"unit":"회","freq":1,"per":"m","type":"work","g":"C"}}],"t":{"min":0,"qty":1,"unit":"회","freq":1,"per":"d","type":"work","g":"C"}},{"id":"n89","name":"행정 지원","kids":[{"id":"n85","name":"열쇠·출입카드 보관·대여 관리","kids":[],"t":{"min":2,"qty":20,"unit":"건","freq":1,"per":"d","type":"work","g":"C"}},{"id":"n86","name":"분실물·습득물 접수·보관·반환","kids":[],"t":{"min":5,"qty":2,"unit":"건","freq":1,"per":"d","type":"work","g":"C"}},{"id":"n87","name":"공지문·게시물 부착·회수","kids":[],"t":{"min":20,"qty":6,"unit":"동","freq":2,"per":"m","type":"work","g":"C"}},{"id":"n88","name":"고객사 요청 문서·물품 전달","kids":[],"t":{"min":15,"qty":2,"unit":"건","freq":1,"per":"d","type":"work","g":"C"}}],"t":{"min":0,"qty":1,"unit":"회","freq":1,"per":"d","type":"work","g":"C"}},{"id":"n92","name":"시설·환경 지원","kids":[{"id":"n90","name":"제설·염화칼슘 살포 지원","kids":[],"t":{"min":60,"qty":2,"unit":"구역","freq":3,"per":"y","type":"work","g":"C"}},{"id":"n91","name":"시설 고장 접수·설비팀 연계","kids":[],"t":{"min":10,"qty":2,"unit":"건","freq":1,"per":"d","type":"work","g":"C"}}],"t":{"min":0,"qty":1,"unit":"회","freq":1,"per":"d","type":"work","g":"C"}},{"id":"n95","name":"업종별 특수 지원","kids":[{"id":"n93","name":"출퇴근 통근버스 통제","kids":[],"t":{"min":30,"qty":2,"unit":"회","freq":5,"per":"w","type":"work","g":"C"}},{"id":"n94","name":"협력업체 작업허가서 확인","kids":[],"t":{"min":5,"qty":10,"unit":"건","freq":5,"per":"w","type":"work","g":"C"}}],"t":{"min":0,"qty":1,"unit":"회","freq":1,"per":"d","type":"work","g":"C"}}],"t":{"min":0,"qty":1,"unit":"회","freq":1,"per":"d","type":"work","g":"C"}},{"id":"n101","name":"보고·행정·교육","kids":[{"id":"n97","name":"근무일지·인수인계","kids":[],"t":{"min":15,"qty":2,"unit":"개소","freq":3,"per":"d","type":"work","g":"C"}},{"id":"n98","name":"사건·사고 보고서 작성","kids":[],"t":{"min":30,"qty":1,"unit":"건","freq":6,"per":"m","type":"work","g":"C"}},{"id":"n99","name":"고객사 일일 업무보고","kids":[],"t":{"min":20,"qty":1,"unit":"회","freq":1,"per":"d","type":"work","g":"C"}},{"id":"n100","name":"경비원 직무교육·소방훈련 참여","kids":[],"t":{"min":240,"qty":1,"unit":"회","freq":1,"per":"q","type":"work","g":"C"}}],"t":{"min":0,"qty":1,"unit":"회","freq":1,"per":"d","type":"work","g":"C"}}],"params":{"days":30.4,"allow":15,"week":40,"loss":6,"wage":10700,"otH":0,"nightH":0,"allowance":0,"bonus":0,"pension":5,"health":3.595,"ltc":13.14,"emp":1.85,"acc":0.86,"expense":430000,"mgmt":5,"profit":2,"weekMode":"auto","shift":"d5_8","v19":1,"plan":"precise","cFull":10,"cPartN":0,"cPartH":20}}} | B1: STEC-QUOTE v1 | C1: 12955
